Workbook

Sheet OVERVIEW
B1: OVERVIEW
A2: ITEM | B2: # TOTAL | C2: TOTAL COST VALUE | D2: # SOLD THIS MONTH | E2: SOLD RETAIL VALUE THIS MONTH | F2: # PENDING | G2: PENDING COST VALUE | H2: # AVAILABLE STOCK | I2: AVAILABLE STOCK VALUE
A3: Profit & Loss Explination
A4: STOCK
A5: TOTAL STOCK | B5: ='STOCK OVERVIEW'!B10 -> 2114 | C5: ='STOCK OVERVIEW'!C10 -> 2098139.5 | D5: ='TOTAL OFFICE STOCK'!C22 -> 360 | E5: ='TOTAL OFFICE STOCK'!G22 -> 224661.1 | F5: ='TOTAL OFFICE STOCK'!D22 -> 44 | G5: ='TOTAL OFFICE STOCK'!H22 -> 24677.5 | H5: ='TOTAL OFFICE STOCK'!E22 -> 650 | I5: ='TOTAL OFFICE STOCK'!I22 -> 449941.02
A6: COSTS
A7: FIXED COSTS THIS MONTH
A8: EXPENSES THIS MONTH
A9: MARKETING COSTS THIS MONTH
A10: INCOME
A11: INCOME THIS MONTH
A12: P&L
A13: PROFIT / LOSS THIS MONTH

Sheet STOCK OVERVIEW
A1: TOTAL STOCK OVERVIEW
A2: ITEM | B2: # TOTAL | C2: TOTAL COST VALUE | D2: # SOLD | E2: SOLD COST VALUE | F2: # PENDING | G2: PENDING COST VALUE | H2: # AVAILABLE STOCK | I2: AVAILABLE STOCK VALUE | J2: NET PROFIT AFTER COST
A3: ='TOTAL OFFICE STOCK'!A22 -> SILK TOTAL | B3: ='TOTAL OFFICE STOCK'!B22 -> 1054 | C3: ='TOTAL OFFICE STOCK'!F22 -> 699279.62 | D3: ='TOTAL OFFICE STOCK'!C22 -> 360 | E3: ='TOTAL OFFICE STOCK'!G22 -> 224661.1 | F3: ='TOTAL OFFICE STOCK'!D22 -> 44 | G3: ='TOTAL OFFICE STOCK'!H22 -> 24677.5 | H3: ='TOTAL OFFICE STOCK'!E22 -> 650 | I3: ='TOTAL OFFICE STOCK'!I22 -> 449941.02 | J3: ='SILK - SOLD'!K5 -> 210978.91
A4: ='TOTAL OFFICE STOCK'!A30 -> RICCIARINI CORD LACE (70) | B4: ='TOTAL OFFICE STOCK'!B30 -> 70 | C4: ='LACE - STOCK OVERVIEW'!E7 -> 9900 | D4: ='TOTAL OFFICE STOCK'!C30 -> 0 | E4: ='LACE - STOCK OVERVIEW'!G7 -> 0 | F4: ='TOTAL OFFICE STOCK'!D30 -> 0 | G4: ='TOTAL OFFICE STOCK'!H30 -> 0 | H4: ='TOTAL OFFICE STOCK'!E30 -> 70 | I4: ='TOTAL OFFICE STOCK'!I30 -> 9900
A5: ='TOTAL OFFICE STOCK'!A28 -> LACE TOTAL | B5: ='TOTAL OFFICE STOCK'!B28 -> 182 | C5: ='TOTAL OFFICE STOCK'!F28 -> 179314.59 | D5: ='TOTAL OFFICE STOCK'!C28 -> 51 | E5: ='TOTAL OFFICE STOCK'!G28 -> 48205.59 | F5: ='TOTAL OFFICE STOCK'!D28 -> 4 | G5: ='TOTAL OFFICE STOCK'!H28 -> 3405.5 | H5: ='TOTAL OFFICE STOCK'!E28 -> 127 | I5: ='TOTAL OFFICE STOCK'!I28 -> 127703.5
A6: ='TOTAL OFFICE STOCK'!A38 -> LACE (CEMB) TOTAL | B6: ='TOTAL OFFICE STOCK'!B38 -> 396 | C6: ='TOTAL OFFICE STOCK'!F38 -> 145857.8 | D6: ='TOTAL OFFICE STOCK'!C38 -> 32 | E6: ='TOTAL OFFICE STOCK'!G38 -> 13556.55 | F6: ='TOTAL OFFICE STOCK'!D38 -> 0 | G6: ='TOTAL OFFICE STOCK'!H38 -> 0 | H6: ='TOTAL OFFICE STOCK'!E38 -> 364 | I6: ='TOTAL OFFICE STOCK'!I38 -> 132301.25
A7: ='TOTAL OFFICE STOCK'!A43 -> BEIRUT TOTAL | B7: ='TOTAL OFFICE STOCK'!B43 -> 95 | C7: ='LACE - STOCK OVERVIEW'!E6 -> 135555 | D7: ='TOTAL OFFICE STOCK'!C43 -> 2 | E7: ='TOTAL OFFICE STOCK'!G43 -> 1920 | F7: ='TOTAL OFFICE STOCK'!D43 -> 0 | G7: ='TOTAL OFFICE STOCK'!H43 -> 0 | H7: ='TOTAL OFFICE STOCK'!E43 -> 93 | I7: ='TOTAL OFFICE STOCK'!I43 -> 136515
A8: ='TOTAL OFFICE STOCK'!A75 -> EMBROIDERY TOTAL | B8: ='TOTAL OFFICE STOCK'!B75 -> 317 | C8: ='EMBROIDERY - STOCK OVERVIEW'!F34 -> 928232.5 | D8: ='TOTAL OFFICE STOCK'!C75 -> 10 | E8: ='TOTAL OFFICE STOCK'!G75 -> 31825 | F8: ='TOTAL OFFICE STOCK'!D75 -> 0 | G8: ='TOTAL OFFICE STOCK'!H75 -> 0 | H8: ='TOTAL OFFICE STOCK'!E75 -> 307 | I8: ='TOTAL OFFICE STOCK'!I75 -> 911187.5
A10: TOTAL | B10: =SUM(B3:B9) -> 2114 | C10: =SUM(C3:C9) -> 2098139.5 | D10: =SUM(D3:D9) -> 455 | E10: =SUM(E3:E9) -> 320168.24 | F10: =SUM(F3:F9) -> 48 | G10: =SUM(G3:G9) -> 28083 | H10: =SUM(H3:H9) -> 1611 | I10: =SUM(I3:I9) -> 1767548.3 | J10: =SUM(J3:J9) -> 210978.91
A13: PENDING | B13: # TOTAL | C13: TOTAL COST VALUE
A15: TOTAL | B15: ='TOTAL OFFICE STOCK'!B91 -> 0 | C15: ='TOTAL OFFICE STOCK'!F91 -> 100906.03

Sheet TOTAL OFFICE STOCK
A1: OFFICE STOCK REPORT
A2: ITEM | B2: # TOTAL | C2: # SOLD | D2: # PENDING | E2: # AVAILABLE STOCK | F2: TOTAL COST VALUE | G2: SOLD COST VALUE | H2: PENDING COST VALUE | I2: AVAILABLE STOCK COST VALUE
A3: 1. SILK
A4: M&M 1-70 | B4: =E4+D4+C4 -> 139 | C4: ='SILK - SOLD'!C79 -> 65 | D4: ='SILK - PENDING'!D18 -> 4 | E4: =M7M_A[[#Totals],[QUALITY]] -> 70 | F4: =G4+H4+I4 -> 80224 | G4: ='SILK - SOLD'!K79 -> 37198 | H4: ='SILK - PENDING'!H18 -> 2778 | I4: ='SILK - ALL'!H83 -> 40248
A5: ARGOMENTI (ARGO) | B5: =E5+D5+C5 -> 122 | C5: ='SILK - SOLD'!C107 -> 21 | D5: ='SILK - PENDING'!D27 -> 0 | E5: =ARGO_A[[#Totals],[QUALITY]] -> 101 | F5: =G5+H5+I5 -> 91744 | G5: ='SILK - SOLD'!K107 -> 15636 | H5: ='SILK - PENDING'!H27 -> 0 | I5: ='SILK - ALL'!H189 -> 76108
A6: ALBERTI(ALB) | B6: =E6+D6+C6 -> 186 | C6: ='SILK - SOLD'!C171 -> 59 | D6: ='SILK - PENDING'!D37 -> 1 | E6: ='SILK - ALL'!D321 -> 126 | F6: =G6+H6+I6 -> 111639.87 | G6: ='SILK - SOLD'!K171 -> 34146.6 | H6: ='SILK - PENDING'!H37 -> 693 | I6: ='SILK - ALL'!H321 -> 76800.27
A7: MARITEX (MAR) | B7: =E7+D7+C7 -> 167 | C7: ='SILK - SOLD'!C267 -> 90 | D7: ='SILK - PENDING'!D46 -> 1 | E7: ='SILK - ALL'!D402 -> 76 | F7: =G7+H7+I7 -> 108447.75 | G7: ='SILK - SOLD'!K267 -> 58781 | H7: ='SILK - PENDING'!H46 -> 850 | I7: ='SILK - ALL'!H402 -> 48816.75
A8: NELLA | B8: =E8+D8+C8 -> 50 | C8: ='SILK - SOLD'!C281 -> 7 | D8: ='SILK - PENDING'!D57 -> 2 | E8: ='SILK - ALL'!D448 -> 41 | F8: =G8+H8+I8 -> 34150 | G8: ='SILK - SOLD'!K281 -> 4672 | H8: ='SILK - PENDING'!H57 -> 1400 | I8: ='SILK - ALL'!H448 -> 28078
A9: AVANTGARD (AVAN) | B9: =E9+D9+C9 -> 44 | C9: ='SILK - SOLD'!C300 -> 14 | D9: ='SILK - PENDING'!D65 -> 2 | E9: ='SILK - ALL'!D481 -> 28 | F9: =G9+H9+I9 -> 23225 | G9: ='SILK - SOLD'!K300 -> 7475 | H9: ='SILK - PENDING'!H65 -> 950 | I9: ='SILK - ALL'!H481 -> 14800
A10: CASA DELLO (CASA) | B10: =E10+D10+C10 -> 39 | C10: ='SILK - SOLD'!C330 -> 25 | D10: ='SILK - PENDING'!D75 -> 4 | E10: ='SILK - ALL'!D497 -> 10 | F10: =G10+H10+I10 -> 23382 | G10: ='SILK - SOLD'!K330 -> 15630 | H10: ='SILK - PENDING'!H75 -> 1920 | I10: ='SILK - ALL'!H497 -> 5832
A11: STYLE SILK (STYL) | B11: =E11+D11+C11 -> 46 | C11: ='SILK - SOLD'!C345 -> 9 | D11: ='SILK - PENDING'!D84 -> 4 | E11: =STYL_A[[#Totals],[QUALITY]] -> 33 | F11: =G11+H11+I11 -> 26672.5 | G11: ='SILK - SOLD'!K345 -> 5297.5 | H11: ='SILK - PENDING'!H84 -> 2225 | I11: ='SILK - ALL'!H535 -> 19150
A12: INCOMO (INCO) | B12: =E12+D12+C12 -> 20 | C12: ='SILK - SOLD'!C362 -> 12 | D12: ='SILK - PENDING'!D91 -> 1 | E12: ='SILK - ALL'!D547 -> 7 | F12: =G12+H12+I12 -> 11475 | G12: ='SILK - SOLD'!K362 -> 6675 | H12: ='SILK - PENDING'!H91 -> 500 | I12: ='SILK - ALL'!H547 -> 4300
A13: CARNET (UG) | B13: =E13+D13+C13 -> 26 | C13: ='SILK - SOLD'!C371 -> 3 | D13: ='SILK - PENDING'!D99 -> 0 | E13: =UG_A[[#Totals],[QUALITY]] -> 23 | F13: =G13+H13+I13 -> 20125 | G13: ='SILK - SOLD'!K371 -> 1750 | H13: ='SILK - PENDING'!H99 -> 0 | I13: ='SILK - ALL'!H575 -> 18375
A14: CAVALLI+TGM+ROTARY | B14: =E14+D14+C14 -> 11 | C14: ='SILK - SOLD'!C382 -> 5 | D14: ='SILK - PENDING'!D110 -> 1 | E14: ='SILK - ALL'!D586 -> 5 | F14: =G14+H14+I14 -> 11809 | G14: ='SILK - SOLD'!K382 -> 5128 | H14: ='SILK - PENDING'!H110 -> 880 | I14: ='SILK - ALL'!H586 -> 5801
A15: RUFFO (RUFF) | B15: =E15+D15+C15 -> 28 | C15: ='SILK - SOLD'!C389 -> 2 | D15: ='SILK - PENDING'!D118 -> 0 | E15: =RUFF_A[[#Totals],[QUALITY]] -> 26 | F15: =G15+H15+I15 -> 64450 | G15: ='SILK - SOLD'!K389 -> 5500 | H15: ='SILK - PENDING'!H118 -> 0 | I15: ='SILK - ALL'!H617 -> 58950
A16: SETERIE GR(SETE) | B16: =E16+D16+C16 -> 38 | C16: ='SILK - SOLD'!C400 -> 5 | D16: ='SILK - PENDING'!D125 -> 0 | E16: ='SILK - ALL'!D655 -> 33 | F16: =G16+H16+I16 -> 18345 | G16: ='SILK - SOLD'!K400 -> 3077 | H16: ='SILK - PENDING'!H125 -> 0 | I16: ='SILK - ALL'!H655 -> 15268
A17: TESSILE(TESSI) | B17: =E17+D17+C17 -> 31 | C17: ='SILK - SOLD'!C413 -> 8 | D17: ='SILK - PENDING'!D132 -> 1 | E17: ='SILK - ALL'!D682 -> 22 | F17: =G17+H17+I17 -> 16769.5 | G17: ='SILK - SOLD'!K413 -> 4660.5 | H17: ='SILK - PENDING'!H132 -> 522.5 | I17: ='SILK - ALL'!H682 -> 11586.5
A18: QUORUM(QUO) | B18: =E18+D18+C18 -> 24 | C18: ='SILK - SOLD'!C423 -> 1 | D18: ='SILK - PENDING'!D141 -> 3 | E18: ='SILK - ALL'!D707 -> 20 | F18: =G18+H18+I18 -> 12240 | G18: ='SILK - SOLD'!K423 -> 539 | H18: ='SILK - PENDING'!H141 -> 1650 | I18: ='SILK - ALL'!H707 -> 10051
A19: SILKOMO (SILKO) | B19: =E19+D19+C19 -> 24 | C19: ='SILK - SOLD'!C447 -> 13 | D19: ='SILK - PENDING'!D151 -> 5 | E19: ='SILK - ALL'!D718 -> 6 | F19: =G19+H19+I19 -> 13476 | G19: ='SILK - SOLD'!K447 -> 7590 | H19: ='SILK - PENDING'!H151 -> 2286 | I19: ='SILK - ALL'!H718 -> 3600
A20: NO CODE (NC) | B20: =E20+D20+C20 -> 59 | C20: ='SILK - SOLD'!C473 -> 21 | D20: ='SILK - PENDING'!D171 -> 15 | E20: ='SILK - ALL'!D746 -> 23 | F20: =G20+H20+I20 -> 31105 | G20: ='SILK - SOLD'!K473 -> 10905.5 | H20: ='SILK - PENDING'!H171 -> 8023 | I20: ='SILK - ALL'!H746 -> 12176.5
A22: SILK TOTAL | B22: =SUM(B4:B20) -> 1054 | C22: =SUM(C4:C20) -> 360 | D22: =SUM(D4:D20) -> 44 | E22: =SUM(E4:E20) -> 650 | F22: =G22+H22+I22 -> 699279.62 | G22: =SUM(G4:G20) -> 224661.1 | H22: =SUM(H4:H20) -> 24677.5 | I22: =SUM(I4:I20) -> 449941.02
A24: 2. LACE
A25: PLAIN LACE (PL) | B25: ='LACE - STOCK OVERVIEW'!L3 -> 62 | C25: ='LACE - STOCK OVERVIEW'!F3 -> 16 | D25: ='LACE - STOCK OVERVIEW'!I3 -> 3 | E25: ='LACE - ALL'!C56 -> 43 | F25: =G25+H25+I25 -> 49242.1 | G25: ='LACE - STOCK OVERVIEW'!H3 -> 11238.6 | H25: ='LACE - STOCK OVERVIEW'!K3 -> 2160 | I25: 35843.5
A26: LUREXLACE (LL) | B26: ='LACE - STOCK OVERVIEW'!L4 -> 68 | C26: ='LACE - STOCK OVERVIEW'!F4 -> 17 | D26: ='LACE - STOCK OVERVIEW'!I4 -> 1 | E26: ='LACE - ALL'!C111 -> 50 | F26: =G26+H26+I26 -> 86282.41 | G26: ='LACE - STOCK OVERVIEW'!H4 -> 21860.91 | H26: ='LACE - STOCK OVERVIEW'!K4 -> 1245.5 | I26: 63176
A27: CASA DELLO (CD) | B27: ='LACE - STOCK OVERVIEW'!L5 -> 52 | C27: ='LACE - STOCK OVERVIEW'!F5 -> 18 | D27: ='LACE - STOCK OVERVIEW'!I5 -> 0 | E27: =B27-C27-D27 -> 34 | F27: =G27+H27+I27 -> 43790.08 | G27: ='LACE - STOCK OVERVIEW'!H5 -> 15106.08 | H27: ='LACE - STOCK OVERVIEW'!K5 -> 0 | I27: 28684
A28: LACE TOTAL | B28: =SUM(B25:B27) -> 182 | C28: =SUM(C25:C27) -> 51 | D28: =SUM(D25:D27) -> 4 | E28: =B28-C28-D28 -> 127 | F28: =SUM(F25:F27) -> 179314.59 | G28: =SUM(G25:G27) -> 48205.59 | H28: =SUM(H25:H27) -> 3405.5 | I28: =SUM(I25:I27) -> 127703.5
A30: RICCIARINI CORD LACE (70) | B30: 70 | C30: ='LACE - STOCK OVERVIEW'!F7 -> 0 | D30: ='LACE - STOCK OVERVIEW'!I7 -> 0 | E30: =B30-C30-D30 -> 70 | F30: ='LACE - STOCK OVERVIEW'!E7 -> 9900 | G30: ='LACE - STOCK OVERVIEW'!H7 -> 0 | H30: ='LACE - STOCK OVERVIEW'!K7 -> 0 | I30: ='LACE - STOCK OVERVIEW'!N7 -> 9900
A32: 3. CEMB
A33: CEMB 40 | B33: ='CEMB - STOCK OVERVIEW'!C3 -> 201 | C33: ='CEMB - STOCK OVERVIEW'!D3 -> 6 | D33: ='CEMB - PENDING'!C18 -> 0 | E33: =B33-C33-D33 -> 195 | F33: =G33+H33+I33 -> 30476.25 | G33: =Table121[[#Totals],[COST PER PC]] -> 301 | H33: =Table127[[#Totals],[COST PIECE RM]] -> 0 | I33: 30175.25
A34: CEMB 60 | B34: 81 | C34: ='CEMB - STOCK OVERVIEW'!D4 -> 14 | D34: ='CEMB - PENDING'!C31 -> 0 | E34: =B34-C34-D34 -> 67 | F34: =G34+H34+I34 -> 26940 | G34: =Table126[[#Totals],[COST PER PC]] -> 4440 | H34: =Table130[[#Totals],[COST PIECE RM]] -> 0 | I34: 22500
A35: CEMB 120 | B35: 62 | C35: ='CEMB - STOCK OVERVIEW'!D5 -> 7 | D35: ='CEMB - PENDING'!C43 -> 0 | E35: =B35-C35-D35 -> 55 | F35: =G35+H35+I35 -> 35271.8 | G35: ='CEMB - SOLD'!L56 -> 3975.8 | H35: =Table137[[#Totals],[COST PIECE RM]] -> 0 | I35: 31296
A36: CEMB 180 | B36: 52 | C36: ='CEMB - STOCK OVERVIEW'!D6 -> 5 | D36: ='CEMB - PENDING'!C55 -> 0 | E36: =B36-C36-D36 -> 47 | F36: =G36+H36+I36 -> 53169.75 | G36: ='CEMB - SOLD'!L68 -> 4839.75 | H36: =Table138[[#Totals],[COST PIECE RM]] -> 0 | I36: 48330
A38: LACE (CEMB) TOTAL | B38: =SUM(B33:B36) -> 396 | C38: =SUM(C33:C36) -> 32 | D38: =SUM(D33:D36) -> 0 | E38: =SUM(E33:E36) -> 364 | F38: =SUM(F33:F36) -> 145857.8 | G38: =SUM(G33:G36) -> 13556.55 | H38: =SUM(H33:H36) -> 0 | I38: =SUM(I33:I36) -> 132301.25
A40: 4. BEIRUT
A41: LACE (BEIRUT) | B41: 95 | C41: ='LACE - SOLD'!C100 -> 2 | D41: ='LACE - PENDING'!C50 -> 0 | E41: =B41-C41-D41 -> 93 | F41: =G41+H41+I41 -> 138435 | G41: ='LACE - SOLD'!J100 -> 1920 | H41: ='LACE - PENDING'!G50 -> 0 | I41: 136515
A43: BEIRUT TOTAL | B43: =B41 -> 95 | C43: =C41 -> 2 | D43: =D41 -> 0 | E43: =E41 -> 93 | F43: =F41 -> 138435 | G43: =G41 -> 1920 | H43: =H41 -> 0 | I43: =I41 -> 136515
A45: 5. EMBROIDERY
A46: ARGOMENTI (ARGO) | B46: 10 | C46: 0 | D46: 0 | E46: ='EMBROIDERY - ALL'!D25 -> 10 | F46: 15672.5 | G46: 0 | I46: =F46-G46-H46 -> 15672.5
A47: RICAMIFICIO PAOLO (RIC-P) | B47: 5 | C47: 2 | D47: 0 | E47: ='EMBROIDERY - ALL'!D34 -> 3 | F47: 35185 | G47: 6210 | I47: =F47-G47-H47 -> 28975
A48: HOFERHECHT (HOFE) | B48: 5 | C48: 0 | D48: 0 | E48: ='EMBROIDERY - ALL'!D45 -> 5 | F48: 18920 | G48: 0 | I48: =F48-G48-H48 -> 18920
A49: ALDOBIANCHI (ALDO) | B49: 13 | C49: 1 | D49: 0 | E49: ='EMBROIDERY - ALL'!D63 -> 12 | F49: 112605 | G49: 5725 | I49: =F49-G49-H49 -> 106880
A50: RICAMIFICIO GUEGAIN (RIC-G) | B50: 11 | C50: 3 | D50: 0 | E50: ='EMBROIDERY - ALL'!D77 -> 8 | F50: 29217.5 | G50: 7938 | I50: =F50-G50-H50 -> 21279.5
A51: QUORUM (QUO) | B51: 6 | C51: 0 | D51: 0 | E51: ='EMBROIDERY - ALL'!D89 -> 6 | F51: 5700 | G51: 0 | I51: =F51-G51-H51 -> 5700
A52: RICAMIFICIO BRAGA & ASPESI (ASPE) | B52: 4 | C52: 0 | D52: 0 | E52: ='EMBROIDERY - ALL'!D99 -> 4 | F52: 10080 | G52: 0 | I52: =F52-G52-H52 -> 10080
A53: RICAMIFICIO CANDELLI (CAND) | B53: 15 | C53: 0 | D53: 0 | E53: ='EMBROIDERY - ALL'!D120 -> 15 | F53: 26207 | G53: 0 | I53: =F53-G53-H53 -> 26207
A54: UNICRAFT (UNI) | B54: 16 | C54: 0 | D54: 0 | E54: ='EMBROIDERY - ALL'!D142 -> 16 | F54: 15503.5 | G54: 0 | I54: =F54-G54-H54 -> 15503.5
A55: OKU TEX AG (OKU) | B55: 12 | C55: 0 | D55: 0 | E55: ='EMBROIDERY - ALL'!D160 -> 12 | F55: 73370 | G55: 0 | I55: =F55-G55-H55 -> 73370
A56: RICAMIFICIO GIMAR (RIC-GIM) | B56: 44 | C56: 0 | D56: 0 | E56: ='EMBROIDERY - ALL'!D210 -> 44 | F56: 98559 | G56: 0 | I56: =F56-G56-H56 -> 98559
A57: DISENO & ELIESAAB (DIS) | B57: 9 | C57: 0 | D57: 0 | E57: ='EMBROIDERY - ALL'!D225 -> 9 | F57: 44475 | G57: 0 | I57: =F57-G57-H57 -> 44475
A58: RICAMIFICIO BRAGA (R-BR) | B58: 14 | C58: 0 | D58: 0 | E58: ='EMBROIDERY - ALL'!D245 -> 14 | F58: 25584 | G58: 0 | I58: =F58-G58-H58 -> 25584
A59: VEMA (VEM) | B59: 23 | C59: 0 | D59: 0 | E59: ='EMBROIDERY - ALL'!D274 -> 23 | F59: 104627.5 | G59: 0 | I59: =F59-G59-H59 -> 104627.5
A60: TGM EMBROIDERY BORDER (TGM-B) | B60: 13 | C60: 0 | D60: 0 | E60: ='EMBROIDERY - ALL'!D293 -> 13 | F60: 38585 | G60: 0 | I60: =F60-G60-H60 -> 38585
A61: MURARAKA (MURA) | B61: 6 | C61: 0 | D61: 0 | E61: ='EMBROIDERY - ALL'!D305 -> 6 | F61: 6000 | G61: 0 | I61: =F61-G61-H61 -> 6000
A62: LAGATOLA (LAGA) | B62: 7 | C62: 0 | D62: 0 | E62: ='EMBROIDERY - ALL'!D317 -> 7 | F62: 37700.5 | G62: 0 | I62: =F62-G62-H62 -> 37700.5
A63: CASA DELLO (CASA) | B63: 14 | C63: 0 | D63: 0 | E63: ='EMBROIDERY - ALL'!D337 -> 14 | F63: 10692.5 | G63: 0 | I63: =F63-G63-H63 -> 10692.5
A64: SHAGUN (SHA) | B64: 3 | C64: 0 | D64: 0 | E64: ='EMBROIDERY - ALL'!D346 -> 3 | F64: 6710 | G64: 0 | I64: =F64-G64-H64 -> 6710
A65: SOLSTISS (SID) | B65: 10 | C65: 0 | D65: 0 | E65: ='EMBROIDERY - ALL'!D362 -> 10 | F65: 42090 | G65: 0 | I65: =F65-G65-H65 -> 42090
A66: SOLSTISS (ORIGINAL) | B66: 10 | C66: 1 | D66: 0 | E66: ='EMBROIDERY - ALL'!D377 -> 9 | F66: 39892.5 | G66: 5880 | I66: =F66-G66-H66 -> 34012.5
A67: TGM SILK (TGM) | B67: 8 | C67: 0 | D67: 0 | E67: ='EMBROIDERY - ALL'!D391 -> 8 | F67: 24500 | G67: 0 | I67: =F67-G67-H67 -> 24500
A68: TGM WITH BORDER | B68: 7 | C68: 0 | D68: 0 | E68: ='EMBROIDERY - ALL'!D404 -> 7 | F68: 28505 | G68: 0 | I68: =F68-G68-H68 -> 28505
A69: NEC EMBROIDERY (NEC) | B69: 5 | C69: 0 | D69: 0 | E69: ='EMBROIDERY - ALL'!D415 -> 5 | F69: 11250 | G69: 0 | I69: =F69-G69-H69 -> 11250
A70: RUFFO COLI (RUFF) | B70: 3 | C70: 0 | D70: 0 | E70: ='EMBROIDERY - ALL'!D424 -> 3 | F70: 7425 | G70: 0 | I70: =F70-G70-H70 -> 7425
A71: QUORUM EMBROIDERY | B71: 4 | C71: 0 | D71: 0 | E71: ='EMBROIDERY - ALL'!D434 -> 4 | F71: 3950 | G71: 0 | I71: =F71-G71-H71 -> 3950
A72: ALB 6, MAR 1, EMB 17, STY 2 | B72: 26 | C72: 3 | D72: 0 | E72: ='EMBROIDERY - ALL'!D462 -> 23 | F72: 58686 | G72: 6072 | I72: =F72-G72-H72 -> 52614
A73: QUORUM EMBROIDERY | B73: 14 | C73: 0 | D73: 0 | E73: ='EMBROIDERY - ALL'!D483 -> 14 | F73: 11320 | G73: 0 | I73: =F73-G73-H73 -> 11320
A75: EMBROIDERY TOTAL | B75: =SUM(B46:B73) -> 317 | C75: =SUM(C46:C73) -> 10 | D75: =SUM(D46:D73) -> 0 | E75: =SUM(E46:E74) -> 307 | F75: =SUM(F46:F74) -> 943012.5 | G75: =SUM(G46:G74) -> 31825 | I75: =SUM(I46:I73) -> 911187.5
A78: TOTAL | B78: =SUM(B75,B28,B22,B43,B38,B30) -> 2114 | C78: =SUM(C75,C28,C22,C43,C38,C30) -> 455 | D78: =SUM(D75,D28,D22,D43,D38,D30) -> 48 | E78: =SUM(E75,E28,E22,E43,E38,E30) -> 1611 | F78: =SUM(F75,F28,F22,F43,F38,F30) -> 2115799.5 | G78: =SUM(G75,G28,G22,G43,G38,G30) -> 320168.24 | H78: =SUM(H75,H28,H22,H43,H38,H30) -> 28083 | I78: =SUM(I75,I28,I22,I43,I38,I30) -> 1767548.3
A81: PENDING | F81: VALUE | G81: NOTES
A82: Mr Cetin | F82: 16131
A83: Ms Klara & Ms Silvia | F83: 2193.5
A84: TENGKU SHERRY | F84: 4314.6
A85: TENGKU SHERRY | F85: 24620.93
A86: VIP SET-13 ( invoice) | F86: 23224
A87: VIP SET-14 ( invoice) | F87: 11000
A88: VIP SET-15 ( invoice) | F88: 19422
A91: TOTAL | B91: =SUM(B82:B86) -> 0 | F91: =SUM(F82:F90) -> 100906.03

Sheet SILK  - STOCK OVERVIEW
A1: ITEM | B1: TOTAL BOXES | C1: BOXES SOLD | D1: TOTAL BOXES IN OFFICE | E1: BOXES AVAILABLE | F1: BOXES PENDING | G1: TOTAL METERS | H1: TOTAL METERS IN OFFICE | I1: TOTAL METERS IN SOLD | J1: TOTAL METERS PENDING | K1: TOTAL COST VALUE MYR | L1: TOTAL COST VALUE OF SOLD | M1: TOTAL COST VALUE IN OFFICE MYR | N1: TOTAL COST VALUE OF PENDING | O1: NET PROFIT AFTER COST
A2: M&M 1-70
A3: CDC | B3: =C3+F3+E3 -> 69 | C3: =COUNTIFS('SILK - SOLD'!D14:D78,"*CDC*") -> 29 | D3: =F3+E3 -> 40 | E3: =COUNTIF(M7M_A[QUALITY],"*CDC") -> 38 | F3: =COUNTIF('SILK - PENDING'!D13:D17,"*CDC*") -> 2 | G3: =H3+I3+J3 -> 354.1 | H3: =SUMIF(M7M_A[#All],"CDC",'SILK - ALL'!E12:E83) -> 195.2 | I3: =SUMIF('SILK - SOLD'!D13:D79,"CDC",'SILK - SOLD'!E13:E79) -> 147.7 | J3: =SUMIF(MM_P[#All],"CDC",Table6[#All]) -> 11.2 | K3: =L3+N3+M3 -> 46835 | L3: =SUMIF('SILK - SOLD'!D13:D79,"CDC",'SILK - SOLD'!K13:K79) -> 19760.5 | M3: =SUMIF(M7M_A[#All],"CDC",'SILK - ALL'!H12:H82) -> 25506.5 | N3: =SUMIF(MM_P[#All],"CDC",'SILK - PENDING'!H13:H18) -> 1568
A4: GEORGETTE | B4: =C4+F4+E4 -> 66 | C4: =COUNTIFS('SILK - SOLD'!D14:D76,"*GEORGETTE*") -> 32 | D4: =F4+E4 -> 34 | E4: =COUNTIF('SILK - ALL'!D13:D83,"*GEORGETTE*") -> 32 | F4: =COUNTIF('SILK - PENDING'!D13:D17,"*CDC*") -> 2 | G4: =H4+I4+J4 -> 299.2 | H4: =SUMIF(M7M_A[#All],"GEORGETTE*",'SILK - ALL'!E12:E83) -> 142 | I4: =SUMIF('SILK - SOLD'!D13:D79,"GEORGETTE",'SILK - SOLD'!E13:E79) -> 146.2 | J4: =SUMIF(MM_P[#All],"GEORGETTE",Table6[#All]) -> 11 | K4: =L4+N4+M4 -> 31011.5 | L4: =SUMIF('SILK - SOLD'!D13:D79,"GEORGETTE",'SILK - SOLD'!K13:K79) -> 15060 | M4: =SUMIF(M7M_A[#All],"GEORGETTE*",'SILK - ALL'!H12:H82) -> 14741.5 | N4: =SUMIF(MM_P[#All],"GEORGETTE",'SILK - PENDING'!H13:H18) -> 1210
A5: CHIFFON | B5: =C5+F5+E5 -> 3 | C5: =COUNTIFS('SILK - SOLD'!D15:D79,"*CHIFFON*") -> 3 | D5: =F5+E5 -> 0 | E5: =COUNTIF('SILK - ALL'!D13:D84,"*CHIFFON*") -> 0 | F5: =COUNTIF('SILK - PENDING'!D15:D19,"*CHIFFON*") -> 0 | G5: =H5+I5+J5 -> 16 | H5: =SUMIF(M7M_A[#All],"CHIFFON*",'SILK - ALL'!E13:E84) -> 0 | I5: =SUMIF('SILK - SOLD'!D13:D79,"CHIFFON",'SILK - SOLD'!E13:E79) -> 16 | J5: =SUMIF(MM_P[#All],"CHIFFON",Table6[#All]) -> 0 | K5: =L5+N5+M5 -> 1745 | L5: =SUMIF('SILK - SOLD'!D13:D79,"CHIFFON",'SILK - SOLD'!K13:K79) -> 1745 | M5: =SUMIF(M7M_A[#All],"CHIFFON",'SILK - ALL'!H12:H82) -> 0 | N5: =SUMIF(MM_P[#All],"CHIFFON",'SILK - PENDING'!H13:H18) -> 0
A6: SATIN | B6: =C6+F6+E6 -> 1 | C6: =COUNTIFS('SILK - SOLD'!D16:D80,"*SATIN*") -> 1 | D6: =F6+E6 -> 0 | E6: =COUNTIF('SILK - ALL'!D13:D85,"*SATIN*") -> 0 | F6: =COUNTIF('SILK - PENDING'!D15:D19,"*SATIN*") -> 0 | G6: =H6+I6+J6 -> 5.5 | H6: =SUMIF(M7M_A[#All],"SATIN*",'SILK - ALL'!E14:E85) -> 0 | I6: =SUMIF('SILK - SOLD'!D13:D79,"SATIN",'SILK - SOLD'!E13:E79) -> 5.5 | J6: =SUMIF(MM_P[#All],"SATIN",Table6[#All]) -> 0 | K6: =L6+N6+M6 -> 632.5 | L6: =SUMIF('SILK - SOLD'!D13:D79,"*SATIN*",'SILK - SOLD'!K13:K79) -> 632.5 | M6: =SUMIF(M7M_A[#All],"*SATIN*",'SILK - ALL'!H12:H82) -> 0 | N6: =SUMIF(MM_P[#All],"SATIN",'SILK - PENDING'!H13:H18) -> 0
A7: M&M 1-70 TOTAL | B7: =SUM(B3:B6) -> 139 | C7: =SUM(C3:C6) -> 65 | D7: =SUM(D3:D6) -> 74 | E7: =SUM(E3:E6) -> 70 | F7: =SUM(F3:F6) -> 4 | G7: =SUM(G3:G6) -> 674.8 | H7: =SUM(H3:H6) -> 337.2 | I7: =SUM(I3:I6) -> 315.4 | ... N7: =SUM(N3:N6) -> 2778 | O7: ='SILK - SOLD'!L79 -> 41540.2
A9: ARGOMENTI (ARGO)
A10: CDC | B10: =C10+F10+E10 -> 55 | C10: =COUNTIFS('SILK - SOLD'!D85:D107,"*CDC*") -> 14 | D10: =F10+E10 -> 41 | E10: =COUNTIF(ARGO_A[#All],"CDC") -> 41 | F10: =COUNTIF(ARGO_P[#All],"*CDC*") -> 0 | G10: =H10+I10+J10 -> 299.1 | H10: =SUMIF(ARGO_A[#All],"CDC",'SILK - ALL'!E87:E189) -> 224.6 | I10: =SUMIF(ARGO_S[#All],"CDC",ARGO_SO[#All]) -> 74.5 | J10: =SUMIF(ARGO_P[#All],"CDC",Table7[#All]) -> 0 | K10: =M10+L10+N10 -> 42039 | L10: =SUMIF(ARGO_S[#All],"CDC",'SILK - SOLD'!K85:K107) -> 10595 | M10: =SUMIF(ARGO_A[#All],"CDC",'SILK - ALL'!H87:H188) -> 31444 | N10: =SUMIF(ARGO_P[#All],"CDC",Table82[#All]) -> 0
A11: GEORGETTE | B11: =C11+F11+E11 -> 14 | C11: =COUNTIFS('SILK - SOLD'!D85:D107,"*GEORGETTE*") -> 1 | D11: =F11+E11 -> 13 | E11: =COUNTIF(ARGO_A[#All],"GEORGETTE") -> 13 | F11: =COUNTIF(ARGO_P[#All],"*GEORGETTE*") -> 0 | G11: =H11+I11+J11 -> 64 | H11: =SUMIF(ARGO_A[#All],"GEORGETTE",'SILK - ALL'!E87:E189) -> 61.5 | I11: =SUMIF(ARGO_S[#All],"GEORGETTE",ARGO_SO[#All]) -> 2.5 | J11: =SUMIF(ARGO_P[#All],"GEORGETTE",Table7[#All]) -> 0 | K11: =M11+L11+N11 -> 7040 | L11: =SUMIF(ARGO_S[#All],"GEORGETTE",'SILK - SOLD'!K85:K107) -> 275 | M11: =SUMIF(ARGO_A[#All],"GEORGETTE",'SILK - ALL'!H87:H188) -> 6765 | N11: =SUMIF(ARGO_P[#All],"GEORGETTE",Table82[#All]) -> 0
A12: CHIFFON | B12: =C12+F12+E12 -> 10 | C12: =COUNTIFS('SILK - SOLD'!D85:D107,"*CHIFFON*") -> 0 | D12: =F12+E12 -> 10 | E12: =COUNTIF(ARGO_A[#All],"CHIFFON") -> 10 | F12: =COUNTIF(ARGO_P[#All],"*CHIFFON*") -> 0 | G12: =H12+I12+J12 -> 65.5 | H12: =SUMIF(ARGO_A[#All],"CHIFFON",'SILK - ALL'!E87:E189) -> 65.5 | I12: =SUMIF(ARGO_S[#All],"CHIFFON",ARGO_SO[#All]) -> 0 | J12: =SUMIF(ARGO_P[#All],"CHIFFON",Table7[#All]) -> 0 | K12: =M12+L12+N12 -> 7205 | L12: =SUMIF(ARGO_S[#All],"CHIFFON",'SILK - SOLD'!K85:K107) -> 0 | M12: =SUMIF(ARGO_A[#All],"CHIFFON",'SILK - ALL'!H87:H188) -> 7205 | N12: =SUMIF(ARGO_P[#All],"CHIFFON",Table82[#All]) -> 0
A13: LUREX | B13: =C13+F13+E13 -> 35 | C13: =COUNTIFS('SILK - SOLD'!D85:D107,"*LUREX*") -> 4 | D13: =F13+E13 -> 31 | E13: =COUNTIF(ARGO_A[#All],"LUREX") -> 31 | F13: =COUNTIF(ARGO_P[#All],"*LUREX*") -> 0 | G13: =H13+I13+J13 -> 177 | H13: =SUMIF(ARGO_A[#All],"LUREX",'SILK - ALL'!E87:E189) -> 157.2 | I13: =SUMIF(ARGO_S[#All],"LUREX",ARGO_SO[#All]) -> 19.8 | J13: =SUMIF(ARGO_P[#All],"LUREX",Table7[#All]) -> 0 | K13: =M13+L13+N13 -> 30090 | L13: =SUMIF(ARGO_S[#All],"LUREX",'SILK - SOLD'!K85:K107) -> 3366 | M13: =SUMIF(ARGO_A[#All],"LUREX",'SILK - ALL'!H87:H188) -> 26724 | N13: =SUMIF(ARGO_P[#All],"LUREX",Table82[#All]) -> 0
A14: LUREX_CHIFFON | B14: =C14+F14+E14 -> 2 | C14: =COUNTIFS('SILK - SOLD'!D85:D107,"*LUREX_CHIFFON*") -> 0 | D14: =F14+E14 -> 2 | E14: =COUNTIF(ARGO_A[#All],"*LUREX_CHIFFON") -> 2 | F14: =COUNTIF(ARGO_P[#All],"*LUREX_CHIFFON*") -> 0 | G14: =H14+I14+J14 -> 10 | H14: =SUMIF(ARGO_A[#All],"LUREX_CHIFFON",'SILK - ALL'!E87:E189) -> 10 | I14: =SUMIF(ARGO_S[#All],"LUREX_CHIFFON",ARGO_SO[#All]) -> 0 | J14: =SUMIF(ARGO_P[#All],"LUREX_CHIFFON",Table7[#All]) -> 0 | K14: =M14+L14+N14 -> 1100 | L14: =SUMIF(ARGO_S[#All],"LUREX_CHIFFON",'SILK - SOLD'!K85:K107) -> 0 | M14: =SUMIF(ARGO_A[#All],"LUREX_CHIFFON",'SILK - ALL'!H87:H188) -> 1100 | N14: =SUMIF(ARGO_P[#All],"LUREX_CHIFFONC",Table82[#All]) -> 0
A15: SATIN | B15: =C15+F15+E15 -> 4 | C15: =COUNTIFS('SILK - SOLD'!D85:D107,"*SATIN*") -> 1 | D15: =F15+E15 -> 3 | E15: =COUNTIF(ARGO_A[#All],"SATIN") -> 3 | F15: =COUNTIF(ARGO_P[#All],"*SATIN*") -> 0 | G15: =H15+I15+J15 -> 20.5 | H15: =SUMIF(ARGO_A[#All],"SATIN",'SILK - ALL'!E87:E189) -> 15.5 | I15: =SUMIF(ARGO_S[#All],"SATIN",ARGO_SO[#All]) -> 5 | J15: =SUMIF(ARGO_P[#All],"SATIN",Table7[#All]) -> 0 | K15: =M15+L15+N15 -> 2870 | L15: =SUMIF(ARGO_S[#All],"SATIN",'SILK - SOLD'!K85:K107) -> 700 | M15: =SUMIF(ARGO_A[#All],"SATIN",'SILK - ALL'!H87:H188) -> 2170 | N15: =SUMIF(ARGO_P[#All],"SATIN",Table82[#All]) -> 0
A16: JACQUARD | B16: =C16+F16+E16 -> 2 | C16: =COUNTIFS('SILK - SOLD'!D85:D107,"*JACQUARD*") -> 1 | D16: =F16+E16 -> 1 | E16: =COUNTIF(ARGO_A[#All],"*JACQUARD") -> 1 | F16: =COUNTIF(ARGO_P[#All],"*JACQUARD*") -> 0 | G16: =H16+I16+J16 -> 10 | H16: =SUMIF(ARGO_A[#All],"JACQUARD",'SILK - ALL'!E87:E189) -> 5 | I16: =SUMIF(ARGO_S[#All],"JACQUARD",ARGO_SO[#All]) -> 5 | J16: =SUMIF(ARGO_P[#All],"JACQUARD",Table7[#All]) -> 0 | K16: =M16+L16+N16 -> 1400 | L16: =SUMIF(ARGO_S[#All],"*JACQUARD*",'SILK - SOLD'!K85:K107) -> 700 | M16: =SUMIF(ARGO_A[#All],"JACQUARD",'SILK - ALL'!H87:H188) -> 700 | N16: =SUMIF(ARGO_P[#All],"JACQUARD",Table82[#All]) -> 0
A17: ARGOMENTI (ARGO) TOTAL | B17: =SUM(B10:B16) -> 122 | C17: =SUM(C10:C16) -> 21 | D17: =SUM(D10:D16) -> 101 | E17: =SUM(E10:E16) -> 101 | F17: =SUM(F10:F16) -> 0 | G17: =SUM(G10:G16) -> 646.1 | H17: =SUM(H10:H16) -> 539.3 | I17: =SUM(I10:I16) -> 106.8 | ... N17: =SUM(N10:N16) -> 0 | O17: ='SILK - SOLD'!L107 -> 11520
A19: ALBERTI (ALB)
A20: CDC | B20: =C20+F20+E20 -> 80 | C20: =COUNTIFS(Table21[#All],"*CDC*") -> 23 | D20: =F20+E20 -> 57 | E20: =COUNTIF('SILK - ALL'!D195:D320,"*CDC") -> 56 | F20: =COUNTIF(ALB_P[#All],"*CDC*") -> 1 | G20: =H20+I20+J20 -> 440.1 | H20: =SUMIF(ALB_A[#All],"CDC",Table36[#All]) -> 308.9 | I20: =SUMIF(Table21[#All],"CDC",ALB_SO[#All]) -> 124.9 | J20: =SUMIF(ALB_P[#All],"CDC",Table8[#All]) -> 6.3 | K20: =M20+L20+N20 -> 49589.27 | L20: =SUMIF(Table21[#All],"CDC",Table66[#All]) -> 14917 | M20: =SUMIF(ALB_A[#All],"CDC",Table48[#All]) -> 33979.27 | N20: =SUMIF(ALB_P[#All],"CDC",Table83[#All]) -> 693
A21: GEORGETTE | B21: =C21+F21+E21 -> 71 | C21: =COUNTIFS(Table21[#All],"*GEORGETTE*") -> 26 | D21: =F21+E21 -> 45 | E21: =COUNTIF('SILK - ALL'!D195:D320,"*GEORGETTE") -> 45 | F21: =COUNTIF(ALB_P[#All],"*GEORGETTE*") -> 0 | G21: =H21+I21+J21 -> 372.1 | H21: =SUMIF(ALB_A[#All],"GEORGETTE",Table36[#All]) -> 242.3 | I21: =SUMIF(Table21[#All],"GEORGETTE",ALB_SO[#All]) -> 129.8 | J21: =SUMIF(ALB_P[#All],"GEORGETTE",Table8[#All]) -> 0 | K21: =M21+L21+N21 -> 38878 | L21: =SUMIF(Table21[#All],"GEORGETTE",Table66[#All]) -> 12890 | M21: =SUMIF(ALB_A[#All],"GEORGETTE",Table48[#All]) -> 25988 | N21: =SUMIF(ALB_P[#All],"GEORGETTE",Table83[#All]) -> 0
A22: CHIFFON | B22: =C22+F22+E22 -> 5 | C22: =COUNTIFS(Table21[#All],"*CHIFFON*") -> 1 | D22: =F22+E22 -> 4 | E22: =COUNTIF('SILK - ALL'!D195:D320,"*CHIFFON") -> 4 | F22: =COUNTIF(ALB_P[#All],"*CHIFFON*") -> 0 | G22: =H22+I22+J22 -> 28 | H22: =SUMIF(ALB_A[#All],"CHIFFON",Table36[#All]) -> 23 | I22: =SUMIF(Table21[#All],"CHIFFON",ALB_SO[#All]) -> 5 | J22: =SUMIF(ALB_P[#All],"CHIFFON",Table8[#All]) -> 0 | K22: =M22+L22+N22 -> 3080 | L22: =SUMIF(Table21[#All],"CHIFFON",Table66[#All]) -> 550 | M22: =SUMIF(ALB_A[#All],"CHIFFON",Table48[#All]) -> 2530 | N22: =SUMIF(ALB_P[#All],"CHIFFON",Table83[#All]) -> 0
A23: LUREX | B23: =C23+F23+E23 -> 17 | C23: =COUNTIFS(Table21[#All],"*LUREX*") -> 7 | D23: =F23+E23 -> 10 | E23: =COUNTIF('SILK - ALL'!D195:D320,"*LUREX") -> 10 | F23: =COUNTIF(ALB_P[#All],"*LUREX*") -> 0 | G23: =H23+I23+J23 -> 95.6 | H23: =SUMIF(ALB_A[#All],"LUREX",Table36[#All]) -> 58.4 | I23: =SUMIF(Table21[#All],"LUREX",ALB_SO[#All]) -> 37.2 | J23: =SUMIF(ALB_P[#All],"lUREX",Table8[#All]) -> 0 | K23: =M23+L23+N23 -> 12795.6 | L23: =SUMIF(Table21[#All],"LUREX",Table66[#All]) -> 4619.6 | M23: =SUMIF(ALB_A[#All],"LUREX",Table48[#All]) -> 8176 | N23: =SUMIF(ALB_P[#All],"LUREX",Table83[#All]) -> 0
A24: SATIN | B24: =C24+F24+E24 -> 5 | C24: =COUNTIFS(Table21[#All],"*SATIN*") -> 2 | D24: =F24+E24 -> 3 | E24: =COUNTIF('SILK - ALL'!D195:D320,"*SATIN") -> 3 | F24: =COUNTIF(ALB_P[#All],"*SATIN*") -> 0 | G24: =H24+I24+J24 -> 25.7 | H24: =SUMIF(ALB_A[#All],"SATIN",Table36[#All]) -> 15.7 | I24: =SUMIF(Table21[#All],"SATIN",ALB_SO[#All]) -> 10 | J24: =SUMIF(ALB_P[#All],"SATIN",Table8[#All]) -> 0 | K24: =M24+L24+N24 -> 2897 | L24: =SUMIF(Table21[#All],"SATIN",Table66[#All]) -> 1170 | M24: =SUMIF(ALB_A[#All],"SATIN",Table48[#All]) -> 1727 | N24: =SUMIF(ALB_P[#All],"SATIN",Table83[#All]) -> 0
A25: JACQUARD | B25: =C25+F25+E25 -> 4 | C25: =COUNTIFS(Table21[#All],"*JACQUARD*") -> 0 | D25: =F25+E25 -> 4 | E25: =COUNTIF('SILK - ALL'!D195:D320,"*JACQUARD") -> 4 | F25: =COUNTIF(ALB_P[#All],"*JACQUARD*") -> 0 | G25: =H25+I25+J25 -> 20 | H25: =SUMIF(ALB_A[#All],"JACQUARD",Table36[#All]) -> 20 | I25: =SUMIF(Table21[#All],"JACQUARD",ALB_SO[#All]) -> 0 | J25: =SUMIF(ALB_P[#All],"JACQUARD",Table8[#All]) -> 0 | K25: =M25+L25+N25 -> 2200 | L25: =SUMIF(Table21[#All],"JACQUARD",Table66[#All]) -> 0 | M25: =SUMIF(ALB_A[#All],"JACQUARD",Table48[#All]) -> 2200 | N25: =SUMIF(ALB_P[#All],"JACQUARD",Table83[#All]) -> 0
A26: CADY | B26: =C26+F26+E26 -> 4 | C26: =COUNTIFS(Table21[#All],"*CADY*") -> 0 | D26: =F26+E26 -> 4 | E26: =COUNTIF('SILK - ALL'!D195:D320,"*CADY") -> 4 | F26: =COUNTIF(ALB_P[#All],"*CADY*") -> 0 | G26: =H26+I26+J26 -> 20 | H26: =SUMIF(ALB_A[#All],"*CADY",Table36[#All]) -> 20 | I26: =SUMIF(Table21[#All],"*CADY*",ALB_SO[#All]) -> 0 | J26: =SUMIF(ALB_P[#All],"CADY",Table8[#All]) -> 0 | K26: =M26+L26+N26 -> 2200 | L26: =SUMIF(Table21[#All],"*CADY*",Table66[#All]) -> 0 | M26: =SUMIF(ALB_A[#All],"*CADY",Table48[#All]) -> 2200 | N26: =SUMIF(ALB_P[#All],"CADY",Table83[#All]) -> 0
A27: ALBERTI (ALB) TOTAL | B27: =SUM(B19:B26) -> 186 | C27: =SUM(C20:C26) -> 59 | D27: =SUM(D20:D26) -> 127 | E27: =SUM(E19:E26) -> 126 | F27: =SUM(F20:F26) -> 1 | G27: =SUM(G20:G26) -> 1001.5 | H27: =SUM(H20:H26) -> 688.3 | I27: =SUM(I20:I26) -> 306.9 | J27: =SUM(J20:J26) -> 6.3 | K27: =SUM(K20:K26) -> 111639.87 | L27: =SUM(L20:L26) -> 34146.6 | M27: =SUM(M20:M26) -> 76800.27 | N27: =SUM(N20:N26) -> 693 | O27: ='SILK - SOLD'!L171 -> 30188.6
A29: MARITEX (MAR)
A30: CDC | B30: =C30+F30+E30 -> 74 | C30: =COUNTIFS(Table23[#All],"*CDC*") -> 39 | D30: =F30+E30 -> 35 | E30: =COUNTIF(MAR_A[#All],"*CDC") -> 35 | F30: =COUNTIF('SILK - PENDING'!D42:D45,"*CDC*") -> 0 | G30: =H30+I30+J30 -> 370.2 | H30: =SUMIF(MAR_A[#All],"CDC",Table39[#All]) -> 175.2 | I30: =SUMIF(Table23[#All],"CDC",MAR_SO[#All]) -> 195 | J30: =SUMIF(MAR_P[#All],"CDC",Table9[#All]) -> 0 | K30: =M30+L30+N30 -> 42588 | L30: =SUMIF(Table23[#All],"CDC",Table67[#All]) -> 22440 | M30: =SUMIF(MAR_A[#All],"CDC",Table49[#All]) -> 20148 | N30: =SUMIF(MAR_P[#All],"CDC",Table84[#All]) -> 0
A31: GEORGETTE | B31: =C31+F31+E31 -> 10 | C31: =COUNTIFS(Table23[#All],"*GEORGETTE*") -> 2 | D31: =F31+E31 -> 8 | E31: =COUNTIF(MAR_A[#All],"*GEORGETTE") -> 8 | F31: =COUNTIF('SILK - PENDING'!D42:D45,"*GEORGETTE*") -> 0 | G31: =H31+I31+J31 -> 32.7 | H31: =SUMIF(MAR_A[#All],"GEORGETTE",Table39[#All]) -> 24.1 | I31: =SUMIF(Table23[#All],"GEORGETTE",MAR_SO[#All]) -> 8.6 | J31: =SUMIF(MAR_P[#All],"GEORGETTE",Table9[#All]) -> 0 | K31: =M31+L31+N31 -> 2764.75 | L31: =SUMIF(Table23[#All],"GEORGETTE",Table67[#All]) -> 656 | M31: =SUMIF(MAR_A[#All],"GEORGETTE",Table49[#All]) -> 2108.75 | N31: =SUMIF(MAR_P[#All],"GEORGETTE",Table84[#All]) -> 0
A32: CHIFFON | B32: =C32+F32+E32 -> 0 | C32: =COUNTIFS(Table23[#All],"*CHIFFON*") -> 0 | D32: =F32+E32 -> 0 | E32: =COUNTIF(MAR_A[#All],"CHIFFON") -> 0 | F32: =COUNTIF('SILK - PENDING'!D42:D45,"CHIFFON*") -> 0 | G32: =H32+I32+J32 -> 0 | H32: =SUMIF(MAR_A[#All],"CHIFFON",Table39[#All]) -> 0 | I32: =SUMIF(Table23[#All],"CHIFFON",MAR_SO[#All]) -> 0 | J32: =SUMIF(MAR_P[#All],"CHIFFON",Table9[#All]) -> 0 | K32: =M32+L32+N32 -> 0 | L32: =SUMIF(Table23[#All],"CHIFFON",Table67[#All]) -> 0 | M32: =SUMIF(MAR_A[#All],"CHIFFON",Table49[#All]) -> 0 | N32: =SUMIF(MAR_P[#All],"CHIFFON",Table84[#All]) -> 0
A33: LUREX | B33: =C33+F33+E33 -> 78 | C33: =COUNTIFS(Table23[#All],"*LUREX*") -> 47 | D33: =F33+E33 -> 31 | E33: =COUNTIF(MAR_A[#All],"LUREX") -> 30 | F33: =COUNTIF('SILK - PENDING'!D42:D45,"LUREX") -> 1 | G33: =H33+I33+J33 -> 388 | H33: =SUMIF(MAR_A[#All],"LUREX",Table39[#All]) -> 148 | I33: =SUMIF(Table23[#All],"LUREX",MAR_SO[#All]) -> 235 | J33: =SUMIF(MAR_P[#All],"LUREX",Table9[#All]) -> 5 | K33: =M33+L33+N33 -> 61695 | L33: =SUMIF(Table23[#All],"LUREX",Table67[#All]) -> 35685 | M33: =SUMIF(MAR_A[#All],"LUREX",Table49[#All]) -> 25160 | N33: =SUMIF(MAR_P[#All],"LUREX",Table84[#All]) -> 850
A34: LUREX_CHIFFON | B34: =C34+F34+E34 -> 1 | C34: =COUNTIFS(Table23[#All],"*LUREX_CHIFFON*") -> 0 | D34: =F34+E34 -> 1 | E34: =COUNTIF(MAR_A[#All],"*LUREX_CHIFFON") -> 1 | F34: =COUNTIF('SILK - PENDING'!D42:D45,"LUREX_CHIFFON") -> 0 | G34: =H34+I34+J34 -> 5 | H34: =SUMIF(MAR_A[#All],"LUREX_CHIFFON",Table39[#All]) -> 5 | I34: =SUMIF(Table23[#All],"LUREX_CHIFFON",MAR_SO[#All]) -> 0 | J34: =SUMIF(MAR_P[#All],"LUREX_CHIFFON",Table9[#All]) -> 0 | K34: =M34+L34+N34 -> 700 | L34: =SUMIF(Table23[#All],"LUREX_CHIFFON",Table67[#All]) -> 0 | M34: =SUMIF(MAR_A[#All],"LUREX_CHIFFON",Table49[#All]) -> 700 | N34: =SUMIF(MAR_P[#All],"LUREX_CHIFFON",Table84[#All]) -> 0
A35: PRINTED_LACE | B35: =C35+F35+E35 -> 2 | C35: =COUNTIFS(Table23[#All],"*PRINTED_KACE*") -> 0 | D35: =F35+E35 -> 2 | E35: =COUNTIF(MAR_A[#All],"*PRINTED_LACE") -> 2 | F35: =COUNTIF('SILK - PENDING'!D42:D45,"*PRINTED_LACE") -> 0 | G35: =H35+I35+J35 -> 20 | H35: =SUMIF(MAR_A[#All],"PRINTED_LACE",Table39[#All]) -> 10 | I35: =SUMIF(Table23[#All],"PRINTED_LACE",MAR_SO[#All]) -> 10 | J35: =SUMIF(MAR_P[#All],"PRINTED_LACE",Table9[#All]) -> 0 | K35: =M35+L35+N35 -> 700 | L35: =SUMIF(Table23[#All],"PRINTED_LACE",Table67[#All]) -> 0 | M35: =SUMIF(MAR_A[#All],"PRINTED_LACE",Table49[#All]) -> 700 | N35: =SUMIF(MAR_P[#All],"CDC",Table84[#All]) -> 0
A36: MARITEX (MAR) TOTAL | B36: =SUM(B30:B35) -> 165 | C36: =SUM(C30:C35) -> 88 | D36: =SUM(D30:D35) -> 77 | E36: =SUM(E30:E35) -> 76 | F36: =SUM(F30:F35) -> 1 | G36: =SUM(G30:G35) -> 815.9 | H36: =SUM(H30:H35) -> 362.3 | I36: =SUM(I30:I35) -> 448.6 | ... N36: =SUM(N30:N35) -> 850 | O36: ='SILK - SOLD'!L267 -> 40709
A38: NELLA
A39: CDC | B39: =C39+F39+E39 -> 13 | C39: =COUNTIFS(Table25[#All],"*CDC*") -> 3 | D39: =F39+E39 -> 10 | E39: =COUNTIF(NELL_A[#All],"CDC") -> 10 | F39: =COUNTIF(Table4[#All],"CDC") -> 0 | G39: =H39+I39+J39 -> 63.4 | H39: =SUMIF(NELL_A[#All],"CDC",Table52[#All]) -> 48.4 | I39: =SUMIF(Table25[#All],"CDC",NELL_SO[#All]) -> 15 | J39: =SUMIF(Table4[#All],"CDC",Table5[#All]) -> 0 | K39: =M39+L39+N39 -> 8876 | L39: =SUMIF(Table25[#All],"CDC",Table68[#All]) -> 2100 | M39: =SUMIF(NELL_A[#All],"CDC",Table50[#All]) -> 6776 | N39: =SUMIF(Table4[#All],"CDC",Table85[#All]) -> 0
A40: GEORGETTE | B40: =C40+F40+E40 -> 2 | C40: =COUNTIFS(Table25[#All],"*GEORGETTE*") -> 1 | D40: =F40+E40 -> 1 | E40: =COUNTIF(NELL_A[#All],"GEORGETTE") -> 1 | F40: =COUNTIF(Table4[#All],"GEORGETTE") -> 0 | G40: =H40+I40+J40 -> 10 | H40: =SUMIF(NELL_A[#All],"GEORGETTE",Table52[#All]) -> 5 | I40: =SUMIF(Table25[#All],"GEORGETTE",NELL_SO[#All]) -> 5 | J40: =SUMIF(Table4[#All],"GEORGETTE",Table5[#All]) -> 0 | K40: =M40+L40+N40 -> 1000 | L40: =SUMIF(Table25[#All],"GEORGETTE",Table68[#All]) -> 500 | M40: =SUMIF(NELL_A[#All],"GEORGETTE",Table50[#All]) -> 500 | N40: =SUMIF(Table4[#All],"GEORGETTE",Table85[#All]) -> 0
A41: SATIN | B41: =C41+F41+E41 -> 16 | C41: =COUNTIFS(Table25[#All],"*SATIN*") -> 2 | D41: =F41+E41 -> 14 | E41: =COUNTIF(NELL_A[#All],"*SATIN*") -> 13 | F41: =COUNTIF(Table4[#All],"SATIN") -> 1 | G41: =H41+I41+J41 -> 80 | H41: =SUMIF(NELL_A[#All],"*SATIN*",Table52[#All]) -> 65 | I41: =SUMIF(Table25[#All],"SATIN",NELL_SO[#All]) -> 10 | J41: =SUMIF(Table4[#All],"SATIN",Table5[#All]) -> 5 | K41: =M41+L41+N41 -> 11300 | L41: =SUMIF(Table25[#All],"SATIN",Table68[#All]) -> 1400 | M41: =SUMIF(NELL_A[#All],"*SATIN*",Table50[#All]) -> 9200 | N41: =SUMIF(Table4[#All],"SATIN",Table85[#All]) -> 700
A42: LUREX_CHIFFON | B42: =C42+F42+E42 -> 6 | C42: =COUNTIFS(Table25[#All],"*LUREX_CHIFFON*") -> 0 | D42: =F42+E42 -> 6 | E42: =COUNTIF(NELL_A[#All],"LUREX_CHIFFON") -> 6 | F42: =COUNTIF(Table4[#All],"LUREX_CHIFFON") -> 0 | G42: =H42+I42+J42 -> 32.2 | H42: =SUMIF(NELL_A[#All],"LUREX_CHIFFON",Table52[#All]) -> 32.2 | I42: =SUMIF(Table25[#All],"LUREX_CHIFFON",NELL_SO[#All]) -> 0 | J42: =SUMIF(Table4[#All],"LUREX_CHIFFON",Table5[#All]) -> 0 | K42: =M42+L42+N42 -> 5324 | L42: =SUMIF(Table25[#All],"LUREX_CHIFFON",Table68[#All]) -> 0 | M42: =SUMIF(NELL_A[#All],"LUREX_CHIFFON",Table50[#All]) -> 5324 | N42: =SUMIF(Table4[#All],"LUREX_CHIFFON",Table85[#All]) -> 0
A43: CHIFFON | B43: =C43+F43+E43 -> 8 | C43: =COUNTIFS(Table25[#All],"CHIFFON") -> 0 | D43: =F43+E43 -> 8 | E43: =COUNTIF(NELL_A[#All],"CHIFFON") -> 8 | F43: =COUNTIF(Table4[#All],"CHIFFON") -> 0 | G43: =H43+I43+J43 -> 39.5 | H43: =SUMIF(NELL_A[#All],"CHIFFON",Table52[#All]) -> 39.5 | I43: =SUMIF(Table25[#All],"CHIFFON",NELL_SO[#All]) -> 0 | J43: =SUMIF(Table4[#All],"CHIFFON",Table5[#All]) -> 0 | K43: =M43+L43+N43 -> 4150 | L43: =SUMIF(Table25[#All],"CHIFFON",Table68[#All]) -> 0 | M43: =SUMIF(NELL_A[#All],"CHIFFON",Table50[#All]) -> 4150 | N43: =SUMIF(Table4[#All],"CHIFFON",Table85[#All]) -> 0
A44: TWILLCDC | B44: =C44+F44+E44 -> 3 | C44: =COUNTIFS(Table25[#All],"*TWILLCDC*") -> 0 | D44: =F44+E44 -> 3 | E44: =COUNTIF(NELL_A[#All],"TWILLCDC") -> 2 | F44: =COUNTIF(Table4[#All],"TWILLCDC") -> 1 | G44: =H44+I44+J44 -> 15 | H44: =SUMIF(NELL_A[#All],"TWILLCDC",Table52[#All]) -> 10 | I44: =SUMIF(Table25[#All],"TWILLCDC",NELL_SO[#All]) -> 0 | J44: =SUMIF(Table4[#All],"TWILLCDC",Table5[#All]) -> 5 | K44: =M44+L44+N44 -> 2100 | L44: =SUMIF(Table25[#All],"TWILLCDC",Table68[#All]) -> 0 | M44: =SUMIF(NELL_A[#All],"TWILLCDC",Table50[#All]) -> 1400 | N44: =SUMIF(Table4[#All],"TWILLCDC",Table85[#All]) -> 700
A45: PRINTED_SILK | B45: =C45+F45+E45 -> 2 | C45: =COUNTIFS(Table25[#All],"*PRINTED_SILK*") -> 1 | D45: =F45+E45 -> 1 | E45: =COUNTIF(NELL_A[#All],"PRINTED_SILK") -> 1 | F45: =COUNTIF(Table4[#All],"PRINTED_SILK") -> 0 | G45: =H45+I45+J45 -> 10 | H45: =SUMIF(NELL_A[#All],"PRINTED_SILK",Table52[#All]) -> 5.2 | I45: =SUMIF(Table25[#All],"PRINTED_SILK",NELL_SO[#All]) -> 4.8 | J45: =SUMIF(Table4[#All],"PRINTED_SILK",Table5[#All]) -> 0 | K45: =M45+L45+N45 -> 1400 | L45: =SUMIF(Table25[#All],"PRINTED_SILK",Table68[#All]) -> 672 | M45: =SUMIF(NELL_A[#All],"PRINTED_SILK",Table50[#All]) -> 728 | N45: =SUMIF(Table4[#All],"CDC",Table85[#All]) -> 0
A46: NELLA TOTAL | B46: =SUM(B39:B45) -> 50 | C46: =SUM(C39:C45) -> 7 | D46: =SUM(D39:D45) -> 43 | E46: =SUM(E39:E45) -> 41 | F46: =SUM(F39:F45) -> 2 | G46: =SUM(G39:G45) -> 250.1 | H46: =SUM(H39:H45) -> 205.3 | I46: =SUM(I39:I45) -> 34.8 | ... N46: =SUM(N39:N45) -> 1400 | O46: ='SILK - SOLD'!L281 -> 3585.6
A48: AVANTGARD (AVAN)
A49: CDC | B49: =C49+F49+E49 -> 22 | C49: =COUNTIFS(Table20[#All],"*CDC*") -> 7 | D49: =F49+E49 -> 15 | E49: =COUNTIF(AVAN_A[#All],"CDC") -> 15 | F49: =COUNTIF(Table10[#All],"CDC") -> 0 | G49: =H49+I49+J49 -> 110 | H49: =SUMIF(AVAN_A[#All],"CDC",Table53[#All]) -> 75 | I49: =SUMIF(Table20[#All],"CDC",Table22[#All]) -> 35 | J49: =SUMIF(Table10[#All],"CDC",Table11[#All]) -> 0 | K49: =M49+L49+N49 -> 12775 | L49: =SUMIF(Table20[#All],"CDC",Table69[#All]) -> 4150 | M49: =SUMIF(AVAN_A[#All],"CDC",Table51[#All]) -> 8625 | N49: =SUMIF(Table10[#All],"CDC",Table86[#All]) -> 0
A50: GEORGETTE | B50: =C50+F50+E50 -> 22 | C50: =COUNTIFS(Table20[#All],"GEORGETTE") -> 7 | D50: =F50+E50 -> 15 | E50: =COUNTIF(AVAN_A[#All],"GEORGETTE") -> 13 | F50: =COUNTIF(Table10[#All],"GEORGETTE") -> 2 | G50: =H50+I50+J50 -> 110 | H50: =SUMIF(AVAN_A[#All],"GEORGETTE",Table53[#All]) -> 65 | I50: =SUMIF(Table20[#All],"GEORGETTE",Table22[#All]) -> 35 | J50: =SUMIF(Table10[#All],"GEORGETTE",Table11[#All]) -> 10 | K50: =M50+L50+N50 -> 10450 | L50: =SUMIF(Table20[#All],"GEORGETTE",Table69[#All]) -> 3325 | M50: =SUMIF(AVAN_A[#All],"GEORGETTE",Table51[#All]) -> 6175 | N50: =SUMIF(Table10[#All],"GEORGETTE",Table86[#All]) -> 950
A51: AVANTGARD (AVAN) TOTAL | B51: =SUM(B49:B50) -> 44 | C51: =SUM(C49:C50) -> 14 | D51: =SUM(D49:D50) -> 30 | E51: =SUM(E49:E50) -> 28 | F51: =SUM(F49:F50) -> 2 | G51: =SUM(G49:G50) -> 220 | H51: =SUM(H49:H50) -> 140 | I51: =SUM(I49:I50) -> 70 | ... N51: =SUM(N49:N50) -> 950 | O51: ='SILK - SOLD'!L300 -> 8475
A53: CASA DELLO (CASA)
A54: CDC | B54: =C54+F54+E54 -> 12 | C54: =COUNTIFS(CASA_SOLD[#All],"*CDC*") -> 6 | D54: =F54+E54 -> 6 | E54: =COUNTIF(CASA_A[#All],"CDC") -> 4 | F54: =COUNTIF(Table12[#All],"CDC") -> 2 | G54: =H54+I54+J54 -> 61.3 | H54: =SUMIF(CASA_A[#All],"CDC",CASA_AV[#All]) -> 22.2 | I54: =SUMIF(CASA_SOLD[#All],"CDC",CASA_SO[#All]) -> 31.1 | J54: =SUMIF(Table12[#All],"CDC",Table13[#All]) -> 8 | K54: =M54+L54+N54 -> 7578 | L54: =SUMIF(CASA_SOLD[#All],"CDC",Table70[#All]) -> 3954 | M54: =SUMIF(CASA_A[#All],"CDC",Table54[#All]) -> 2664 | N54: =SUMIF(Table12[#All],"CDC",Table87[#All]) -> 960
A55: SATIN | B55: =C55+F55+E55 -> 26 | C55: =COUNTIFS(CASA_SOLD[#All],"*SATIN*") -> 18 | D55: =F55+E55 -> 8 | E55: =COUNTIF(CASA_A[#All],"SATIN") -> 6 | F55: =COUNTIF(Table12[#All],"SATIN") -> 2 | G55: =H55+I55+J55 -> 126.1 | H55: =SUMIF(CASA_A[#All],"SATIN",CASA_AV[#All]) -> 26.4 | I55: =SUMIF(CASA_SOLD[#All],"SATIN",CASA_SO[#All]) -> 91.7 | J55: =SUMIF(Table12[#All],"SATIN",Table13[#All]) -> 8 | K55: =M55+L55+N55 -> 15132 | L55: =SUMIF(CASA_SOLD[#All],"SATIN",Table70[#All]) -> 11004 | M55: =SUMIF(CASA_A[#All],"SATIN",Table54[#All]) -> 3168 | N55: =SUMIF(Table12[#All],"SATIN",Table87[#All]) -> 960
A56: CADY | B56: =C56+F56+E56 -> 1 | C56: =COUNTIFS(CASA_SOLD[#All],"*CADY*") -> 1 | D56: =F56+E56 -> 0 | E56: =COUNTIF(CASA_A[#All],"CADY") -> 0 | F56: =COUNTIF(Table12[#All],"*CADY*") -> 0 | G56: =H56+I56+J56 -> 4.8 | H56: =SUMIF(CASA_A[#All],"CADY",CASA_AV[#All]) -> 0 | I56: =SUMIF(CASA_SOLD[#All],"CADY",CASA_SO[#All]) -> 4.8 | J56: =SUMIF(Table12[#All],"CADY",Table13[#All]) -> 0 | K56: =M56+L56+N56 -> 672 | L56: =SUMIF(CASA_SOLD[#All],"cady",Table70[#All]) -> 672 | M56: =SUMIF(CASA_A[#All],"CADY",Table54[#All]) -> 0 | N56: =SUMIF(Table12[#All],"CADY",Table87[#All]) -> 0
A57: CASA DELLO (CASA) TOTAL | B57: =SUM(B54:B56) -> 39 | C57: =SUM(C54:C56) -> 25 | D57: =SUM(D54:D56) -> 14 | E57: =SUM(E53:E56) -> 10 | F57: =SUM(F54:F56) -> 4 | G57: =SUM(G54:G56) -> 192.2 | H57: =SUM(H54:H56) -> 48.6 | I57: =SUM(I54:I56) -> 127.6 | J57: =SUM(J54:J56) -> 16 | K57: =SUM(K54:K56) -> 23382 | L57: =SUM(L54:L56) -> 15630 | M57: =SUM(M54:M56) -> 5832 | N57: =SUM(N54:N56) -> 1920 | O57: ='SILK - SOLD'!L330 -> 19780.608
A59: STYLE SILK (STYL)
A60: CDC | B60: =C60+F60+E60 -> 22 | C60: =COUNTIFS(Table26[#All],"*CDC*") -> 5 | D60: =F60+E60 -> 17 | E60: =COUNTIF(STYL_A[#All],"CDC") -> 15 | F60: =COUNTIF(Table14[#All],"CDC") -> 2 | G60: =H60+I60+J60 -> 108 | H60: =SUMIF(STYL_A[#All],"CDC",STY_A[#All]) -> 75 | I60: =SUMIF(Table26[#All],"CDC",STY_SO[#All]) -> 23 | J60: =SUMIF(Table14[#All],"CDC",Table15[#All]) -> 10 | K60: =M60+L60+N60 -> 15560 | L60: =SUMIF(Table26[#All],"CDC",Table71[#All]) -> 3335 | M60: =SUMIF(STYL_A[#All],"CDC",Table55[#All]) -> 10775 | N60: =SUMIF(Table14[#All],"CDC",Table88[#All]) -> 1450
A61: GEORGETTE | B61: =C61+F61+E61 -> 21 | C61: =COUNTIFS(Table26[#All],"*GEORGETTE*") -> 4 | D61: =F61+E61 -> 17 | E61: =COUNTIF(STYL_A[#All],"CDC") -> 15 | F61: =COUNTIF(Table14[#All],"GEORGETTE") -> 2 | G61: =H61+I61+J61 -> 88.9 | H61: =SUMIF(STYL_A[#All],"GEORGETTE",STY_A[#All]) -> 67 | I61: =SUMIF(Table26[#All],"GEORGETTE",STY_SO[#All]) -> 15.7 | J61: =SUMIF(Table14[#All],"GEORGETTE",Table15[#All]) -> 6.2 | K61: =M61+L61+N61 -> 11112.5 | L61: =SUMIF(Table26[#All],"GEORGETTE",Table71[#All]) -> 1962.5 | M61: =SUMIF(STYL_A[#All],"GEORGETTE",Table55[#All]) -> 8375 | N61: =SUMIF(Table14[#All],"GEORGETTE",Table88[#All]) -> 775
A62: STYLE SILK (STYL) TOTAL | B62: =SUM(B59:B61) -> 43 | C62: =SUM(C59:C61) -> 9 | D62: =SUM(D60:D61) -> 34 | E62: =SUM(E58:E61) -> 30 | F62: =SUM(F59:F61) -> 4 | G62: =SUM(G59:G61) -> 196.9 | H62: =SUM(H59:H61) -> 142 | I62: =SUM(I59:I61) -> 38.7 | J62: =SUM(J59:J61) -> 16.2 | K62: =SUM(K59:K61) -> 26672.5 | L62: =SUM(L59:L61) -> 5297.5 | M62: =SUM(M59:M61) -> 19150 | N62: =SUM(N59:N61) -> 2225 | O62: ='SILK - SOLD'!L345 -> 4568.1
A64: INCOMO (INCO)
A65: CDC | B65: =C65+F65+E65 -> 10 | C65: =COUNTIFS(Table27[#All],"*CDC*") -> 6 | D65: =F65+E65 -> 4 | E65: =COUNTIF(INCO_A[#All],"CDC") -> 4 | F65: =COUNTIF(Table16[#All],"CDC") -> 0 | G65: =H65+I65+J65 -> 50 | H65: =SUMIF(INCO_A[#All],"CDC",INCO_AV[#All]) -> 20 | I65: =SUMIF(Table27[#All],"CDC",INCO_SO[#All]) -> 30 | J65: =SUMIF(Table16[#All],"CDC",Table17[#All]) -> 0 | K65: =M65+L65+N65 -> 6550 | L65: =SUMIF(Table27[#All],"CDC",Table72[#All]) -> 3750 | M65: =SUMIF(INCO_A[#All],"CDC",Table56[#All]) -> 2800 | N65: =SUMIF(Table16[#All],"CDC",Table89[#All]) -> 0
A66: GEORGETTE | B66: =C66+F66+E66 -> 10 | C66: =COUNTIFS(Table27[#All],"*GEORGETTE*") -> 6 | D66: =F66+E66 -> 4 | E66: =COUNTIF(INCO_A[#All],"GEORGETTE") -> 3 | F66: =COUNTIF(Table16[#All],"GEORGETTE") -> 1 | G66: =H66+I66+J66 -> 50 | H66: =SUMIF(INCO_A[#All],"GEORGETTE",INCO_AV[#All]) -> 15 | I66: =SUMIF(Table27[#All],"GEORGETTE",INCO_SO[#All]) -> 30 | J66: =SUMIF(Table16[#All],"GEORGETTE",Table17[#All]) -> 5 | K66: =M66+L66+N66 -> 4925 | L66: =SUMIF(Table27[#All],"GEORGETTE",Table72[#All]) -> 2925 | M66: =SUMIF(INCO_A[#All],"GEORGETTE",Table56[#All]) -> 1500 | N66: =SUMIF(Table16[#All],"GEORGETTE",Table89[#All]) -> 500
A67: STYLE SILK (STYL) TOTAL | B67: =SUM(B64:B66) -> 20 | C67: =SUM(C64:C66) -> 12 | D67: =SUM(D65:D66) -> 8 | E67: =SUM(E63:E66) -> 7 | F67: =SUM(F64:F66) -> 1 | G67: =SUM(G64:G66) -> 100 | H67: =SUM(H64:H66) -> 35 | I67: =SUM(I64:I66) -> 60 | J67: =SUM(J64:J66) -> 5 | K67: =SUM(K64:K66) -> 11475 | L67: =SUM(L64:L66) -> 6675 | M67: =SUM(M64:M66) -> 4300 | N67: =SUM(N64:N66) -> 500 | O67: ='SILK - SOLD'!L362 -> 7665
A69: CARNET (UG)
A70: JACAURD | B70: =C70+F70+E70 -> 11 | C70: =COUNTIFS(Table28[#All],"*JACAURD*") -> 0 | D70: =F70+E70 -> 11 | E70: =COUNTIF(UG_A[#All],"JACAURD") -> 11 | F70: =COUNTIF(Table18[#All],"JACAURD") -> 0 | G70: =H70+I70+J70 -> 55 | H70: =SUMIF(UG_A[#All],"JACAURD",Table40[#All]) -> 55 | I70: =SUMIF(Table28[#All],"JACAURD",Table29[#All]) -> 0 | J70: =SUMIF(Table18[#All],"JACAURD",Table19[#All]) -> 0 | K70: =M70+L70+N70 -> 10500 | L70: =SUMIF(Table28[#All],"JACAURD",Table73[#All]) -> 0 | M70: =SUMIF(UG_A[#All],"JACAURD",Table57[#All]) -> 10500 | N70: =SUMIF(Table18[#All],"JACAURD",Table90[#All]) -> 0
A71: GEORGETTE | B71: =C71+F71+E71 -> 15 | C71: =COUNTIFS(Table28[#All],"*GEORGETTE*") -> 3 | D71: =F71+E71 -> 12 | E71: =COUNTIF(UG_A[#All],"GEORGETTE") -> 12 | F71: =COUNTIF(Table18[#All],"GEORGETTE") -> 0 | G71: =H71+I71+J71 -> 55 | H71: =SUMIF(UG_A[#All],"GEORGETTE",Table40[#All]) -> 45 | I71: =SUMIF(Table28[#All],"GEORGETTE",Table29[#All]) -> 10 | J71: =SUMIF(Table18[#All],"GEORGETTE",Table19[#All]) -> 0 | K71: =M71+L71+N71 -> 9625 | L71: =SUMIF(Table28[#All],"GEORGETTE",Table73[#All]) -> 1750 | M71: =SUMIF(UG_A[#All],"GEORGETTE",Table57[#All]) -> 7875 | N71: =SUMIF(Table18[#All],"GEORGETTE",Table90[#All]) -> 0
A72: CARNET (UG) TOTAL | B72: =SUM(B70:B71) -> 26 | C72: =SUM(C70:C71) -> 3 | D72: =SUM(D70:D71) -> 23 | E72: =SUM(E70:E71) -> 23 | F72: =SUM(F70:F71) -> 0 | G72: =SUM(G70:G71) -> 110 | H72: =SUM(H70:H71) -> 100 | I72: =SUM(I70:I71) -> 10 | ... N72: =SUM(N70:N71) -> 0 | O72: ='SILK - SOLD'!L371 -> 1157.7
A74: CAVALLI+TGM+ROTARY
A75: SATIN | B75: =C75+F75+E75 -> 4 | C75: =COUNTIFS(Table30[#All],"SATIN") -> 2 | D75: =F75+E75 -> 2 | E75: =COUNTIF(CAVA_A[#All],"SATIN") -> 1 | F75: =COUNTIFS(Table46[#All],"SATIN") -> 1 | G75: =H75+I75+J75 -> 19.3 | H75: =SUMIF(CAVA_A[#All],"SATIN",CAVA_AV[#All]) -> 5 | I75: =SUMIF(Table30[#All],"SATIN",CAVA_SO[#All]) -> 9.9 | J75: =SUMIF(Table46[#All],"SATIN",Table24[#All]) -> 4.4 | K75: =M75+L75+N75 -> 3860 | L75: =SUMIF(Table30[#All],"SATIN",Table74[#All]) -> 1980 | M75: =SUMIF(CAVA_A[#All],"SATIN",Table58[#All]) -> 1000 | N75: =SUMIF(Table46[#All],"SATIN",Table91[#All]) -> 880
A76: MILANO_SATIN | B76: =C76+F76+E76 -> 1 | C76: =COUNTIFS(Table30[#All],"MILANO_SATIN") -> 0 | D76: =F76+E76 -> 1 | E76: =COUNTIF(CAVA_A[#All],"MILANO_SATIN") -> 1 | F76: =COUNTIFS(Table46[#All],"MILANO_SATIN") -> 0 | G76: =H76+I76+J76 -> 5 | H76: =SUMIF(CAVA_A[#All],"MILANO_SATIN",CAVA_AV[#All]) -> 5 | I76: =SUMIF(Table30[#All],"MILANO_SATIN",CAVA_SO[#All]) -> 0 | J76: =SUMIF(Table46[#All],"MILANO_SATIN",Table24[#All]) -> 0 | K76: =M76+L76+N76 -> 725 | L76: =SUMIF(Table30[#All],"MILANO_SATIN",Table74[#All]) -> 0 | M76: =SUMIF(CAVA_A[#All],"MILANO_SATIN",Table58[#All]) -> 725 | N76: =SUMIF(Table46[#All],"MILANO_SATIN",Table91[#All]) -> 0
A77: CDC | B77: =C77+F77+E77 -> 4 | C77: =COUNTIFS(Table30[#All],"*CDC*") -> 2 | D77: =F77+E77 -> 2 | E77: =COUNTIF(CAVA_A[#All],"CDC") -> 2 | F77: =COUNTIFS(Table46[#All],"*CDC*") -> 0 | G77: =H77+I77+J77 -> 16.6 | H77: =SUMIF(CAVA_A[#All],"CDC",CAVA_AV[#All]) -> 8.4 | I77: =SUMIF(Table30[#All],"CDC",CAVA_SO[#All]) -> 8.2 | J77: =SUMIF(Table46[#All],"CDC",Table24[#All]) -> 0 | K77: =M77+L77+N77 -> 2324 | L77: =SUMIF(Table30[#All],"CDC",Table74[#All]) -> 1148 | M77: =SUMIF(CAVA_A[#All],"CDC",Table58[#All]) -> 1176 | N77: =SUMIF(Table46[#All],"CDC",Table91[#All]) -> 0
A78: FIL_COUPE | B78: =C78+F78+E78 -> 1 | C78: =COUNTIFS(Table30[#All],"*FIL_COUPE*") -> 0 | D78: =F78+E78 -> 1 | E78: =COUNTIF(CAVA_A[#All],"FIL_COUPE") -> 1 | F78: =COUNTIFS(Table46[#All],"*FIL_COUPE*") -> 0 | G78: =H78+I78+J78 -> 5.8 | H78: =SUMIF(CAVA_A[#All],"FIL_COUPE",CAVA_AV[#All]) -> 5.8 | I78: =SUMIF(Table30[#All],"FIL_COUPE",CAVA_SO[#All]) -> 0 | J78: =SUMIF(Table46[#All],"FIL_COUPE",Table24[#All]) -> 0 | K78: =M78+L78+N78 -> 2900 | L78: =SUMIF(Table30[#All],"FIL_COUPE",Table74[#All]) -> 0 | M78: =SUMIF(CAVA_A[#All],"FIL_COUPE",Table58[#All]) -> 2900 | N78: =SUMIF(Table46[#All],"FIL_COUPE",Table91[#All]) -> 0
A79: GOLD_LUREX | B79: =C79+F79+E79 -> 1 | C79: =COUNTIFS(Table30[#All],"GOLD_LUREX") -> 1 | D79: =F79+E79 -> 0 | E79: =COUNTIF(CAVA_A[#All],"GOLD_LUREX") -> 0 | F79: =COUNTIFS(Table46[#All],"GOLD_LUREX") -> 0 | G79: =H79+I79+J79 -> 5 | H79: =SUMIF(CAVA_A[#All],"GOLD_LUREX",CAVA_AV[#All]) -> 0 | I79: =SUMIF(Table30[#All],"GOLD_LUREX",CAVA_SO[#All]) -> 5 | J79: =SUMIF(Table46[#All],"GOLD_LUREX",Table24[#All]) -> 0 | K79: =M79+L79+N79 -> 2000 | L79: =SUMIF(Table30[#All],"GOLD_LUREX",Table74[#All]) -> 2000 | M79: =SUMIF(CAVA_A[#All],"GOLD_LUREX",Table58[#All]) -> 0 | N79: =SUMIF(Table46[#All],"GOLD_LUREX",Table91[#All]) -> 0
A80: CAVALLI+TGM+ROTARY TOTAL | B80: =SUM(B75:B79) -> 11 | C80: =SUM(C75:C79) -> 5 | D80: =SUM(D75:D79) -> 6 | E80: =SUM(E75:E79) -> 5 | F80: =SUM(F75:F79) -> 1 | G80: =SUM(G75:G79) -> 51.7 | H80: =SUM(H75:H79) -> 24.2 | I80: =SUM(I75:I79) -> 23.1 | ... N80: =SUM(N75:N79) -> 880 | O80: ='SILK - SOLD'!L382 -> 5187.2
A82: RUFFO (RUFF)
A83: CDC | B83: =C83+F83+E83 -> 3 | C83: =COUNTIFS(Table31[#All],"CDC") -> 0 | D83: =F83+E83 -> 3 | E83: =COUNTIF(RUFF_A[#All],"CDC") -> 3 | F83: =COUNTIFS(Table47[#All],"CDC") -> 0 | G83: =H83+I83+J83 -> 15.5 | H83: =SUMIF(RUFF_A[#All],"CDC",RUFFO_A[#All]) -> 15.5 | I83: =SUMIF(Table31[#All],"CDC",RUFFO_SO[#All]) -> 0 | J83: =SUMIF(Table47[#All],"CDC",Table98[#All]) -> 0 | K83: =M83+L83+N83 -> 6200 | L83: =SUMIF(Table31[#All],"CDC",RUFFO_SO[#All]) -> 0 | M83: =SUMIF(RUFF_A[#All],"CDC",Table59[#All]) -> 6200 | N83: =SUMIF(Table47[#All],"CDC",Table92[#All]) -> 0
A84: LUREX_ON_CHIFFON_DELUX | B84: =C84+F84+E84 -> 25 | C84: =COUNTIFS(Table31[#All],"LUREX_ON_CHIFFON_DELUX") -> 2 | D84: =F84+E84 -> 23 | E84: =COUNTIF(RUFF_A[#All],"LUREX_ON_CHIFFON_DELUX") -> 23 | F84: =COUNTIFS(Table47[#All],"LUREX_ON_CHIFFON_DELUX") -> 0 | G84: =H84+I84+J84 -> 125 | H84: =SUMIF(RUFF_A[#All],"LUREX_ON_CHIFFON_DELUX",RUFFO_A[#All]) -> 115 | I84: =SUMIF(Table31[#All],"LUREX_ON_CHIFFON_DELUX",RUFFO_SO[#All]) -> 10 | J84: =SUMIF(Table47[#All],"LUREX_ON_CHIFFON_DELUX",Table98[#All]) -> 0 | K84: =M84+L84+N84 -> 58250 | L84: =SUMIF(Table31[#All],"LUREX_ON_CHIFFON_DELUX",Table75[#All]) -> 5500 | M84: =SUMIF(RUFF_A[#All],"LUREX_ON_CHIFFON_DELUX",Table59[#All]) -> 52750 | N84: =SUMIF(Table47[#All],"LUREX_ON_CHIFFON_DELUX",Table92[#All]) -> 0
A85: RUFFO (RUFF) TOTAL | B85: =SUM(B83:B84) -> 28 | C85: =SUM(C83:C84) -> 2 | D85: =SUM(D83:D84) -> 26 | E85: =SUM(E83:E84) -> 26 | F85: =SUM(F83:F84) -> 0 | G85: =SUM(G83:G84) -> 140.5 | H85: =SUM(H83:H84) -> 130.5 | I85: =SUM(I83:I84) -> 10 | ... N85: =SUM(N83:N84) -> 0 | O85: ='SILK - SOLD'!L389 -> 5060
A87: SETERIE GR(SETE)
A88: CDC | B88: =C88+F88+E88 -> 38 | C88: =COUNTIFS(Table32[#All],"CDC") -> 5 | D88: =F88+E88 -> 33 | E88: =COUNTIF(SETE_A[#All],"CDC") -> 33 | F88: =COUNTIFS(Table99[#All],"CDC") -> 0 | G88: =H88+I88+J88 -> 164.5 | H88: =SUMIF(SETE_A[#All],"CDC",Table41[#All]) -> 138.8 | I88: =SUMIF(Table32[#All],"CDC",SETE_SOL[#All]) -> 25.7 | J88: =SUMIF(Table99[#All],"CDC",Table100[#All]) -> 0 | K88: =M88+L88+N88 -> 18345 | L88: =SUMIF(Table32[#All],"CDC",Table76[#All]) -> 3077 | M88: =SUMIF(SETE_A[#All],"CDC",Table60[#All]) -> 15268 | N88: =SUMIF(Table99[#All],"CDC",Table93[#All]) -> 0
A89: SETERIE GR(SETE) TOTAL | B89: =SUM(B88) -> 38 | C89: =SUM(C88) -> 5 | D89: =SUM(D88) -> 33 | E89: =SUM(E88) -> 33 | F89: =SUM(F88) -> 0 | G89: =SUM(G88) -> 164.5 | H89: =SUM(H88) -> 138.8 | I89: =SUM(I88) -> 25.7 | ... N89: =SUM(N88) -> 0 | O89: ='SILK - SOLD'!L400 -> 4484.6
A91: TESSILE(TESSI)
A92: CDC | B92: =C92+F92+E92 -> 18 | C92: =COUNTIFS(Table33[#All],"CDC") -> 7 | D92: =F92+E92 -> 11 | E92: =COUNTIF(TESSI_A[#All],"CDC") -> 11 | F92: =COUNTIF(Table101[#All],"CDC") -> 0 | G92: =H92+I92+J92 -> 86.1 | H92: =SUMIF(TESSI_A[#All],"CDC",Table42[#All]) -> 55.4 | I92: =SUMIF(Table33[#All],"CDC",TESSI_SO[#All]) -> 30.7 | J92: =SUMIF(Table101[#All],"CDC",Table102[#All]) -> 0 | K92: =M92+L92+N92 -> 10556.5 | L92: =SUMIF(Table33[#All],"CDC",Table77[#All]) -> 4185.5 | M92: =SUMIF(TESSI_A[#All],"CDC",Table61[#All]) -> 6371 | N92: =SUMIF(Table101[#All],"CDC",Table94[#All]) -> 0
A93: GEORGETTE | B93: =C93+F93+E93 -> 12 | C93: =COUNTIFS(Table33[#All],"GEORGETTE") -> 1 | D93: =F93+E93 -> 11 | E93: =COUNTIF(TESSI_A[#All],"GEORGETTE") -> 11 | F93: =COUNTIF(Table101[#All],"GEORGETTE") -> 0 | G93: =H93+I93+J93 -> 59.9 | H93: =SUMIF(TESSI_A[#All],"GEORGETTE",Table42[#All]) -> 54.9 | I93: =SUMIF(Table33[#All],"GEORGETTE",TESSI_SO[#All]) -> 5 | J93: =SUMIF(Table101[#All],"GEORGETTE",Table102[#All]) -> 0 | K93: =M93+L93+N93 -> 5690.5 | L93: =SUMIF(Table33[#All],"GEORGETTE",Table77[#All]) -> 475 | M93: =SUMIF(TESSI_A[#All],"GEORGETTE",Table61[#All]) -> 5215.5 | N93: =SUMIF(Table101[#All],"GEORGETTE",Table94[#All]) -> 0
A94: CHIFFON | B94: =C94+F94+E94 -> 1 | C94: =COUNTIFS(Table33[#All],"CHIFFON") -> 0 | D94: =F94+E94 -> 1 | E94: =COUNTIF(TESSI_A[#All],"CHIFFON") -> 0 | F94: =COUNTIF(Table101[#All],"CHIFFON") -> 1 | G94: =H94+I94+J94 -> 5.5 | H94: =SUMIF(TESSI_A[#All],"CHIFFON",Table42[#All]) -> 0 | I94: =SUMIF(Table33[#All],"CHIFFON",TESSI_SO[#All]) -> 0 | J94: =SUMIF(Table101[#All],"CHIFFON",Table102[#All]) -> 5.5 | K94: =M94+L94+N94 -> 522.5 | L94: =SUMIF(Table33[#All],"CHIFFON",Table77[#All]) -> 0 | M94: =SUMIF(TESSI_A[#All],"CHIFFON",Table61[#All]) -> 0 | N94: =SUMIF(Table101[#All],"CHIFFON",Table94[#All]) -> 522.5
A95: TESSILE(TESSI) TOTAL | B95: =SUM(B92:B94) -> 31 | C95: =SUM(C92:C94) -> 8 | D95: =SUM(D92:D94) -> 23 | E95: =SUM(E92:E94) -> 22 | F95: =SUM(F92:F94) -> 1 | G95: =SUM(G92:G94) -> 151.5 | H95: =SUM(H92:H94) -> 110.3 | I95: =SUM(I92:I94) -> 35.7 | ... N95: =SUM(N92:N94) -> 522.5 | O95: ='SILK - SOLD'!L413 -> 4286.3
A97: QUORUM(QUO)
A98: CDC | B98: =C98+F98+E98 -> 10 | C98: =COUNTIFS(Table34[#All],"CDC") -> 1 | D98: =F98+E98 -> 9 | E98: =COUNTIF(QUO_A[#All],"CDC") -> 9 | F98: =COUNTIF(Table103[#All],"CDC") -> 0 | G98: =H98+I98+J98 -> 50 | H98: =SUMIF(QUO_A[#All],"CDC",QUO_AV[#All]) -> 45.1 | I98: =SUMIF(Table34[#All],"CDC",QUO_SO[#All]) -> 4.9 | J98: =SUMIF(Table103[#All],"CDC",Table104[#All]) -> 0 | K98: =M98+L98+N98 -> 5500 | L98: =SUMIF(Table34[#All],"CDC",Table78[#All]) -> 539 | M98: =SUMIF(QUO_A[#All],"CDC",Table62[#All]) -> 4961 | N98: =SUMIF(Table103[#All],"CDC",Table95[#All]) -> 0
A99: CHIFFON | B99: =C99+F99+E99 -> 1 | C99: =COUNTIFS(Table34[#All],"CHIFFON") -> 0 | D99: =F99+E99 -> 1 | E99: =COUNTIF(QUO_A[#All],"CHIFFON") -> 1 | F99: =COUNTIF(Table103[#All],"CHIFFON") -> 0 | G99: =H99+I99+J99 -> 3.5 | H99: =SUMIF(QUO_A[#All],"CHIFFON",QUO_AV[#All]) -> 3.5 | I99: =SUMIF(Table34[#All],"CHIFFON",QUO_SO[#All]) -> 0 | J99: =SUMIF(Table103[#All],"CHIFFON",Table104[#All]) -> 0 | K99: =M99+L99+N99 -> 350 | L99: =SUMIF(Table34[#All],"CHIFFON",Table78[#All]) -> 0 | M99: =SUMIF(QUO_A[#All],"CHIFFON",Table62[#All]) -> 350 | N99: =SUMIF(Table103[#All],"CHIFFON",Table95[#All]) -> 0
A100: GEORGETTE | B100: =C100+F100+E100 -> 1 | C100: =COUNTIFS(Table34[#All],"GEORGETTE") -> 0 | D100: =F100+E100 -> 1 | E100: =COUNTIF(QUO_A[#All],"GEORGETTE") -> 1 | F100: =COUNTIF(Table103[#All],"GEORGETTE") -> 0 | G100: =H100+I100+J100 -> 5 | H100: =SUMIF(QUO_A[#All],"GEORGETTE",QUO_AV[#All]) -> 5 | I100: =SUMIF(Table34[#All],"GEORGETTE",QUO_SO[#All]) -> 0 | J100: =SUMIF(Table103[#All],"GEORGETTE",Table104[#All]) -> 0 | K100: =M100+L100+N100 -> 500 | L100: =SUMIF(Table34[#All],"GEORGETTE",Table78[#All]) -> 0 | M100: =SUMIF(QUO_A[#All],"GEORGETTE",Table62[#All]) -> 500 | N100: =SUMIF(Table103[#All],"GEORGETTE",Table95[#All]) -> 0
A101: JACQUARD | B101: =C101+F101+E101 -> 2 | C101: =COUNTIFS(Table34[#All],"JACQUARD") -> 0 | D101: =F101+E101 -> 2 | E101: =COUNTIF(QUO_A[#All],"JACQUARD") -> 2 | F101: =COUNTIF(Table103[#All],"JACQUARD") -> 0 | G101: =H101+I101+J101 -> 10 | H101: =SUMIF(QUO_A[#All],"JACQUARD",QUO_AV[#All]) -> 10 | I101: =SUMIF(Table34[#All],"JACQUARD",QUO_SO[#All]) -> 0 | J101: =SUMIF(Table103[#All],"JACQUARD",Table104[#All]) -> 0 | K101: =M101+L101+N101 -> 1000 | L101: =SUMIF(Table34[#All],"JACQUARD",Table78[#All]) -> 0 | M101: =SUMIF(QUO_A[#All],"JACQUARD",Table62[#All]) -> 1000 | N101: =SUMIF(Table103[#All],"JACQUARD",Table95[#All]) -> 0
A102: PRINTED_LACE | B102: =C102+F102+E102 -> 8 | C102: =COUNTIFS(Table34[#All],"PRINTED_LACE") -> 0 | D102: =F102+E102 -> 8 | E102: =COUNTIF(QUO_A[#All],"PRINTED_LACE") -> 7 | F102: =COUNTIF(Table103[#All],"PRINTED_LACE") -> 1 | G102: =H102+I102+J102 -> 36.9 | H102: =SUMIF(QUO_A[#All],"PRINTED_LACE",QUO_AV[#All]) -> 32.4 | I102: =SUMIF(Table34[#All],"PRINTED_LACE",QUO_SO[#All]) -> 0 | J102: =SUMIF(Table103[#All],"PRINTED_LACE",Table104[#All]) -> 4.5 | K102: =M102+L102+N102 -> 3690 | L102: =SUMIF(Table34[#All],"PRINTED_LACE",Table78[#All]) -> 0 | M102: =SUMIF(QUO_A[#All],"PRINTED_LACE",Table62[#All]) -> 3240 | N102: =SUMIF(Table103[#All],"PRINTED_LACE",Table95[#All]) -> 450
A103: SATIN_JACQUARD | B103: =C103+F103+E103 -> 2 | C103: =COUNTIFS(Table34[#All],"SATIN_JACQUARD") -> 0 | D103: =F103+E103 -> 2 | E103: =COUNTIF(QUO_A[#All],"SATIN_JACQUARD") -> 0 | F103: =COUNTIF(Table103[#All],"SATIN_JACQUARD") -> 2 | G103: =H103+I103+J103 -> 12 | H103: =SUMIF(QUO_A[#All],"SATIN_JACQUARD",QUO_AV[#All]) -> 0 | I103: =SUMIF(Table34[#All],"SATIN_JACQUARD",QUO_SO[#All]) -> 0 | J103: =SUMIF(Table103[#All],"SATIN_JACQUARD",Table104[#All]) -> 12 | K103: =M103+L103+N103 -> 1200 | L103: =SUMIF(Table34[#All],"SATIN_JACQUARD",Table78[#All]) -> 0 | M103: =SUMIF(QUO_A[#All],"SATIN_JACQUARD",Table62[#All]) -> 0 | N103: =SUMIF(Table103[#All],"SATIN_JACQUARD",Table95[#All]) -> 1200
A104: QUORUM(QUO) TOTAL | B104: =SUM(B98:B103) -> 24 | C104: =SUM(C98:C103) -> 1 | D104: =SUM(D98:D103) -> 23 | E104: =SUM(E98:E103) -> 20 | F104: =SUM(F98:F103) -> 3 | G104: =SUM(G98:G103) -> 117.4 | H104: =SUM(H98:H103) -> 96 | I104: =SUM(I98:I103) -> 4.9 | ... N104: =SUM(N98:N103) -> 1650 | O104: ='SILK - SOLD'!L423 -> 377.3
A106: SILKOMO (SILKO)
A107: CDC | B107: =C107+F107+E107 -> 11 | C107: =COUNTIFS(Table35[#All],"CDC") -> 7 | D107: =F107+E107 -> 4 | E107: =COUNTIF(SILKO_A[#All],"CDC") -> 3 | F107: =COUNTIF(Table105[#All],"CDC") -> 1 | G107: =H107+I107+J107 -> 54.9 | H107: =SUMIF(SILKO_A[#All],"CDC",Table44[#All]) -> 15 | I107: =SUMIF(Table35[#All],"CDC",SILKO_SO[#All]) -> 35 | J107: =SUMIF(Table105[#All],"CDC",Table106[#All]) -> 4.9 | K107: =M107+L107+N107 -> 7476 | L107: =SUMIF(Table35[#All],"CDC",Table79[#All]) -> 4690 | M107: =SUMIF(SILKO_A[#All],"CDC",Table63[#All]) -> 2100 | N107: =SUMIF(Table105[#All],"CDC",Table96[#All]) -> 686
A108: LUREX | B108: =C108+F108+E108 -> 2 | C108: =COUNTIFS(Table35[#All],"LUREX") -> 2 | D108: =F108+E108 -> 0 | E108: =COUNTIF(SILKO_A[#All],"LUREX") -> 0 | F108: =COUNTIF(Table105[#All],"LUREX") -> 0 | G108: =H108+I108+J108 -> 10 | H108: =SUMIF(SILKO_A[#All],"LUREX",Table44[#All]) -> 0 | I108: =SUMIF(Table35[#All],"LUREX",SILKO_SO[#All]) -> 10 | J108: =SUMIF(Table105[#All],"LUREX",Table106[#All]) -> 0 | K108: =M108+L108+N108 -> 1700 | L108: =SUMIF(Table35[#All],"LUREX",Table79[#All]) -> 1700 | M108: =SUMIF(SILKO_A[#All],"LUREX",Table63[#All]) -> 0 | N108: =SUMIF(Table105[#All],"LUREX",Table96[#All]) -> 0
A109: CHIFFON | B109: =C109+F109+E109 -> 11 | C109: =COUNTIFS(Table35[#All],"CHIFFON") -> 4 | D109: =F109+E109 -> 7 | E109: =COUNTIF(SILKO_A[#All],"CHIFFON") -> 3 | F109: =COUNTIF(Table105[#All],"CHIFFON") -> 4 | G109: =H109+I109+J109 -> 43 | H109: =SUMIF(SILKO_A[#All],"CHIFFON",Table44[#All]) -> 15 | I109: =SUMIF(Table35[#All],"CHIFFON",SILKO_SO[#All]) -> 12 | J109: =SUMIF(Table105[#All],"CHIFFON",Table106[#All]) -> 16 | K109: =M109+L109+N109 -> 4300 | L109: =SUMIF(Table35[#All],"CHIFFON",Table79[#All]) -> 1200 | M109: =SUMIF(SILKO_A[#All],"CHIFFON",Table63[#All]) -> 1500 | N109: =SUMIF(Table105[#All],"CHIFFON",Table96[#All]) -> 1600
A110: QUORUM(QUO) TOTAL | B110: =SUM(B105:B109) -> 24 | C110: =SUM(C105:C109) -> 13 | D110: =SUM(D105:D109) -> 11 | E110: =SUM(E105:E109) -> 6 | F110: =SUM(F105:F109) -> 5 | G110: =SUM(G105:G109) -> 107.9 | H110: =SUM(H105:H109) -> 30 | I110: =SUM(I105:I109) -> 57 | ... N110: =SUM(N105:N109) -> 2286 | O110: ='SILK - SOLD'!L447 -> 7772
A112: NO CODE (NC)
A113: CDC | B113: =C113+F113+E113 -> 33 | C113: =COUNTIFS(Table37[#All],"CDC") -> 16 | D113: =F113+E113 -> 17 | E113: =COUNTIF(NC_A[#All],"CDC") -> 11 | F113: =COUNTIF(Table107[#All],"CDC") -> 6 | G113: =H113+I113+J113 -> 170.1 | H113: =SUMIF(NC_A[#All],"CDC",Table43[#All]) -> 58.3 | I113: =SUMIF(Table37[#All],"CDC",Table38[#All]) -> 81.8 | J113: =SUMIF(Table107[#All],"CDC",Table108[#All]) -> 30 | K113: =M113+L113+N113 -> 18954.5 | L113: =SUMIF(Table37[#All],"CDC",Table80[#All]) -> 8821 | M113: =SUMIF(NC_A[#All],"CDC",Table64[#All]) -> 6583.5 | N113: =SUMIF(Table107[#All],"CDC",Table97[#All]) -> 3550
A114: GEORGETTE | B114: =C114+F114+E114 -> 23 | C114: =COUNTIFS(Table37[#All],"GEORGETTE") -> 5 | D114: =F114+E114 -> 18 | E114: =COUNTIF(NC_A[#All],"GEORGETTE") -> 10 | F114: =COUNTIF(Table107[#All],"GEORGETTE") -> 8 | G114: =H114+I114+J114 -> 106 | H114: =SUMIF(NC_A[#All],"GEORGETTE",Table43[#All]) -> 45.2 | I114: =SUMIF(Table37[#All],"GEORGETTE",Table38[#All]) -> 17.7 | J114: =SUMIF(Table107[#All],"GEORGETTE",Table108[#All]) -> 43.1 | K114: =M114+L114+N114 -> 9600.5 | L114: =SUMIF(Table37[#All],"GEORGETTE",Table80[#All]) -> 2084.5 | M114: =SUMIF(NC_A[#All],"GEORGETTE",Table64[#All]) -> 3893 | N114: =SUMIF(Table107[#All],"GEORGETTE",Table97[#All]) -> 3623
A115: LUREX | B115: =C115+F115+E115 -> 3 | C115: =COUNTIFS(Table37[#All],"LUREX") -> 0 | D115: =F115+E115 -> 3 | E115: =COUNTIF(NC_A[#All],"LUREX") -> 2 | F115: =COUNTIF(Table107[#All],"LUREX") -> 1 | G115: =H115+I115+J115 -> 15 | H115: =SUMIF(NC_A[#All],"LUREX",Table43[#All]) -> 10 | I115: =SUMIF(Table37[#All],"LUREX",Table38[#All]) -> 0 | J115: =SUMIF(Table107[#All],"LUREX",Table108[#All]) -> 5 | K115: =M115+L115+N115 -> 2550 | L115: =SUMIF(Table37[#All],"LUREX",Table80[#All]) -> 0 | M115: =SUMIF(NC_A[#All],"LUREX",Table64[#All]) -> 1700 | N115: =SUMIF(Table107[#All],"LUREX",Table97[#All]) -> 850
A116: NO CODE (NC) TOTAL | B116: =SUM(B113:B115) -> 59 | C116: =SUM(C113:C115) -> 21 | D116: =SUM(D113:D115) -> 38 | E116: =SUM(E113:E115) -> 23 | F116: =SUM(F113:F115) -> 15 | G116: =SUM(G113:G115) -> 291.1 | H116: =SUM(H113:H115) -> 113.5 | I116: =SUM(I113:I115) -> 99.5 | ... N116: =SUM(N113:N115) -> 8023 | O116: ='SILK - SOLD'!L473 -> 14621.7
...

Sheet SILK - ALL
A1: UPDATED ON | F1: UPDATED BY IBRAHIM
A2: DESCRIPTION 31 OCT 2024 | D2: PIECES | F2: VIP-M | I2: NOTED: SOME LINEATRE (LINEA) NOT LISTED .COZ OF SHORT PIECES
A3: TOTAL | D3: 1058 | F3: Sherry - S | H3: PENDING-P
A4: RESERVED (M-30+30+20) | F4: Angie - A
A5: PENDING OUT OFFICE( C-30,K-4,FK-43) | F5: Fong king - FK | I5: Total Cost | K5: =H83+H189+H321+H402+H448+H481+H497+H535+H547+H575+H586+H617+H655+H682+H707+H718+H746 -> 449941.02
A6: SOLD | F6: Bani -B
A7: AVAILABLE | D7: =D3-(D4+D5+D6) -> 1058 | F7: MR. Cetin- C | I7: TOTAL METERS | K7: =E83+E189+E321+E402+E448+E481+E497+E535+E547+E575+E586+E617+E655+E682+E707+E718+E746+8 -> 3249.3
F8: MS. KLARA-K
A10: AVAILABLE
A11: M&M 1-70
A12: NO | B12: DESIGN | C12: ARTICLE | D12: QUALITY | E12: QTY | F12: COST PER MT EURO | G12: COST PER MT RM | H12: COST PIECE RM | I12: V.I.P PER MT RM | J12: V.I.P PIECE RM | K12: SELLING PER MT RM LESS 50% | L12: SELLING PIECE RM | M12: SOLD TO
A13: 1 | B13: VSS-1A | C13: ALB-103A | D13: CDC | E13: 6.1 | F13: 19 | G13: =F13*5 -> 95 | H13: =G13*E13 -> 579.5 | I13: 720 | J13: =I13*E13 -> 4392 | K13: =I13/2 -> 360 | L13: =K13*E13 -> 2196
A14: 2 | B14: VSS-3A | C14: AVAN-18A | D14: CDC | E14: 5 | F14: 23 | G14: =F14*5 -> 115 | H14: =G14*E14 -> 575 | I14: 720 | J14: =I14*E14 -> 3600 | K14: =I14/2 -> 360 | L14: =K14*E14 -> 1800
A15: 3 | B15: VSS-4A | C15: AVAN-39A | D15: CDC | E15: 5 | F15: 23 | G15: =F15*5 -> 115 | H15: =G15*E15 -> 575 | I15: 720 | J15: =I15*E15 -> 3600 | K15: =I15/2 -> 360 | L15: =K15*E15 -> 1800
A16: 4 | B16: NOO-4B | C16: AVAN-39B | D16: GEORGETTE | E16: 5 | F16: 19 | G16: =F16*5 -> 95 | H16: =G16*E16 -> 475 | I16: 720 | J16: =I16*E16 -> 3600 | K16: =I16/2 -> 360 | L16: =K16*E16 -> 1800
A17: 5 | B17: VSS-5A | C17: AVAN-16 | D17: CDC | E17: 5 | F17: 23 | G17: =F17*5 -> 115 | H17: =G17*E17 -> 575 | I17: 720 | J17: =I17*E17 -> 3600 | K17: =I17/2 -> 360 | L17: =K17*E17 -> 1800
A18: 6 | B18: VSS-6A | C18: AVAN-35A | D18: CDC | E18: 5 | F18: 23 | G18: =F18*5 -> 115 | H18: =G18*E18 -> 575 | I18: 720 | J18: =I18*E18 -> 3600 | K18: =I18/2 -> 360 | L18: =K18*E18 -> 1800
A19: 7 | B19: NOO-6B | C19: AVAN-35B | D19: GEORGETTE | E19: 5 | F19: 19 | G19: =F19*5 -> 95 | H19: =G19*E19 -> 475 | I19: 720 | J19: =I19*E19 -> 3600 | K19: =I19/2 -> 360 | L19: =K19*E19 -> 1800
A20: 8 | B20: VSS-7A | C20: AVAN-24A | D20: CDC | E20: 5 | F20: 23 | G20: =F20*5 -> 115 | H20: =G20*E20 -> 575 | I20: 720 | J20: =I20*E20 -> 3600 | K20: =I20/2 -> 360 | L20: =K20*E20 -> 1800
A21: 9 | B21: NOO-7B | C21: AVAN-24B | D21: GEORGETTE | E21: 5 | F21: 19 | G21: =F21*5 -> 95 | H21: =G21*E21 -> 475 | I21: 720 | J21: =I21*E21 -> 3600 | K21: =I21/2 -> 360 | L21: =K21*E21 -> 1800
A22: 10 | B22: VSS-10A | C22: INCO-24A | D22: CDC | E22: 5 | F22: 23.5 | G22: =F22*5 -> 117.5 | H22: =G22*E22 -> 587.5 | I22: 720 | J22: =I22*E22 -> 3600 | K22: =I22/2 -> 360 | L22: =K22*E22 -> 1800
A23: 11 | B23: VSS-13A | C23: INCO-15A | D23: CDC | E23: 5 | F23: 23.5 | G23: =F23*5 -> 117.5 | H23: =G23*E23 -> 587.5 | I23: 720 | J23: =I23*E23 -> 3600 | K23: =I23/2 -> 360 | L23: =K23*E23 -> 1800
A24: 12 | B24: NOO-13B | C24: INCO-15B | D24: GEORGETTE | E24: 5 | F24: 19.5 | G24: =F24*5 -> 97.5 | H24: =G24*E24 -> 487.5 | I24: 720 | J24: =I24*E24 -> 3600 | K24: =I24/2 -> 360 | L24: =K24*E24 -> 1800
... A82: 70 | B82: NOO-66B | C82: ALB-90B | D82: GEORGETTE | E82: 5 | F82: 22 | G82: =F82*5 -> 110 | H82: =G82*E82 -> 550 | I82: 720 | J82: =I82*E82 -> 3600 | K82: =I82/2 -> 360 | L82: =K82*E82 -> 1800
A83: TOTAL COST | D83: =COUNTA(M7M_A[QUALITY]) -> 70 | E83: =SUM(E13:E82) -> 337.2 | H83: =SUM(H13:H82) -> 40248
A86: ARGOMENTI (ARGO)
A87: NO | B87: DESIGN | C87: ARTICLE | D87: QUALITY | E87: QTY | F87: COST PER MT EURO | G87: COST PER MT RM | H87: COST PIECE RM | I87: V.I.P PER MT RM | J87: V.I.P PIECE RM | K87: SELLING PER MT RM LESS 50% | L87: SELLING PIECE RM | M87: SOLD TO
A88: 71 | B88: DUSS-101A | C88: ARGO-31 | D88: LUREX | E88: 6 | F88: 34 | G88: =F88*5 -> 170 | H88: =E88*G88 -> 1020 | I88: =G88*5 -> 850 | J88: =I88*E88 -> 5100 | K88: =I88/2 -> 425 | L88: =K88*E88 -> 2550
A89: 72 | B89: VVS-101B | C89: ARGO-31A | D89: CDC | E89: 5.5 | F89: 28 | G89: =F89*5 -> 140 | H89: =E89*G89 -> 770 | I89: 720 | J89: =I89*E89 -> 3960 | K89: =I89/2 -> 360 | L89: =K89*E89 -> 1980
A90: 73 | B90: DUSS-102A | C90: ARGO-33 | D90: LUREX | E90: 6 | F90: 34 | G90: =F90*5 -> 170 | H90: =E90*G90 -> 1020 | I90: =G90*5 -> 850 | J90: =I90*E90 -> 5100 | K90: =I90/2 -> 425 | L90: =K90*E90 -> 2550
A91: 74 | B91: DDSS-103A | C91: ARGO-32 | D91: LUREX | E91: 5.5 | F91: 34 | G91: =F91*5 -> 170 | H91: =E91*G91 -> 935 | I91: =G91*5 -> 850 | J91: =I91*E91 -> 4675 | K91: =I91/2 -> 425 | L91: =K91*E91 -> 2337.5
A92: 75 | B92: VVS-103B | C92: ARGO-32A | D92: CDC | E92: 5.5 | F92: 28 | G92: =F92*5 -> 140 | H92: =E92*G92 -> 770 | I92: 720 | J92: =I92*E92 -> 3960 | K92: =I92/2 -> 360 | L92: =K92*E92 -> 1980
A93: 76 | B93: DSSS-104A | C93: ARGO-17 | D93: LUREX | E93: 5 | F93: 34 | G93: =F93*5 -> 170 | H93: =E93*G93 -> 850 | I93: =G93*5 -> 850 | J93: =I93*E93 -> 4250 | K93: =I93/2 -> 425 | L93: =K93*E93 -> 2125
A94: 77 | B94: DUSS-104B | C94: ARGO-17A | D94: CDC | E94: 7 | F94: 28 | G94: =F94*5 -> 140 | H94: =E94*G94 -> 980 | I94: 720 | J94: =I94*E94 -> 5040 | K94: =I94/2 -> 360 | L94: =K94*E94 -> 2520
A95: 78 | B95: DSSS-105A | C95: ARGO-11 | D95: LUREX | E95: 5 | F95: 34 | G95: =F95*5 -> 170 | H95: =E95*G95 -> 850 | I95: =G95*5 -> 850 | J95: =I95*E95 -> 4250 | K95: =I95/2 -> 425 | L95: =K95*E95 -> 2125
A96: 79 | B96: DUSS-105B | C96: ARGO-11A | D96: CDC | E96: 7.5 | F96: 28 | G96: =F96*5 -> 140 | H96: =E96*G96 -> 1050 | I96: 720 | J96: =I96*E96 -> 5400 | K96: =I96/2 -> 360 | L96: =K96*E96 -> 2700
A97: 80 | B97: DSSS-106A | C97: ARGO-16 | D97: LUREX | E97: 5 | F97: 34 | G97: =F97*5 -> 170 | H97: =E97*G97 -> 850 | I97: =G97*5 -> 850 | J97: =I97*E97 -> 4250 | K97: =I97/2 -> 425 | L97: =K97*E97 -> 2125
A98: 81 | B98: VVS-106B | C98: ARGO-16A | D98: CDC | E98: 5.5 | F98: 28 | G98: =F98*5 -> 140 | H98: =E98*G98 -> 770 | I98: 720 | J98: =I98*E98 -> 3960 | K98: =I98/2 -> 360 | L98: =K98*E98 -> 1980
A99: 82 | B99: DSSS-107A | C99: ARGO-12 | D99: CDC | E99: 5 | F99: 28 | G99: =F99*5 -> 140 | H99: =E99*G99 -> 700 | I99: 720 | J99: =I99*E99 -> 3600 | K99: =I99/2 -> 360 | L99: =K99*E99 -> 1800
A100: 83 | B100: ENS-107B | C100: ARGO-12A | D100: CDC | E100: 6 | F100: 28 | G100: =F100*5 -> 140 | H100: =E100*G100 -> 840 | I100: 720 | J100: =I100*E100 -> 4320 | K100: =I100/2 -> 360 | L100: =K100*E100 -> 2160
A101: 84 | B101: DSSS-108A | C101: ARGO-5 | D101: LUREX | E101: 5 | F101: 34 | G101: =F101*5 -> 170 | H101: =E101*G101 -> 850 | I101: =G101*5 -> 850 | J101: =I101*E101 -> 4250 | K101: =I101/2 -> 425 | L101: =K101*E101 -> 2125
A102: 85 | B102: VVS-108B | C102: ARGO-5A | D102: CDC | E102: 5.5 | F102: 28 | G102: =F102*5 -> 140 | H102: =E102*G102 -> 770 | I102: 720 | J102: =I102*E102 -> 3960 | K102: =I102/2 -> 360 | L102: =K102*E102 -> 1980
A103: 86 | B103: ENS-109A | C103: ARGO-48 | D103: LUREX | E103: 4.8 | F103: 34 | G103: =F103*5 -> 170 | H103: =E103*G103 -> 816 | I103: =G103*5 -> 850 | J103: =I103*E103 -> 4080 | K103: =I103/2 -> 425 | L103: =K103*E103 -> 2040
A104: 87 | B104: VVS-109B | C104: ARGO-48A | D104: CDC | E104: 5.5 | F104: 28 | G104: =F104*5 -> 140 | H104: =E104*G104 -> 770 | I104: 720 | J104: =I104*E104 -> 3960 | K104: =I104/2 -> 360 | L104: =K104*E104 -> 1980
A105: 88 | B105: DSSS-110A | C105: ARGO-24 | D105: LUREX | E105: 5 | F105: 34 | G105: =F105*5 -> 170 | H105: =E105*G105 -> 850 | I105: =G105*5 -> 850 | J105: =I105*E105 -> 4250 | K105: =I105/2 -> 425 | L105: =K105*E105 -> 2125
A106: 89 | B106: DDSS-110B | C106: ARGO-24A | D106: CDC | E106: 6.5 | F106: 28 | G106: =F106*5 -> 140 | H106: =E106*G106 -> 910 | I106: 720 | J106: =I106*E106 -> 4680 | K106: =I106/2 -> 360 | L106: =K106*E106 -> 2340
A107: 90 | B107: DSSS-111A | C107: ARGO-25 | D107: LUREX | E107: 5 | F107: 34 | G107: =F107*5 -> 170 | H107: =E107*G107 -> 850 | I107: =G107*5 -> 850 | J107: =I107*E107 -> 4250 | K107: =I107/2 -> 425 | L107: =K107*E107 -> 2125
A108: 91 | B108: VVS-111B | C108: ARGO-25A | D108: CDC | E108: 5.5 | F108: 28 | G108: =F108*5 -> 140 | H108: =E108*G108 -> 770 | I108: 720 | J108: =I108*E108 -> 3960 | K108: =I108/2 -> 360 | L108: =K108*E108 -> 1980
A109: 92 | B109: DSSS-112A | C109: ARGO-20 | D109: LUREX | E109: 5 | F109: 34 | G109: =F109*5 -> 170 | H109: =E109*G109 -> 850 | I109: =G109*5 -> 850 | J109: =I109*E109 -> 4250 | K109: =I109/2 -> 425 | L109: =K109*E109 -> 2125
A110: 93 | B110: VSS-112B | C110: ARGO-20A | D110: CDC | E110: 5 | F110: 28 | G110: =F110*5 -> 140 | H110: =E110*G110 -> 700 | I110: 720 | J110: =I110*E110 -> 3600 | K110: =I110/2 -> 360 | L110: =K110*E110 -> 1800
A111: 94 | B111: DSSS-113A | C111: ARGO-46 | D111: LUREX | E111: 5 | F111: 34 | G111: =F111*5 -> 170 | H111: =E111*G111 -> 850 | I111: =G111*5 -> 850 | J111: =I111*E111 -> 4250 | K111: =I111/2 -> 425 | L111: =K111*E111 -> 2125
A112: 95 | B112: VSS-113B | C112: ARGO-46A | D112: CDC | E112: 5 | F112: 28 | G112: =F112*5 -> 140 | H112: =E112*G112 -> 700 | I112: 720 | J112: =I112*E112 -> 3600 | K112: =I112/2 -> 360 | L112: =K112*E112 -> 1800
A113: 96 | B113: DSSS-114A | C113: ARGO-22 | D113: LUREX | E113: 4.9 | F113: 34 | G113: =F113*5 -> 170 | H113: =E113*G113 -> 833 | I113: =G113*5 -> 850 | J113: =I113*E113 -> 4165 | K113: =I113/2 -> 425 | L113: =K113*E113 -> 2082.5
A114: 97 | B114: VSS-114B | C114: ARGO-22A | D114: CDC | E114: 5 | F114: 28 | G114: 140 | H114: 700 | I114: 720 | J114: 3600 | K114: 360 | L114: 1800
A115: 98 | B115: DSSS-115A | C115: ARGO-23 | D115: LUREX | E115: 5 | F115: 34 | G115: =F115*5 -> 170 | H115: =E115*G115 -> 850 | I115: =G115*5 -> 850 | J115: =I115*E115 -> 4250 | K115: =I115/2 -> 425 | L115: =K115*E115 -> 2125
A116: 99 | B116: VVS-115B | C116: ARGO-23A | D116: CDC | E116: 5.5 | F116: 28 | G116: =F116*5 -> 140 | H116: =E116*G116 -> 770 | I116: 720 | J116: =I116*E116 -> 3960 | K116: =I116/2 -> 360 | L116: =K116*E116 -> 1980
A117: 100 | B117: VVS-116B | C117: ARGO-39A | D117: CDC | E117: 5.5 | F117: 28 | G117: =F117*5 -> 140 | H117: =E117*G117 -> 770 | I117: 720 | J117: =I117*E117 -> 3960 | K117: =I117/2 -> 360 | L117: =K117*E117 -> 1980
A118: 101 | B118: DSSS-117A | C118: ARGO-42 | D118: LUREX | E118: 5 | F118: 34 | G118: =F118*5 -> 170 | H118: =E118*G118 -> 850 | I118: =G118*5 -> 850 | J118: =I118*E118 -> 4250 | K118: =I118/2 -> 425 | L118: =K118*E118 -> 2125
A119: 102 | B119: VVS-117B | C119: ARGO-42A | D119: CDC | E119: 5.5 | F119: 28 | G119: =F119*5 -> 140 | H119: =E119*G119 -> 770 | I119: 720 | J119: =I119*E119 -> 3960 | K119: =I119/2 -> 360 | L119: =K119*E119 -> 1980
A120: 103 | B120: ENS-118S | C120: ARGO-26S | D120: CDC | E120: 6 | F120: 28 | G120: =F120*5 -> 140 | H120: =E120*G120 -> 840 | I120: 720 | J120: =I120*E120 -> 4320 | K120: =I120/2 -> 360 | L120: =K120*E120 -> 2160
A121: 104 | B121: VSS-119A | C121: ARGO-62A | D121: CDC | E121: 5 | F121: 28 | G121: =F121*5 -> 140 | H121: =E121*G121 -> 700 | I121: 720 | J121: =I121*E121 -> 3600 | K121: =I121/2 -> 360 | L121: =K121*E121 -> 1800
A122: 105 | B122: NSS-119B | C122: ARGO-62B | D122: GEORGETTE | E122: 5 | F122: 22 | G122: =F122*5 -> 110 | H122: =E122*G122 -> 550 | I122: 720 | J122: =I122*E122 -> 3600 | K122: =I122/2 -> 360 | L122: =K122*E122 -> 1800
A123: 106 | B123: VSS-120A | C123: ARGO-53A | D123: CDC | E123: 5 | F123: 28 | G123: =F123*5 -> 140 | H123: =E123*G123 -> 700 | I123: 720 | J123: =I123*E123 -> 3600 | K123: =I123/2 -> 360 | L123: =K123*E123 -> 1800
A124: 107 | B124: NSS-120B | C124: ARGO-53B | D124: GEORGETTE | E124: 5 | F124: 22 | G124: =F124*5 -> 110 | H124: =E124*G124 -> 550 | I124: 720 | J124: =I124*E124 -> 3600 | K124: =I124/2 -> 360 | L124: =K124*E124 -> 1800
A125: 108 | B125: NSS-121B | C125: ARGO-51A | D125: GEORGETTE | E125: 5 | F125: 22 | G125: =F125*5 -> 110 | H125: =E125*G125 -> 550 | I125: 720 | J125: =I125*E125 -> 3600 | K125: =I125/2 -> 360 | L125: =K125*E125 -> 1800
A126: 109 | B126: DDSS-122A | C126: ARGO-55 | D126: CDC | E126: 6.5 | F126: 28 | G126: =F126*5 -> 140 | H126: =E126*G126 -> 910 | I126: 720 | J126: =I126*E126 -> 4680 | K126: =I126/2 -> 360 | L126: =K126*E126 -> 2340
A127: 110 | B127: NSS-122B | C127: ARGO-55A | D127: GEORGETTE | E127: 5 | F127: 22 | G127: =F127*5 -> 110 | H127: =E127*G127 -> 550 | I127: 720 | J127: =I127*E127 -> 3600 | K127: =I127/2 -> 360 | L127: =K127*E127 -> 1800
A128: 111 | B128: VSS-123A | C128: ARGO-63 | D128: CDC | E128: 5 | F128: 28 | G128: =F128*5 -> 140 | H128: =E128*G128 -> 700 | I128: 720 | J128: =I128*E128 -> 3600 | K128: =I128/2 -> 360 | L128: =K128*E128 -> 1800
A129: 112 | B129: NSS-123B | C129: ARGO-63A | D129: GEORGETTE | E129: 5 | F129: 22 | G129: =F129*5 -> 110 | H129: =E129*G129 -> 550 | I129: 720 | J129: =I129*E129 -> 3600 | K129: =I129/2 -> 360 | L129: =K129*E129 -> 1800
A130: 113 | B130: DDAS-124 | C130: ARGO-77S | D130: CDC | E130: 7 | F130: 28 | G130: =F130*5 -> 140 | H130: =E130*G130 -> 980 | I130: 720 | J130: =I130*E130 -> 5040 | K130: =I130/2 -> 360 | L130: =K130*E130 -> 2520
... A137: 120 | B137: VVS-601B | C137: ARGO-4A | D137: CDC | E137: 5.5 | F137: 28 | G137: =F137*5 -> 140 | H137: =E137*G137 -> 770 | I137: 720 | J137: =I137*E137 -> 3960 | K137: =I137/2 -> 360 | L137: =K137*E137 -> 1980
A138: 121 | B138: DSSS-602A | C138: ARGO-49 | D138: LUREX | E138: 5 | F138: 34 | G138: =F138*5 -> 170 | H138: =E138*G138 -> 850 | I138: =G138*5 -> 850 | J138: =I138*E138 -> 4250 | K138: =I138/2 -> 425 | L138: =K138*E138 -> 2125
A139: 122 | B139: ESS-603A | C139: ARGO-65 | D139: CDC | E139: 5.6 | F139: 28 | G139: =F139*5 -> 140 | H139: =E139*G139 -> 784 | I139: 720 | J139: =I139*E139 -> 4032 | K139: =I139/2 -> 360 | L139: =K139*E139 -> 2016
A140: 123 | B140: NSS-603B | C140: ARGO-65A | D140: GEORGETTE | E140: 5 | F140: 22 | G140: =F140*5 -> 110 | H140: =E140*G140 -> 550 | I140: 720 | J140: =I140*E140 -> 3600 | K140: =I140/2 -> 360 | L140: =K140*E140 -> 1800
A141: 124 | B141: DSSS-604A | C141: ARGO-13 | D141: LUREX | E141: 5 | F141: 34 | G141: =F141*5 -> 170 | H141: =E141*G141 -> 850 | I141: =G141*5 -> 850 | J141: =I141*E141 -> 4250 | K141: =I141/2 -> 425 | L141: =K141*E141 -> 2125
A142: 125 | B142: VVS-604B | C142: ARGO-13A | D142: CDC | E142: 5.5 | F142: 28 | G142: =F142*5 -> 140 | H142: =E142*G142 -> 770 | I142: 720 | J142: =I142*E142 -> 3960 | K142: =I142/2 -> 360 | L142: =K142*E142 -> 1980
A143: 126 | B143: VSS-605A | C143: ARGO-68A | D143: CDC | E143: 5 | F143: 28 | G143: =F143*5 -> 140 | H143: =E143*G143 -> 700 | I143: 720 | J143: =I143*E143 -> 3600 | K143: =I143/2 -> 360 | L143: =K143*E143 -> 1800
A144: 127 | B144: NSS-605B | C144: ARGO-68B | D144: GEORGETTE | E144: 5 | F144: 22 | G144: =F144*5 -> 110 | H144: =E144*G144 -> 550 | I144: 720 | J144: =I144*E144 -> 3600 | K144: =I144/2 -> 360 | L144: =K144*E144 -> 1800
A145: 128 | B145: VSS-606 | C145: ARGO-93APT | D145: SATIN | E145: 5 | F145: 28 | G145: =F145*5 -> 140 | H145: =E145*G145 -> 700 | I145: 800 | J145: =I145*E145 -> 4000 | K145: =I145/2 -> 400 | L145: =K145*E145 -> 2000
A146: 129 | B146: VSS-607 | C146: ARGO-33APT | D146: SATIN | E146: 5 | F146: 28 | G146: =F146*5 -> 140 | H146: =E146*G146 -> 700 | I146: 800 | J146: =I146*E146 -> 4000 | K146: =I146/2 -> 400 | L146: =K146*E146 -> 2000
A147: 130 | B147: DSSS-608 | C147: ARGO-73 | D147: CDC | E147: 6 | F147: 28 | G147: =F147*5 -> 140 | H147: =E147*G147 -> 840 | I147: 720 | J147: =I147*E147 -> 4320 | K147: =I147/2 -> 360 | L147: =K147*E147 -> 2160
A148: 131 | B148: VSS-611 | C148: ARGO-101 | D148: CDC | E148: 5 | F148: 28 | G148: =F148*5 -> 140 | H148: =E148*G148 -> 700 | I148: 720 | J148: =I148*E148 -> 3600 | K148: =I148/2 -> 360 | L148: =K148*E148 -> 1800
A149: 132 | B149: VVS-612 | C149: ARGO-41A | D149: CDC | E149: 5.5 | F149: 28 | G149: =F149*5 -> 140 | H149: =E149*G149 -> 770 | I149: =G149*5 -> 700 | J149: =I149*E149 -> 3850 | K149: =I149/2 -> 350 | L149: =K149*E149 -> 1925
A150: 133 | B150: VVS-614 | C150: ARGO-50A | D150: CDC | E150: 5.5 | F150: 28 | G150: =F150*5 -> 140 | H150: =E150*G150 -> 770 | I150: =G150*5 -> 700 | J150: =I150*E150 -> 3850 | K150: =I150/2 -> 350 | L150: =K150*E150 -> 1925
A151: 134 | B151: DSSS-615 | C151: ARGO-66 | D151: CDC | E151: 6 | F151: 28 | G151: =F151*5 -> 140 | H151: =E151*G151 -> 840 | I151: =G151*5 -> 700 | J151: =I151*E151 -> 4200 | K151: =I151/2 -> 350 | L151: =K151*E151 -> 2100
A152: 135 | B152: DSSS-616A | C152: ARGO-18 | D152: LUREX | E152: 5 | F152: 34 | G152: =F152*5 -> 170 | H152: =E152*G152 -> 850 | I152: =G152*5 -> 850 | J152: =I152*E152 -> 4250 | K152: =I152/2 -> 425 | L152: =K152*E152 -> 2125
A153: 136 | B153: VSS-616B | C153: ARGO-18A | D153: CDC | E153: 5 | F153: 28 | G153: =F153*5 -> 140 | H153: =E153*G153 -> 700 | I153: 720 | J153: =I153*E153 -> 3600 | K153: =I153/2 -> 360 | L153: =K153*E153 -> 1800
A154: 137 | B154: VSS-617 | C154: ARGO-177APT | D154: CDC | E154: 5 | F154: 28 | G154: =F154*5 -> 140 | H154: =E154*G154 -> 700 | I154: 720 | J154: =I154*E154 -> 3600 | K154: =I154/2 -> 360 | L154: =K154*E154 -> 1800
A155: 138 | B155: DSSS-619 | C155: ARGO-71 | D155: LUREX | E155: 5 | F155: 34 | G155: =F155*5 -> 170 | H155: =E155*G155 -> 850 | I155: =G155*5 -> 850 | J155: =I155*E155 -> 4250 | K155: =I155/2 -> 425 | L155: =K155*E155 -> 2125
A156: 139 | B156: DSSS-620 | C156: ARGO-28 | D156: LUREX | E156: 5 | F156: 34 | G156: =F156*5 -> 170 | H156: =E156*G156 -> 850 | I156: =G156*5 -> 850 | J156: =I156*E156 -> 4250 | K156: =I156/2 -> 425 | L156: =K156*E156 -> 2125
A157: 140 | B157: DSSS-621 | C157: ARGO-93APT | D157: LUREX | E157: 5 | F157: 34 | G157: =F157*5 -> 170 | H157: =E157*G157 -> 850 | I157: =G157*5 -> 850 | J157: =I157*E157 -> 4250 | K157: =I157/2 -> 425 | L157: =K157*E157 -> 2125
A158: 141 | B158: DSSS-622 | C158: ARGO-6 | D158: LUREX | E158: 5 | F158: 34 | G158: 170 | H158: 850 | I158: 850 | J158: 4250 | K158: 425 | L158: 2125
A159: 142 | B159: DSSS-623 | C159: ARGO-268 | D159: LUREX | E159: 5 | F159: 34 | G159: =F159*5 -> 170 | H159: =E159*G159 -> 850 | I159: =G159*5 -> 850 | J159: =I159*E159 -> 4250 | K159: =I159/2 -> 425 | L159: =K159*E159 -> 2125
A160: 143 | B160: DSSS-624 | C160: ARGO-47 | D160: LUREX | E160: 5 | F160: 34 | G160: =F160*5 -> 170 | H160: =E160*G160 -> 850 | I160: =G160*5 -> 850 | J160: =I160*E160 -> 4250 | K160: =I160/2 -> 425 | L160: =K160*E160 -> 2125
A161: 144 | B161: DSSS-625 | C161: ARGO-27 | D161: LUREX | E161: 5 | F161: 34 | G161: =F161*5 -> 170 | H161: =E161*G161 -> 850 | I161: =G161*5 -> 850 | J161: =I161*E161 -> 4250 | K161: =I161/2 -> 425 | L161: =K161*E161 -> 2125
A162: 145 | B162: DSSS-626 | C162: ARGO-44 | D162: LUREX | E162: 5 | F162: 34 | G162: =F162*5 -> 170 | H162: =E162*G162 -> 850 | I162: =G162*5 -> 850 | J162: =I162*E162 -> 4250 | K162: =I162/2 -> 425 | L162: =K162*E162 -> 2125
A163: 146 | B163: DSSS-627 | C163: ARGO-243 | D163: LUREX_CHIFFON | E163: 5 | F163: 22 | G163: =F163*5 -> 110 | H163: =E163*G163 -> 550 | I163: 800 | J163: =I163*E163 -> 4000 | K163: =I163/2 -> 400 | L163: =K163*E163 -> 2000
A164: 147 | B164: DSSS-628 | C164: ARGO-30 | D164: LUREX_CHIFFON | E164: 5 | F164: 22 | G164: =F164*5 -> 110 | H164: =E164*G164 -> 550 | I164: 800 | J164: =I164*E164 -> 4000 | K164: =I164/2 -> 400 | L164: =K164*E164 -> 2000
A165: 148 | B165: DSSS-629 | C165: ARGO-1 | D165: LUREX | E165: 5 | F165: 34 | G165: =F165*5 -> 170 | H165: =E165*G165 -> 850 | I165: =G165*5 -> 850 | J165: =I165*E165 -> 4250 | K165: =I165/2 -> 425 | L165: =K165*E165 -> 2125
A166: 149 | B166: DSSS-630 | C166: ARGO-2 | D166: LUREX | E166: 5 | F166: 34 | G166: =F166*5 -> 170 | H166: =E166*G166 -> 850 | I166: =G166*5 -> 850 | J166: =I166*E166 -> 4250 | K166: =I166/2 -> 425 | L166: =K166*E166 -> 2125
...

Sheet SILK - SOLD
A1: UPDATED ON | F1: UPDATED BY IBRAHIM
A2: DESCRIPTION 31 OCT 2024 | D2: PIECES | F2: VIP-M | I2: NOTED: SOME LINEATRE (LINEA) NOT LISTED .COZ OF SHORT PIECES
A3: TOTAL | D3: 1054 | F3: Sherry - S | H3: PENDING-P
A4: RESERVED (M-30+20) | D4: 50 | F4: Angie - A | I4: Total Cost | K4: =K79+K107+K171+K267+K281+K300+K330+K345+K362+K371+K382+K389+K400+K413+K423+K447+K473 -> 224661.1
A5: PENDING OUT OFFICE( C-30,K-4,S-9) | D5: =30+4+9 -> 43 | F5: Fong king - FK | I5: NET PROFIT | K5: =L79+L107+L171+L267+L281+L300+L330+L345+L362+L371+L382+L389+L400+L413+L423+L447+L473 -> 210978.91
A6: SOLD | D6: =C79+C107+C171+C267+C281+C300+C330+C345+C362+C371+C382+C389+C400+C413+C423+C447+C473 -> 360 | F6: Bani -B
A7: AVAILABLE | D7: =D3-(D4+D5+D6) -> 601 | F7: MR. Cetin- C
F8: MS. KLARA-K
A11: M&M 1-70
A12: SOLD
A13: NO | B13: DESIGN | C13: ARTICLE | D13: QUALITY | E13: QTY | F13: PRICE PER MT | G13: PRICE PER PIECE | H13: NET PRICE AFTER DISCOUNT | I13: COM % | J13: LESS COMMISSION PER PC | K13: COST PER PC | L13: NET PROFIT PER PC | M13: SOLD TO
A14: 1 | B14: VSS-22A | C14: STYL-16A | D14: CDC | E14: 5 | F14: 720 | G14: =F14*E14 -> 3600 | H14: 1800 | I14: 0.2 | J14: =H14*(1-I14) -> 1440 | K14: 700 | L14: 560 | M14: M
A15: 2 | B15: NOO-22B | C15: STYL-16B | D15: GEORGETTE | E15: 5 | F15: 720 | G15: =F15*E15 -> 3600 | H15: 1800 | I15: 0.2 | J15: =H15*(1-I15) -> 1440 | K15: 500 | L15: 760 | M15: M
A16: 3 | B16: VSS-23A | C16: STYL-1A | D16: CDC | E16: 5 | F16: 720 | G16: =F16*E16 -> 3600 | H16: 1800 | I16: 0.2 | J16: =H16*(1-I16) -> 1440 | K16: 700 | L16: 560 | M16: M
A17: 4 | B17: NOO-23B | C17: STYL-1B | D17: GEORGETTE | E17: 5 | F17: 720 | G17: =F17*E17 -> 3600 | H17: 1800 | I17: 0.2 | J17: =H17*(1-I17) -> 1440 | K17: 500 | L17: 760 | M17: M
A18: 5 | B18: VSS-27A | C18: STYL-13A | D18: CDC | E18: 5 | F18: 720 | G18: =F18*E18 -> 3600 | H18: 1800 | I18: 0.2 | J18: =H18*(1-I18) -> 1440 | K18: 700 | L18: 560 | M18: M
A19: 6 | B19: NOO-27B | C19: STYL-13B | D19: GEORGETTE | E19: 5 | F19: 720 | G19: =F19*E19 -> 3600 | H19: 1800 | I19: 0.2 | J19: =H19*(1-I19) -> 1440 | K19: 500 | L19: 760 | M19: M
A20: 7 | B20: VSS-28A | C20: STYL-33A | D20: CDC | E20: 5 | F20: 720 | G20: =F20*E20 -> 3600 | H20: 1800 | I20: 0.2 | J20: =H20*(1-I20) -> 1440 | K20: 700 | L20: 560 | M20: M
A21: 8 | B21: RUG-28B | C21: STYL-33B | D21: GEORGETTE | E21: 2.7 | F21: 720 | G21: =F21*E21 -> 1944 | H21: 972 | I21: 0.2 | J21: =H21*(1-I21) -> 777.6 | K21: 270 | L21: 410.4 | M21: M
A22: 9 | B22: VSS-29A | C22: STYL-35A | D22: CDC | E22: 5 | F22: 720 | G22: =F22*E22 -> 3600 | H22: 1800 | I22: 0.2 | J22: =H22*(1-I22) -> 1440 | K22: 700 | L22: 560 | M22: M
A23: 10 | B23: RUG-29B | C23: STYL-35B | D23: GEORGETTE | E23: 2.7 | F23: 720 | G23: =F23*E23 -> 1944 | H23: 972 | I23: 0.2 | J23: =H23*(1-I23) -> 777.6 | K23: 270 | L23: 410.4 | M23: M
A24: 11 | B24: VSS-24A | C24: STYL-5A | D24: CDC | E24: 5 | F24: 720 | G24: 3600 | H24: 1800 | I24: 0.2 | J24: =H24*(1-I24) -> 1440 | K24: 700 | L24: 560 | M24: M
A25: 12 | B25: RUG-24B | C25: STYL-5B | D25: GEORGETTE | E25: 2.7 | F25: 720 | G25: 1944 | H25: 972 | I25: 0.2 | J25: =H25*(1-I25) -> 777.6 | K25: 270 | L25: 410.4 | M25: M
A26: 13 | B26: VSS-2A | C26: AVAN-32A | D26: CDC | E26: 5 | F26: 720 | G26: 3600 | H26: 1800 | I26: 0.2 | J26: =H26*(1-I26) -> 1440 | K26: 700 | L26: 560 | M26: M
A27: 14 | B27: NOO-2B | C27: AVAN-32B | D27: GEORGETTE | E27: 5 | F27: 720 | G27: 3600 | H27: 1800 | I27: 0.2 | J27: =H27*(1-I27) -> 1440 | K27: 500 | L27: 760 | M27: M
A28: 15 | B28: VSS-8A | C28: AVAN-33A | D28: CDC | E28: 5 | F28: 720 | G28: 3600 | H28: 1800 | I28: 0.2 | J28: =H28*(1-I28) -> 1440 | K28: 700 | L28: 560 | M28: M
A29: 16 | B29: NOO-8B | C29: AVAN-33B | D29: CHIFFON | E29: 5 | F29: 720 | G29: 3600 | H29: 1800 | I29: 0.2 | J29: =H29*(1-I29) -> 1440 | K29: 700 | L29: 560 | M29: M
A30: 17 | B30: VSS-11A | C30: INCO-17A | D30: CDC | E30: 5 | F30: 720 | G30: 3600 | H30: 1800 | I30: 0.2 | J30: =H30*(1-I30) -> 1440 | K30: 587.5 | L30: 672.5 | M30: M
A31: 18 | B31: NOO-11B | C31: INCO-17B | D31: GEORGETTE | E31: 5 | F31: 720 | G31: 3600 | H31: 1800 | I31: 0.2 | J31: =H31*(1-I31) -> 1440 | K31: 487.5 | L31: 772.5 | M31: M
A32: 19 | B32: VSS-14A | C32: INCO-7A | D32: CDC | E32: 5 | F32: 720 | G32: 3600 | H32: 1800 | I32: 0.2 | J32: =H32*(1-I32) -> 1440 | K32: 587.5 | L32: 672.5 | M32: M
A33: 20 | B33: NOO-14B | C33: INCO-7B | D33: GEORGETTE | E33: 5 | F33: 720 | G33: 3600 | H33: 1800 | I33: 0.2 | J33: =H33*(1-I33) -> 1440 | K33: 487.5 | L33: 772.5 | M33: M
A34: 21 | B34: VSS-18A | C34: INCO-11A | D34: CDC | E34: 5 | F34: 720 | G34: 3600 | H34: 1800 | I34: 0.2 | J34: =H34*(1-I34) -> 1440 | K34: 587.5 | L34: 672.5 | M34: M
A35: 22 | B35: VSS-21A | C35: INCO-8A | D35: CDC | E35: 5 | F35: 720 | G35: 3600 | H35: 1800 | I35: 0.2 | J35: =H35*(1-I35) -> 1440 | K35: 587.5 | L35: 852.5 | M35: M
... A63: 50 | B63: NOO-9B | C63: AVAN-38B | D63: CHIFFON | E63: 5 | F63: 720 | G63: 3600 | H63: 1800 | I63: 0.15 | J63: =H63*(1-I63) -> 1530 | K63: 475 | L63: 1055 | M63: M
A64: 51 | B64: VSS-47 A | C64: MAR-118 A | D64: CDC | E64: 5 | F64: 720 | G64: 3600 | H64: 1800 | I64: 0.2 | J64: 1440 | K64: 700 | L64: 740 | M64: M
A65: 52 | B65: RUG-47 B | C65: MAR-118 B | D65: GEORGETTE | E65: 2.7 | F65: 720 | G65: 1944 | H65: 972 | I65: 0.2 | J65: 777.6 | K65: 297 | L65: 480.6 | M65: M
A66: 53 | B66: VVS-67A | C66: ALB-20A | D66: CDC | E66: 5.5 | F66: 720 | G66: 3960 | H66: 1980 | I66: 0.2 | J66: 1584 | K66: 770 | L66: 814 | M66: M
A67: 54 | B67: NOO-67B | C67: ALB-20B | D67: GEORGETTE | E67: 5 | F67: 720 | G67: 3600 | H67: 1800 | I67: 0.2 | J67: 1440 | K67: 550 | L67: 890 | M67: M
A68: 55 | B68: VVS-57A | C68: ALB-12A | D68: CDC | E68: 5.5 | F68: 720 | G68: 3960 | H68: 1980 | I68: 0.2 | J68: 1584 | K68: 770 | L68: 814 | M68: M
A69: 56 | B69: NOO-32B | C69: QUORUM-154B | D69: GEORGETTE | E69: 4.9 | F69: 220 | G69: 1078 | H69: 862.4 | I69: 0 | J69: 862.4 | K69: 539 | L69: 323.4 | M69: FK
A70: 57 | B70: IUS-53 B | C70: ALB-92 B | D70: GEORGETTE | E70: 6 | F70: 220 | G70: 1320 | H70: 1056 | I70: 0 | J70: 1056 | K70: 660 | L70: 396 | M70: FK
A71: 58 | B71: NSS-54 B | C71: ALB-13 B | D71: GEORGETTE | E71: 5 | F71: 220 | G71: 1100 | H71: 880 | I71: 0 | J71: 880 | K71: 550 | L71: 330 | M71: FK
A72: 59 | B72: VSS-49 A | C72: M&M MAR-105 A | D72: CDC | E72: 5 | F72: 250 | G72: 1250 | H72: 1000 | I72: 0 | J72: 1000 | K72: 700 | L72: 300 | M72: FK
A73: 60 | B73: NNS-57 B | C73: ALB-12 B | D73: GEORGETTE | E73: 5.5 | F73: 220 | G73: 1210 | H73: 968 | I73: 0 | J73: 968 | K73: 605 | L73: 363 | M73: FK
A74: 61 | B74: NOO-1B | C74: M&M ALB-103B | D74: GEORGETTE | E74: 5 | F74: 220 | G74: 1100 | H74: 880 | I74: 0 | J74: 880 | K74: 400 | L74: 480 | M74: FK
A75: 62 | B75: NOO-21B | C75: INCO-8B | D75: GEORGETTE | E75: 5 | F75: 220 | G75: 1100 | H75: 880 | I75: 0 | J75: 880 | K75: 487.5 | L75: 392.5 | M75: FK
A76: 63 | B76: NOO-58B | C76: ALB-4B | D76: GEORGETTE | E76: 5 | F76: 220 | G76: 1100 | H76: 880 | I76: 0 | J76: 880 | K76: 550 | L76: 330 | M76: FK
A77: 64 | B77: VSS-62A | C77: ALB-121A | D77: CDC | E77: 5 | F77: 720 | G77: =E77*F77 -> 3600 | H77: 1800 | I77: 0.2 | J77: 1440 | K77: 700 | L77: 740 | M77: M
A78: 65 | B78: ENS-62B | C78: ALB-121B | D78: CDC | E78: 6 | F78: 720 | G78: =E78*F78 -> 4320 | H78: 2160 | I78: 0.2 | J78: 1728 | K78: 660 | L78: 1068 | M78: M
B79: TOTAL | C79: =COUNTA(C14:C78) -> 65 | E79: =SUM(E12:E78) -> 315.4 | K79: =SUM(K14:K78) -> 37198 | L79: =SUBTOTAL(9,L14:L78) -> 41540.2
A84: ARGOMENTI (ARGO) SOLD
A85: NO | B85: DESIGN | C85: ARTICLE | D85: QUALITY | E85: QTY | F85: PRICE PER MT | G85: PRICE PER PIECE | H85: NET PRICE AFTER DISCOUNT | I85: COM % | J85: LESS COM PER PC | K85: COST PER PC | L85: NET PROFIT PER PC | M85: SOLD TO
A86: 66 | B86: VVS-646 | C86: ARGO-100 | D86: CDC | E86: 5 | F86: 720 | G86: =F86*E86 -> 3600 | H86: 1800 | I86: 0.2 | J86: =H86*(1-I86) -> 1440 | K86: 700 | L86: =J86-K86 -> 740 | M86: M
A87: 67 | B87: NSS-642 | C87: ARGO-099 | D87: CDC | E87: 5 | F87: 720 | G87: =F87*E87 -> 3600 | H87: 1800 | I87: 0.2 | J87: =H87*(1-I87) -> 1440 | K87: 700 | L87: =J87-K87 -> 740 | M87: M
A88: 68 | B88: VVS-618 | C88: ARGO-10A | D88: CDC | E88: 5.5 | F88: 720 | G88: =F88*E88 -> 3960 | H88: 1980 | I88: 0.2 | J88: =H88*(1-I88) -> 1584 | K88: 935 | L88: =J88-K88 -> 649 | M88: M
A89: 69 | B89: VSS-609 | C89: ARGO-102 | D89: CDC | E89: 5 | F89: 720 | G89: =F89*E89 -> 3600 | H89: 1800 | I89: 0.2 | J89: =H89*(1-I89) -> 1440 | K89: 700 | L89: =J89-K89 -> 740 | M89: M
A90: 70 | B90: VSS-659A | C90: ARGO-269A | D90: CDC | E90: 5 | F90: 720 | G90: =F90*E90 -> 3600 | H90: 1800 | I90: 0.2 | J90: =H90*(1-I90) -> 1440 | K90: 700 | L90: =J90-K90 -> 740 | M90: M
A91: 71 | B91: ISS-659B | C91: ARGO-269B | D91: GEORGETTE | E91: 2.5 | F91: 720 | G91: =F91*E91 -> 1800 | H91: 900 | I91: 0.2 | J91: =H91*(1-I91) -> 720 | K91: 275 | L91: =J91-K91 -> 445 | M91: M
A92: 72 | B92: VSS-121A | C92: ARGO-51 | D92: CDC | E92: 5 | F92: 720 | G92: =F92*E92 -> 3600 | H92: 1800 | I92: 0.2 | J92: =H92*(1-I92) -> 1440 | K92: 700 | L92: =J92-K92 -> 740 | M92: M
A93: 73 | B93: DSSS-635 | C93: ARGO-14 | D93: LUREX | E93: 5 | F93: 240 | G93: =F93*E93 -> 1200 | H93: 1200 | I93: 0 | J93: =H93*(1-I93) -> 1200 | K93: 850 | L93: =J93-K93 -> 350 | M93: FK
A94: 74 | B94: VSS-70S | C94: ARGO-210S | D94: CDC | E94: 5 | F94: 390 | G94: =F94*E94 -> 1950 | H94: 1950 | I94: 0.2 | J94: =H94*(1-I94) -> 1560 | K94: 700 | L94: =J94-K94 -> 860 | M94: B
A95: 75 | B95: VVS-658A | C95: ARGO-3A | D95: CDC | E95: 5.5 | F95: 720 | G95: =F95*E95 -> 3960 | H95: 1980 | I95: 0.2 | J95: =H95*(1-I95) -> 1584 | K95: 770 | L95: =J95-K95 -> 814 | M95: M
A96: 76 | B96: VVS-602B | C96: ARGO-49A | D96: CDC | E96: 5.5 | F96: 720 | G96: =F96*E96 -> 3960 | H96: 1980 | I96: 0.2 | J96: =H96*(1-I96) -> 1584 | K96: 770 | L96: =J96-K96 -> 814 | M96: M
A97: 77 | B97: VVS-613 | C97: ARGO-34A | D97: CDC | E97: 5.5 | F97: 720 | G97: =F97*E97 -> 3960 | H97: 1980 | I97: 0.2 | J97: =H97*(1-I97) -> 1584 | K97: 770 | L97: =J97-K97 -> 814 | M97: M
A98: 78 | B98: DSSS-610 | C98: ARGO-72 | D98: CDC | E98: 6 | F98: 720 | G98: 4320 | H98: 2160 | I98: 0.2 | J98: 1728 | K98: 840 | L98: 888 | M98: M
A99: 79 | B99: DSSS-601 A | C99: ARGO-4 | D99: LUREX | E99: 4.8 | F99: 900 | G99: 900 | H99: 900 | I99: 0 | J99: 900 | K99: 816 | L99: 84 | M99: S
A100: 80 | B100: ESS-648 | C100: ARGO-56 | D100: SATIN | E100: 5 | F100: 400 | G100: 800 | H100: 800 | I100: 0 | J100: 800 | K100: 700 | L100: 100 | M100: S
A101: 81 | B101: ISS-649 | C101: ARGO-209 | D101: JACQUARD | E101: 5 | F101: 266.66667 | G101: 800 | H101: 800 | I101: 0 | J101: 800 | K101: 700 | L101: 100 | M101: S
A102: 82 | B102: DSSS-116 A | C102: ARGO-39 | D102: LUREX | E102: 5 | F102: 180 | G102: 900 | H102: 900 | I102: 0 | J102: 900 | K102: 850 | L102: 50 | M102: S
A103: 83 | B103: DSSS-631 | C103: ARGO-26 | D103: LUREX | E103: 5 | F103: 180 | G103: 900 | H103: 900 | I103: 0 | J103: 900 | K103: 850 | L103: 50 | M103: S
A104: 84 | B104: VSS-647 | C104: ARGO-98 | D104: CDC | E104: 5 | F104: 160 | G104: 800 | H104: 800 | I104: 0 | J104: 800 | K104: 700 | L104: 100 | M104: S
A105: 85 | B105: DSSS-656 | C105: ARGO-007 | D105: CDC | E105: 6 | F105: 720 | G105: 4320 | H105: 2160 | I105: 0.2 | J105: 1728 | K105: 840 | L105: 888 | M105: M
A106: 86 | B106: VVS-102B | C106: ARGO-33A | D106: CDC | E106: 5.5 | F106: 720 | G106: 3960 | H106: 1980 | I106: 0.2 | J106: 1584 | K106: 770 | L106: 814 | M106: M
B107: TOTAL | C107: =COUNTA(C86:C106) -> 21 | E107: =SUM(E85:E106) -> 106.8 | K107: =SUM(K86:K106) -> 15636 | L107: =SUM(L86:L106) -> 11520
A110: ALBERTI (ALB) SOLD
A111: NO | B111: DESIGN | C111: ARTICLE | D111: QUALITY | E111: QTY | F111: PRICE PER MT | G111: PRICE PER PIECE | H111: NET PRICE AFTER DISCOUNT | I111: COM % | J111: LESS COM PER PC | K111: COST PER PC | L111: NET PROFIT PER PC | M111: SOLD TO
A112: 87 | B112: VVS-324A | C112: ALB71A | D112: CDC | E112: 5.5 | F112: 720 | G112: =E112*F112 -> 3960 | H112: 1980 | I112: 0.2 | J112: =H112*(1-I112) -> 1584 | K112: 522.5 | L112: =J112-K112 -> 1061.5 | M112: M
A113: 88 | B113: NSS-324B | C113: ALB71B | D113: GEORGETTE | E113: 5 | F113: 720 | G113: =E113*F113 -> 3600 | H113: 1800 | I113: 0.2 | J113: =H113*(1-I113) -> 1440 | K113: 400 | L113: =J113-K113 -> 1040 | M113: M
A114: 89 | B114: VVS- | C114: ALB76A | D114: CDC | E114: 6.5 | F114: 720 | G114: =E114*F114 -> 4680 | H114: 2340 | I114: 0.2 | J114: =H114*(1-I114) -> 1872 | K114: 617.5 | L114: =J114-K114 -> 1254.5 | M114: M
A115: 90 | B115: NSS- | C115: ALB76B | D115: GEORGETTE | E115: 5 | F115: 720 | G115: =E115*F115 -> 3600 | H115: 1800 | I115: 0.2 | J115: =H115*(1-I115) -> 1440 | K115: 400 | L115: =J115-K115 -> 1040 | M115: M
A116: 91 | B116: VSS-325A | C116: ALB105A | D116: CDC | E116: 5 | F116: 720 | G116: =E116*F116 -> 3600 | H116: 1800 | I116: 0.2 | J116: =H116*(1-I116) -> 1440 | K116: 475 | L116: =J116-K116 -> 965 | M116: M
A117: 92 | B117: NSS-325B | C117: ALB105B | D117: GEORGETTE | E117: 5 | F117: 720 | G117: =E117*F117 -> 3600 | H117: 1800 | I117: 0.2 | J117: =H117*(1-I117) -> 1440 | K117: 400 | L117: =J117-K117 -> 1040 | M117: M
A118: 93 | B118: VSS-350 | C118: ALB-240 | D118: CDC | E118: 5 | F118: 720 | G118: =E118*F118 -> 3600 | H118: 1800 | I118: 0.2 | J118: =H118*(1-I118) -> 1440 | K118: 700 | L118: =J118-K118 -> 740 | M118: M
A119: 94 | B119: VSS-274 | C119: ALB-149 | D119: CDC | E119: 5 | F119: 720 | G119: =E119*F119 -> 3600 | H119: 1800 | I119: 0.2 | J119: =H119*(1-I119) -> 1440 | K119: 550 | L119: =J119-K119 -> 890 | M119: M
A120: 95 | B120: DSAS-211A | C120: ALB-26A | D120: CDC | E120: 6.6 | F120: 720 | G120: =E120*F120 -> 4752 | H120: 2376 | I120: 0.2 | J120: =H120*(1-I120) -> 1900.8 | K120: 825 | L120: =J120-K120 -> 1075.8 | M120: M
A121: 96 | B121: NSS-211B | C121: ALB-26B | D121: GEORGETTE | E121: 2.5 | F121: 720 | G121: =E121*F121 -> 1800 | H121: 900 | I121: 0.2 | J121: =H121*(1-I121) -> 720 | K121: 250 | L121: =J121-K121 -> 470 | M121: M
A122: 97 | B122: VVS-205A | C122: ALB-6A | D122: CDC | E122: 4.7 | F122: 720 | G122: =E122*F122 -> 3384 | H122: 1692 | I122: 0.2 | J122: =H122*(1-I122) -> 1353.6 | K122: 517 | L122: =J122-K122 -> 836.6 | M122: M
A123: 98 | B123: NSS-330 | C123: ALB-39B | D123: GEORGETTE | E123: 5 | F123: 144 | G123: =E123*F123 -> 720 | H123: 720 | I123: 0 | J123: =H123*(1-I123) -> 720 | K123: 400 | L123: =J123-K123 -> 320 | M123: FK
... A144: 119 | B144: DDSS-223A | C144: ALB-124A | D144: LUREX | E144: 5.4 | F144: 166.66667 | G144: =E144*F144 -> 900 | H144: 900 | I144: 0 | J144: =H144*(1-I144) -> 900 | K144: 700 | L144: =J144-K144 -> 200 | M144: S
A145: 120 | B145: NSS-223B | C145: ALB-124B | D145: GEORGETTE | E145: 5 | F145: GIFT | I145: 0 | J145: =H145*(1-I145) -> 0 | K145: 550 | L145: =J145-K145 -> -550 | M145: S
A146: 121 | B146: VSS-302 | C146: ALB-006 | D146: CDC | E146: 5 | F146: 720 | G146: =E146*F146 -> 3600 | H146: =G146/2 -> 1800 | I146: 0.2 | J146: =H146*(1-I146) -> 1440 | K146: 550 | L146: =J146-K146 -> 890 | M146: M
A147: 122 | B147: ISS-212A | C147: ALB-111A | D147: CDC | E147: 5.8 | F147: 720 | G147: =E147*F147 -> 4176 | H147: =G147/2 -> 2088 | I147: 0.2 | J147: =H147*(1-I147) -> 1670.4 | K147: 638 | L147: =J147-K147 -> 1032.4 | M147: M
A148: 123 | B148: NNS-212B | C148: ALB-111B | D148: GEORGETTE | E148: 5.5 | F148: 720 | G148: =E148*F148 -> 3960 | H148: =G148/2 -> 1980 | I148: 0.2 | J148: =H148*(1-I148) -> 1584 | K148: 550 | L148: =J148-K148 -> 1034 | M148: M
A149: 124 | B149: VAS-255 | C149: ALB-115A | D149: CDC | E149: 5.3 | F149: 720 | G149: =E149*F149 -> 3816 | H149: =G149/2 -> 1908 | I149: 0.15 | J149: =H149*(1-I149) -> 1621.8 | K149: 583 | L149: =J149-K149 -> 1038.8 | M149: M
A150: 125 | B150: NSS-324B | C150: ALB-71 B | D150: GEORGETTE | E150: 5 | F150: 220 | G150: 1100 | H150: 880 | I150: 0 | J150: 880 | K150: 550 | L150: 330 | M150: FK
A151: 126 | B151: VSS-272S | C151: ALB-155 | D151: CDC | E151: 5 | F151: 720 | G151: 3600 | H151: 1800 | I151: 0.2 | J151: 1440 | K151: 550 | L151: 890 | M151: M
A152: 127 | B152: VVS-275 | C152: ALB-4A | D152: CDC | E152: 5.5 | F152: 720 | G152: 3960 | H152: 1980 | I152: 0.2 | J152: 1584 | K152: 605 | L152: 979 | M152: M
A153: 128 | B153: DSSS-277 | C153: ALB-67A | D153: CDC | E153: 5.9 | F153: 720 | G153: 4248 | H153: 2124 | I153: 0.2 | J153: 1699.2 | K153: 649 | L153: 1050.2 | M153: M
A154: 129 | B154: DSSS-280 | C154: ALB-10A | D154: CDC | E154: 6.3 | F154: 720 | G154: 4536 | H154: 2268 | I154: 0.2 | J154: 1814.4 | K154: 1121.4 | L154: 693 | M154: M
A155: 130 | B155: VSS-359A | C155: ALB-89A | D155: CDC | E155: 5 | F155: 720 | G155: 3600 | H155: 1800 | I155: 0.2 | J155: 1440 | K155: 890 | L155: 550 | M155: M
...

Sheet SILK - PENDING
B1: UPDATED BY IBRAHIM
B2: VIP-M
B3: Sherry - S | D3: PENDING-P | J3: Total Cost | L3: =H18+H27+H37+H46+H57+H65+H75+H84+H91+H99+H110+H118+H125+H132+H141+H151+H171 -> 24677.5
B4: Angie - A
B5: Fong king - FK | D5: MS. KLARA-K
B6: Bani -B
B7: MR. Cetin- C
A11: PENDING
A12: M&M 1-70
A13: NO | B13: DESIGN | C13: ARTICLE | D13: QUALITY | E13: QTY | F13: COST PER MT EURO | G13: COST PER MT RM | H13: COST PIECE RM | I13: V.I.P PER MT RM | J13: V.I.P PIECE RM | K13: SELLING PER MT RM LESS 50% | L13: SELLING PIECE RM | M13: SOLD TO
A14: 1 | B14: EDS-68A | C14: ALB-110A | D14: CDC | E14: 5.7 | F14: 28 | G14: =F14*5 -> 140 | H14: =G14*E14 -> 798 | I14: 720 | J14: =I14*E14 -> 4104 | K14: =I14/2 -> 360 | L14: =K14*E14 -> 2052 | M14: P-C
A15: 2 | B15: NOO-68B | C15: ALB-110B | D15: GEORGETTE | E15: 5 | F15: 22 | G15: =F15*5 -> 110 | H15: =G15*E15 -> 550 | I15: 720 | J15: =I15*E15 -> 3600 | K15: =I15/2 -> 360 | L15: =K15*E15 -> 1800 | M15: P-C
A16: 3 | B16: DDSS-70A | C16: ALB-122A | D16: CDC | E16: 5.5 | F16: 28 | G16: =F16*5 -> 140 | H16: =G16*E16 -> 770 | I16: 720 | J16: =I16*E16 -> 3960 | K16: =I16/2 -> 360 | L16: =K16*E16 -> 1980 | M16: P-C
A17: 4 | B17: IUS-70B | C17: ALB-122B | D17: GEORGETTE | E17: 6 | F17: 22 | G17: =F17*5 -> 110 | H17: =G17*E17 -> 660 | I17: 720 | J17: =I17*E17 -> 4320 | K17: =I17/2 -> 360 | L17: =K17*E17 -> 2160 | M17: P-C
A18: TOTAL COST | D18: =COUNTA(D14:D17) -> 4 | E18: =SUM(E14:E17) -> 22.2 | H18: =SUM(H14:H17) -> 2778
A21: ARGOMENTI (ARGO)
A22: NO | B22: NO | C22: ARTICLE | D22: QUALITY | E22: QTY | F22: COST PER MT EURO | G22: COST PER MT RM | H22: COST PIECE RM | I22: V.I.P PER MT RM | J22: V.I.P PIECE RM | K22: SELLING PER MT RM LESS 50% | L22: SELLING PIECE RM | M22: SOLD TO
A27: TOTAL COST | D27: =COUNTA(D23:D26) -> 0 | E27: =SUM(E22:E25) -> 0 | H27: =SUM(H22:H26) -> 0
A31: ALBERTI(ALB)
A32: NO | B32: DESIGN | C32: ARTICLE | D32: QUALITY | E32: QTY | F32: COST PER MT EURO | G32: COST PER MT RM | H32: COST PIECE RM | I32: V.I.P PER MT RM | J32: V.I.P PIECE RM | K32: SELLING PER MT RM LESS 50% | L32: SELLING PIECE RM | M32: SOLD TO
A33: 5 | B33: DSSS-257S | C33: ALB-50A | D33: CDC | E33: 6.3 | F33: €22.00 | G33: =F33*5 -> 110 | H33: =G33*E33 -> 693 | I33: 720 | J33: =I33*E33 -> 4536 | K33: =I33/2 -> 360 | L33: =K33*E33 -> 2268 | M33: S
A37: TOTAL COST | D37: =COUNTA(D33:D36) -> 1 | E37: =SUM(E32:E35) -> 6.3 | H37: =SUM(H32:H35) -> 693
A41: MARITEX (MAR)
A42: NO | B42: DESIGN | C42: ARTICLE | D42: QUALITY | E42: QTY | F42: COST PER MT EURO | G42: COST PER MT RM | H42: COST PIECE RM | I42: V.I.P PER MT RM | J42: V.I.P PIECE RM | K42: SELLING PER MT RM | L42: SELLING PIECE RM | M42: SOLD TO
A43: 6 | B43: DSSS-451A | C43: MAR-86 | D43: LUREX | E43: 5 | F43: 34 | G43: =F43*5 -> 170 | H43: =G43*E43 -> 850 | I43: 720 | J43: =I43*E43 -> 3600 | K43: =I43/2 -> 360 | L43: =K43*E43 -> 1800 | M43: S
A46: TOTAL COST | D46: =COUNTA(D43:D45) -> 1 | E46: =SUM(E43:E45) -> 5 | H46: =SUM(H43:H45) -> 850
A50: NELLA
A51: NO | B51: DESIGN | C51: ARTICLE | D51: QUALITY | E51: QTY | F51: COST PER MT EURO | G51: COST PER MT RM | H51: COST PIECE RM | I51: V.I.P PER MT RM | J51: V.I.P PIECE RM | K51: SELLING PER MT RM LESS 50% | L51: SELLING PIECE RM | M51: SOLD TO
A52: 7 | B52: VSS-745 | C52: NELLA-045 | D52: TWILLCDC | E52: 5 | F52: 28 | G52: =F52*5 -> 140 | H52: =G52*E52 -> 700 | I52: 720 | J52: =I52*E52 -> 3600 | K52: =I52/2 -> 360 | L52: =K52*E52 -> 1800 | M52: P-K
A53: 8 | B53: VSS-721 | C53: NELLA-193S | D53: SATIN | E53: 5 | F53: 28 | G53: =F53*5 -> 140 | H53: =G53*E53 -> 700 | I53: 720 | J53: =I53*E53 -> 3600 | K53: =I53/2 -> 360 | L53: =K53*E53 -> 1800 | M53: S
A57: TOTAL COST | D57: =COUNTA(D52:D56) -> 2 | E57: =SUM(E52:E56) -> 10 | H57: =SUM(H52:H56) -> 1400
A60: AVANTGARD (AVAN)
A61: NO | B61: DESIGN | C61: ARTICLE | D61: QUALITY | E61: QTY | F61: COST PER MT EURO | G61: COST PER MT RM | H61: COST PIECE RM | I61: V.I.P PER MT RM | J61: V.I.P PIECE RM | K61: SELLING PER MT RM LESS 50% | L61: SELLING PIECE RM | M61: SOLD TO
A62: 9 | B62: NSS-827 | C62: AVAN-103 | D62: GEORGETTE | E62: 5 | F62: 19 | G62: =F62*5 -> 95 | H62: =E62*G62 -> 475 | I62: 720 | J62: =I62*E62 -> 3600 | K62: =I62/2 -> 360 | L62: =K62*E62 -> 1800 | M62: P-C
A63: 10 | B63: NSS-830 | C63: AVAN-001 | D63: GEORGETTE | E63: 5 | F63: 19 | G63: =F63*5 -> 95 | H63: =E63*G63 -> 475 | I63: 720 | J63: =I63*E63 -> 3600 | K63: =I63/2 -> 360 | L63: =K63*E63 -> 1800 | M63: P-C
A65: TOTAL COST | D65: =COUNTA(D62:D64) -> 2 | E65: =SUM(E62:E64) -> 10 | H65: =SUM(H62:H64) -> 950
A69: CASA DELLO (CASA)
A70: NO | B70: DESIGN | C70: ARTICLE | D70: QUALITY | E70: QTY | F70: COST PER MT EURO | G70: COST PER MT RM | H70: COST PIECE RM | I70: V.I.P PER MT RM | J70: V.I.P PIECE RM | K70: SELLING PER MT RM LESS 50% | L70: SELLING PIECE RM | M70: SOLD TO
A71: 11 | B71: VSS-869 | C71: CASA-57 | D71: CDC | E71: 5 | F71: 24 | G71: =F71*5 -> 120 | H71: =G71*E71 -> 600 | I71: 720 | J71: =I71*E71 -> 3600 | K71: =I71/2 -> 360 | L71: =K71*E71 -> 1800 | M71: P-C
A72: 12 | B72: ASS-876 | C72: CASA-91 A | D72: CDC | E72: 3 | F72: 24 | G72: =F72*5 -> 120 | H72: =G72*E72 -> 360 | I72: 720 | J72: =I72*E72 -> 2160 | K72: =I72/2 -> 360 | L72: =K72*E72 -> 1080 | M72: P-C
A73: 13 | B73: DDSS-877 | C73: CASA-92 | D73: SATIN | E73: 5.7 | F73: 24 | G73: =F73*5 -> 120 | H73: =G73*E73 -> 684 | I73: 800 | J73: =I73*E73 -> 4560 | K73: =I73/2 -> 400 | L73: =K73*E73 -> 2280 | M73: P-C
A74: 14 | B74: ASS-880 | C74: CASA-88 | D74: SATIN | E74: 2.3 | F74: 24 | G74: =F74*5 -> 120 | H74: =G74*E74 -> 276 | I74: 800 | J74: =I74*E74 -> 1840 | K74: =I74/2 -> 400 | L74: =K74*E74 -> 920 | M74: P-K
A75: TOTAL COST | D75: =COUNTA(D71:D74) -> 4 | E75: =SUM(E71:E74) -> 16 | H75: =SUM(H71:H74) -> 1920
A77: STYLE SILK (STYL)
A78: NO | B78: DESIGN | C78: ARTICLE | D78: QUALITY | E78: QTY | F78: COST PER MT EURO | G78: COST PER MT RM | H78: COST PIECE RM | I78: V.I.P PER MT RM | J78: V.I.P PIECE RM | K78: SELLING PER MT RM LESS 50% | L78: SELLING PIECE RM | M78: SOLD TO
A79: 15 | B79: GSS-922 S | C79: STYL-42 B | D79: GEORGETTE | E79: 2.7 | F79: 25 | G79: =F79*5 -> 125 | H79: =G79*E79 -> 337.5 | I79: 720 | J79: =I79*E79 -> 1944 | K79: =I79/2 -> 360 | L79: =K79*E79 -> 972 | M79: P-K
A80: 16 | B80: ASS-908B | C80: STYL-36B | D80: GEORGETTE | E80: 3.5 | F80: 25 | G80: =F80*5 -> 125 | H80: =G80*E80 -> 437.5 | I80: 720 | J80: =I80*E80 -> 2520 | K80: =I80/2 -> 360 | L80: =K80*E80 -> 1260 | M80: S
A81: 17 | B81: ESS-920A | C81: STYL-8A | D81: CDC | E81: 5 | F81: 29 | G81: =F81*5 -> 145 | H81: =G81*E81 -> 725 | I81: 720 | J81: =I81*E81 -> 3600 | K81: =I81/2 -> 360 | L81: =K81*E81 -> 1800 | M81: S
A82: 18 | B82: ESS-926A | C82: STYL-17A | D82: CDC | E82: 5 | F82: 29 | G82: =F82*5 -> 145 | H82: =G82*E82 -> 725 | I82: 720 | J82: =I82*E82 -> 3600 | K82: =I82/2 -> 360 | L82: =K82*E82 -> 1800 | M82: S
A84: TOTAL COST | D84: =COUNTA(D79:D83) -> 4 | E84: =SUM(E79:E83) -> 16.2 | H84: =SUM(H79:H83) -> 2225
A87: INCOMO (INCO)
A88: NO | B88: DESIGN | C88: ARTICLE | D88: QUALITY | E88: QTY | F88: COST PER MT EURO | G88: COST PER MT RM | H88: COST PIECE RM | I88: V.I.P PER MT RM | J88: V.I.P PIECE RM | K88: SELLING PER MT RM LESS 50% | L88: SELLING PIECE RM | M88: SOLD TO
A89: 19 | B89: NSS-930B | C89: INCO-14B | D89: GEORGETTE | E89: 5 | F89: 20 | G89: =F89*5 -> 100 | H89: =E89*G89 -> 500 | I89: 720 | J89: =I89*E89 -> 3600 | K89: =I89/2 -> 360 | L89: =K89*E89 -> 1800 | M89: P-C
A91: TOTAL COST | D91: =COUNTA(D89:D90) -> 1 | E91: =SUM(E89:E90) -> 5 | H91: =SUM(H89:H90) -> 500
A95: CARNET (UG)
A96: NO | B96: DESIGN | C96: ARTICLE | D96: QUALITY | E96: QTY | F96: COST PER MT EURO | G96: COST PER MT RM | H96: COST PIECE RM | I96: V.I.P PER MT RM | J96: V.I.P PIECE RM | K96: SELLING PER MT RM LESS 50% | L96: SELLING PIECE RM | M96: SOLD TO
A99: TOTAL COST | D99: =COUNTA(D97:D98) -> 0 | E99: =SUM(E97:E98) -> 0 | H99: =SUM(H97:H98) -> 0
A105: CAVALLI+TGM+ROTARY
A106: NO | B106: DESIGN | C106: ARTICLE | D106: QUALITY | E106: QTY | F106: COST PER MT EURO | G106: COST PER MT RM | H106: COST PIECE RM | I106: V.I.P PER MT RM | J106: V.I.P PIECE RM | K106: SELLING PER MT RM LESS 50% | L106: SELLING PIECE RM | M106: SOLD TO
A107: 20 | B107: DUAS-982 | C107: CAVA-03 | D107: SATIN | E107: 4.4 | F107: 40 | G107: =F107*5 -> 200 | H107: =G107*E107 -> 880 | I107: =G107*5 -> 1000 | J107: =E107*I107 -> 4400 | K107: =I107/2 -> 500 | L107: =K107*E107 -> 2200 | M107: P-K
A110: TOTAL COST | D110: =COUNTA(D107:D109) -> 1 | E110: =SUM(E106:E109) -> 4.4 | H110: =SUM(H107:H109) -> 880
A114: RUFFO (RUFF)
A115: NO | B115: DESIGN | C115: ARTICLE | D115: QUALITY | E115: QTY | F115: COST PER MT EURO | G115: COST PER MT RM | H115: COST PIECE RM | I115: V.I.P PER MT RM | J115: V.I.P PIECE RM | K115: SELLING PER MT RM LESS 50% | L115: SELLING PIECE RM | M115: SOLD TO
A118: TOTAL COST | D118: =COUNTA(D116:D117) -> 0 | E118: =SUM(E116:E117) -> 0 | H118: =SUM(H116:H117) -> 0
A121: SETERIE GR(SETE)
A122: NO | B122: DESIGN | C122: ARTICLE | D122: QUALITY | E122: QTY | F122: COST PER MT EURO | G122: COST PER MT RM | H122: COST PIECE RM | I122: V.I.P PER MT RM | J122: V.I.P PIECE RM | K122: SELLING PER MT RM LESS 50% | L122: SELLING PIECE RM | M122: SOLD TO
A125: TOTAL COST | D125: =COUNTA(D123:D124) -> 0 | E125: =SUM(E123:E124) -> 0 | H125: =SUM(H123:H124) -> 0
A128: TESSILE(TESSI)
A129: NO | B129: DESIGN | C129: ARTICLE | D129: QUALITY | E129: QTY | F129: COST PER MT EURO | G129: COST PER MT RM | H129: COST PIECE RM | I129: V.I.P PER MT RM | J129: V.I.P PIECE RM | K129: SELLING PER MT RM LESS 50% | L129: SELLING PIECE RM | M129: SOLD TO
A130: 21 | B130: NSS-19 S | C130: TESI-118 S | D130: CHIFFON | E130: 5.5 | F130: 19 | G130: =F130*5 -> 95 | H130: =E130*G130 -> 522.5 | I130: 720 | J130: =I130*E130 -> 3960 | K130: =I130/2 -> 360 | L130: =K130*E130 -> 1980 | M130: S
A132: TOTAL COST | D132: =COUNTA(D130:D131) -> 1 | E132: =SUM(E130:E131) -> 5.5 | H132: =SUM(H130:H131) -> 522.5
A136: QUORUM(QUO)
A137: NO | B137: DESIGN | C137: ARTICLE | D137: QUALITY | E137: QTY | F137: COST PER MT EURO | G137: COST PER MT RM | H137: COST PIECE RM | I137: V.I.P PER MT RM | J137: V.I.P PIECE RM | K137: SELLING PER MT RM LESS 50% | L137: SELLING PIECE RM | M137: SOLD TO
A138: 22 | B138: NSS-20 | C138: QUO-APT-294 | D138: PRINTED_LACE | E138: 4.5 | F138: 20 | G138: =F138*5 -> 100 | H138: =E138*G138 -> 450 | I138: 720 | J138: =I138*E138 -> 3240 | K138: =I138/2 -> 360 | L138: =K138*E138 -> 1620 | M138: P-C
A139: 23 | B139: IAS-14 | C139: QUO-008 | D139: SATIN_JACQUARD | E139: 6 | F139: 20 | G139: =F139*5 -> 100 | H139: =E139*G139 -> 600 | I139: 720 | J139: =I139*E139 -> 4320 | K139: =I139/2 -> 360 | L139: =K139*E139 -> 2160 | M139: S
A140: 24 | B140: IAS-15 | C140: QUO-190 | D140: SATIN_JACQUARD | E140: 6 | F140: 20 | G140: =F140*5 -> 100 | H140: =E140*G140 -> 600 | I140: 720 | J140: =I140*E140 -> 4320 | K140: =I140/2 -> 360 | L140: =K140*E140 -> 2160 | M140: S
A141: TOTAL COST | D141: =COUNTA(D138:D140) -> 3 | E141: =SUM(E138:E140) -> 16.5 | H141: =SUM(H138:H140) -> 1650
A144: SILKOMO (SILKO)
A145: NO | B145: DESIGN | C145: ARTICLE | D145: QUALITY | E145: QTY | F145: COST PER MT EURO | G145: COST PER MT RM | H145: COST PIECE RM | I145: V.I.P PER MT RM | J145: V.I.P PIECE RM | K145: SELLING PER MT RM LESS 50% | L145: SELLING PIECE RM | M145: SOLD TO
A146: 25 | B146: GSS-1 | C146: SILKO-1 B | D146: CHIFFON | E146: 3 | F146: 20 | G146: =F146*5 -> 100 | H146: =E146*G146 -> 300 | I146: 720 | J146: =I146*E146 -> 2160 | K146: =I146/2 -> 360 | L146: =K146*E146 -> 1080 | M146: P-C
A147: 26 | B147: GSS-3 | C147: SILKO-C 35 | D147: CHIFFON | E147: 3 | F147: 20 | G147: =F147*5 -> 100 | H147: =E147*G147 -> 300 | I147: 720 | J147: =I147*E147 -> 2160 | K147: =I147/2 -> 360 | L147: =K147*E147 -> 1080 | M147: P-C
A148: 27 | B148: NGS-7 | C148: SILKO-132 | D148: CHIFFON | E148: 5 | F148: 20 | G148: =F148*5 -> 100 | H148: =E148*G148 -> 500 | I148: 720 | J148: =I148*E148 -> 3600 | K148: =I148/2 -> 360 | L148: =K148*E148 -> 1800 | M148: P-C
A149: 28 | B149: VSS-12 A | C149: SILKO-145 A | D149: CDC | E149: 4.9 | F149: 28 | G149: =F149*5 -> 140 | H149: =E149*G149 -> 686 | I149: 720 | J149: =I149*E149 -> 3528 | K149: =I149/2 -> 360 | L149: =K149*E149 -> 1764 | M149: P-C
A150: 29 | B150: NSS-12 B | C150: SILKO-145 B | D150: CHIFFON | E150: 5 | F150: 20 | G150: =F150*5 -> 100 | H150: =E150*G150 -> 500 | I150: 720 | J150: =I150*E150 -> 3600 | K150: =I150/2 -> 360 | L150: =K150*E150 -> 1800 | M150: P-C
A151: TOTAL COST | D151: =COUNTA(D146:D150) -> 5 | E151: =SUM(E146:E150) -> 20.9 | H151: =SUM(H146:H150) -> 2286
A154: NO CODE (NC)
A155: NO | B155: DESIGN | C155: ARTICLE | D155: QUALITY | E155: QTY | F155: COST PER MT EURO | G155: COST PER MT RM | H155: COST PIECE RM | I155: V.I.P PER MT RM | J155: V.I.P PIECE RM | K155: SELLING PER MT RM LESS 50% | L155: SELLING PIECE RM | M155: SOLD TO
A156: 30 | B156: VSS-NC2A | C156: MAR-25A | D156: CDC | E156: 5 | F156: 23 | G156: =F156*5 -> 115 | H156: =E156*G156 -> 575 | I156: 720 | J156: =I156*E156 -> 3600 | K156: =G156*2 -> 230 | L156: =K156*E156 -> 1150 | M156: P-C
A157: 31 | B157: DSSS-NC2B | C157: MAR-25B | D157: LUREX | E157: 5 | F157: 34 | G157: =F157*5 -> 170 | H157: =E157*G157 -> 850 | I157: 800 | J157: =I157*E157 -> 4000 | K157: =G157*2 -> 340 | L157: =K157*E157 -> 1700 | M157: P-C
A158: 32 | B158: NSS-NC6B | C158: AVAV-15B | D158: GEORGETTE | E158: 5 | F158: 19 | G158: =F158*5 -> 95 | H158: =E158*G158 -> 475 | I158: 720 | J158: =I158*E158 -> 3600 | K158: =G158*2 -> 190 | L158: =K158*E158 -> 950 | M158: P-C
A159: 33 | B159: VSS-NC9A | C159: ALB-25A | D159: CDC | E159: 5 | F159: 19 | G159: =F159*5 -> 95 | H159: =E159*G159 -> 475 | I159: 720 | J159: =I159*E159 -> 3600 | K159: =G159*2 -> 190 | L159: =K159*E159 -> 950 | M159: P-C
A160: 34 | B160: NNS-NC9B | C160: ALB-25B | D160: GEORGETTE | E160: 5 | F160: 16 | G160: =F160*5 -> 80 | H160: =E160*G160 -> 400 | I160: 720 | J160: =I160*E160 -> 3600 | K160: =G160*2 -> 160 | L160: =K160*E160 -> 800 | M160: P-C
A161: 35 | B161: NSS-NC11B | C161: ALB-108B | D161: GEORGETTE | E161: 5 | F161: 16 | G161: =F161*5 -> 80 | H161: =E161*G161 -> 400 | I161: 720 | J161: =I161*E161 -> 3600 | K161: =G161*2 -> 160 | L161: =K161*E161 -> 800 | M161: P-C
A162: 36 | B162: NNS-NC12B | C162: ALB-88B | D162: GEORGETTE | E162: 5.5 | F162: 16 | G162: =F162*5 -> 80 | H162: =E162*G162 -> 440 | I162: 720 | J162: =I162*E162 -> 3960 | K162: =G162*2 -> 160 | L162: =K162*E162 -> 880 | M162: P-C
A163: 37 | B163: NNS-NC13B | C163: ALB-79B | D163: GEORGETTE | E163: 5.3 | F163: 16 | G163: =F163*5 -> 80 | H163: =E163*G163 -> 424 | I163: 720 | J163: =I163*E163 -> 3816 | K163: =G163*2 -> 160 | L163: =K163*E163 -> 848 | M163: P-C
A164: 38 | B164: IAS-NC14B | C164: ALB-116B | D164: GEORGETTE | E164: 5.9 | F164: 16 | G164: =F164*5 -> 80 | H164: =E164*G164 -> 472 | I164: 720 | J164: =I164*E164 -> 4248 | K164: =G164*2 -> 160 | L164: =K164*E164 -> 944 | M164: P-C
A165: 39 | B165: VSS-NC15B | C165: ALB-55B | D165: GEORGETTE | E165: 6.4 | F165: 16 | G165: =F165*5 -> 80 | H165: =E165*G165 -> 512 | I165: 720 | J165: =I165*E165 -> 4608 | K165: =G165*2 -> 160 | L165: =K165*E165 -> 1024 | M165: P-C
A166: 40 | B166: VSS-NC-21 | C166: NC | D166: CDC | E166: 5 | F166: 28 | G166: =F166*5 -> 140 | H166: =E166*G166 -> 700 | I166: 720 | J166: =I166*E166 -> 3600 | K166: =G166*2 -> 280 | L166: =K166*E166 -> 1400 | M166: P-C
A167: 41 | B167: VSS-NC-26 | C167: ALB-NC | D167: CDC | E167: 5 | F167: 28 | G167: =F167*5 -> 140 | H167: =E167*G167 -> 700 | I167: 720 | J167: =I167*E167 -> 3600 | K167: =G167*2 -> 280 | L167: =K167*E167 -> 1400 | M167: P-C
... A170: 44 | B170: NSS-NC-36B | C170: INCO-014B | D170: GEORGETTE | E170: 5 | F170: 20 | G170: =F170*5 -> 100 | H170: =E170*G170 -> 500 | I170: 720 | J170: =I170*E170 -> 3600 | K170: =G170*2 -> 200 | L170: =K170*E170 -> 1000 | M170: S
...

Sheet LACE  - STOCK OVERVIEW
A1: ITEM | B1: BOXES AVAILABLE | C1: TOTAL BOXES IN OFFICE | D1: TOTAL METERS IN OFFICE | E1: TOTAL VALUE IN OFFICE MYR | F1: BOXES SOLD | G1: TOTAL METERS IN SOLD | H1: TOTAL COST VALUE OF SOLD | I1: BOXES PENDING | J1: TOTAL METERS PENDING | K1: TOTAL VALUE OF PENDING | L1: TOTAL BOXES | M1: TOTAL METERS | N1: TOTAL VALUE MYR | O1: NET PROFIT
A2: LACE
A3: PLAIN LACE (PL) | B3: =PL[[#Totals],[ARTICLE ]] -> 43 | C3: =I3+B3 -> 46 | D3: ='LACE - ALL'!E56 -> 213.1 | E3: ='LACE - ALL'!H56 -> 33683.5 | F3: ='LACE - SOLD'!C32 -> 16 | G3: ='LACE - SOLD'!E32 -> 78.3 | H3: ='LACE - SOLD'!J32 -> 11238.6 | I3: ='LACE - PENDING'!C18 -> 3 | J3: ='LACE - PENDING'!E18 -> 14.4 | K3: ='LACE - PENDING'!G18 -> 2160 | L3: =F3+I3+B3 -> 62 | M3: =D3+G3+J3 -> 305.8 | N3: =H3+K3+E3 -> 47082.1 | O3: ='LACE - SOLD'!L32 -> 14349.68
A4: LUREXLACE (LL) | B4: ='LACE - ALL'!C111 -> 50 | C4: =I4+B4 -> 51 | D4: ='LACE - ALL'!E111 -> 238.4 | E4: ='LACE - ALL'!H111 -> 63176 | F4: ='LACE - SOLD'!C56 -> 17 | G4: ='LACE - SOLD'!E56 -> 82.2 | H4: ='LACE - SOLD'!J56 -> 21860.91 | I4: ='LACE - PENDING'!C30 -> 1 | J4: ='LACE - PENDING'!E30 -> 4.7 | K4: ='LACE - PENDING'!G30 -> 1245.5 | L4: =F4+I4+B4 -> 68 | M4: =D4+G4+J4 -> 325.3 | N4: =H4+K4+E4 -> 86282.41 | O4: ='LACE - SOLD'!L56 -> 26736.891
A5: CASA DELLO (CD) | B5: =CD[[#Totals],[ARTICLE ]] -> 34 | C5: =I5+B5 -> 34 | D5: ='LACE - ALL'!E151 -> 156.8 | E5: ='LACE - ALL'!H151 -> 28684 | F5: ='LACE - SOLD'!C91 -> 18 | G5: ='LACE - SOLD'!E91 -> 93 | H5: ='LACE - SOLD'!J91 -> 15106.08 | I5: ='LACE - PENDING'!C40 -> 0 | J5: ='LACE - PENDING'!E40 -> 0 | K5: ='LACE - PENDING'!G40 -> 0 | L5: =F5+I5+B5 -> 52 | M5: =D5+G5+J5 -> 249.8 | N5: =H5+K5+E5 -> 43790.08 | O5: ='LACE - SOLD'!L91 -> 30607.227
A6: LACE (BEIRUT) | B6: ='LACE - ALL'!B252 -> 93 | C6: =I6+B6 -> 93 | D6: ='LACE - ALL'!E252 -> 591.2 | E6: ='LACE - ALL'!H252 -> 135555 | F6: ='LACE - SOLD'!C100 -> 2 | G6: ='LACE - SOLD'!E100 -> 12.8 | H6: ='LACE - SOLD'!J100 -> 1920 | I6: ='LACE - PENDING'!C50 -> 0 | J6: ='LACE - PENDING'!E50 -> 0 | K6: ='LACE - PENDING'!G50 -> 0 | L6: =F6+I6+B6 -> 95 | M6: =D6+G6+J6 -> 604 | N6: =H6+K6+E6 -> 137475 | O6: ='LACE - SOLD'!L100 -> 120
A7: RICCIARINI CORD LACE (70) | B7: ='LACE - ALL'!B329 -> 70 | C7: =I7+B7 -> 70 | D7: ='LACE - ALL'!E329 -> 330 | E7: ='LACE - ALL'!H329 -> 9900 | F7: ='LACE - SOLD'!C109 -> 0 | G7: ='LACE - SOLD'!E109 -> 0 | H7: ='LACE - SOLD'!J109 -> 0 | I7: ='LACE - PENDING'!C61 -> 0 | J7: ='LACE - PENDING'!E61 -> 0 | K7: ='LACE - PENDING'!G61 -> 0 | L7: =F7+I7+B7 -> 70 | M7: =D7+G7+J7 -> 330 | N7: =H7+K7+E7 -> 9900 | O7: ='LACE - SOLD'!L109 -> 0
A8: LACE TOTAL | B8: =SUM(B3:B7) -> 290 | C8: =SUM(C3:C7) -> 294 | D8: =SUM(D3:D7) -> 1529.5 | E8: =SUM(E3:E7) -> 270998.5 | F8: =SUM(F3:F7) -> 53 | G8: =SUM(G3:G7) -> 266.3 | H8: =SUM(H3:H7) -> 50125.59 | I8: =SUM(I3:I7) -> 4 | ... O8: =SUM(O3:O7) -> 71813.798

Sheet LACE - ALL
A1: UPDATED ON | F1: UPDATED BY IBRAHIM
A2: DESCRIPTION 31 OCT 2024 | D2: PIECES | F2: VIP-M | I2: NOTED: SOME LINEATRE (LINEA) NOT LISTED .COZ OF SHORT PIECES
F3: Sherry - S | H3: PENDING-P
F4: Angie - A
F5: Fong king - FK
F6: Bani -B
F7: MR. Cetin- C | I7: Total Cost | K7: =H56+H111+H151+H252+H329 -> 270998.5
F8: MS. KLARA-K
A11: LAGATOLA PLAN LACE (P.L)
A12: NO | B12: DESIGN | C12: ARTICLE | D12: QUALITY | E12: QTY (m) | F12: COST PER MT EURO | G12: COST PER MT RM | H12: COST PIECE RM | I12: V.I.P PER MT RM | J12: V.I.P PIECE RM | K12: SELLING PER MT RM | L12: SELLING PIECE RM | M12: SOLD TO
A13: 1 | B13: SOL-PL-EAS-2 | C13: ML 007314-090-0 | D13: BONIFICO | E13: 5.3 | F13: 30 | G13: =F13*5 -> 150 | H13: =G13*E13 -> 795 | I13: 918 | J13: =I13*E13 -> 4865.4 | K13: =I13/2 -> 459 | L13: =K13*E13 -> 2432.7
A14: 2 | B14: SOL-PL-ESS-4 | C14: ML 007314-090-0 | D14: BONIFICO | E14: 4.8 | F14: 30 | G14: =F14*5 -> 150 | H14: =G14*E14 -> 720 | I14: 918 | J14: =I14*E14 -> 4406.4 | K14: =I14/2 -> 459 | L14: =K14*E14 -> 2203.2
A15: 3 | B15: SOL-PL-ESS-6 | C15: ML 007314-090-0 | D15: BALZATO | E15: 5 | F15: 30 | G15: =F15*5 -> 150 | H15: =G15*E15 -> 750 | I15: 918 | J15: =I15*E15 -> 4590 | K15: =I15/2 -> 459 | L15: =K15*E15 -> 2295
A16: 4 | B16: SOL-PL-ESS-8 | C16: ML 007314-090-0 | D16: BLUE | E16: 5 | F16: 30 | G16: =F16*5 -> 150 | H16: =G16*E16 -> 750 | I16: 918 | J16: =I16*E16 -> 4590 | K16: =I16/2 -> 459 | L16: =K16*E16 -> 2295
A17: 5 | B17: SOL-PL-DDSS-9 | C17: ML 007314-090-0 | D17: RED | E17: 5.9 | F17: 30 | G17: =F17*5 -> 150 | H17: =G17*E17 -> 885 | I17: 918 | J17: =I17*E17 -> 5416.2 | K17: =I17/2 -> 459 | L17: =K17*E17 -> 2708.1
A18: 6 | B18: SOL-PL-EAS-10 | C18: ML 007314-090-0 | D18: BONIFICO | E18: 5.2 | F18: 30 | G18: =F18*5 -> 150 | H18: =G18*E18 -> 780 | I18: 918 | J18: =I18*E18 -> 4773.6 | K18: =I18/2 -> 459 | L18: =K18*E18 -> 2386.8
A19: 7 | B19: SOL-PL-DSSS-13 | C19: ML 007314-090-0 | D19: BONIFICO | E19: 5.4 | F19: 30 | G19: =F19*5 -> 150 | H19: =G19*E19 -> 810 | I19: 918 | J19: =I19*E19 -> 4957.2 | K19: =I19/2 -> 459 | L19: =K19*E19 -> 2478.6
A20: 8 | B20: SOL-PL-EAS-14 | C20: ML 007314-090-0 | D20: PIENO | E20: 5.2 | F20: 30 | G20: =F20*5 -> 150 | H20: =G20*E20 -> 780 | I20: 918 | J20: =I20*E20 -> 4773.6 | K20: =I20/2 -> 459 | L20: =K20*E20 -> 2386.8
A21: 9 | B21: SOL-PL-VSS-18 | C21: ML 007314-090-0 | D21: BONIFICO | E21: 4.3 | F21: 30 | G21: =F21*5 -> 150 | H21: =G21*E21 -> 645 | I21: 918 | J21: =I21*E21 -> 3947.4 | K21: =I21/2 -> 459 | L21: =K21*E21 -> 1973.7
A22: 10 | B22: SOL-PL-VAS-19 | C22: ML 007314-090-0 | D22: BONIFICO | E22: 4.6 | F22: 30 | G22: =F22*5 -> 150 | H22: =G22*E22 -> 690 | I22: 918 | J22: =I22*E22 -> 4222.8 | K22: =I22/2 -> 459 | L22: =K22*E22 -> 2111.4
A23: 11 | B23: SOL-PL-ESS-21 | C23: ML 007314-090-0 | D23: BLUE | E23: 4.8 | F23: 30 | G23: =F23*5 -> 150 | H23: =G23*E23 -> 720 | I23: 918 | J23: =I23*E23 -> 4406.4 | K23: =I23/2 -> 459 | L23: =K23*E23 -> 2203.2
A24: 12 | B24: SOL-PL-EAS-24 | C24: ML 007314-090-0 | D24: IVORY | E24: 5.2 | F24: 30 | G24: =F24*5 -> 150 | H24: =G24*E24 -> 780 | I24: 918 | J24: =I24*E24 -> 4773.6 | K24: =I24/2 -> 459 | L24: =K24*E24 -> 2386.8
... A54: 42 | B54: SOL-PL-DSSS-164 | C54: 43 007245 85 90 | D54: BONIFICO | E54: 5.4 | F54: 30 | G54: =F54*5 -> 150 | H54: =G54*E54 -> 810 | I54: 918 | J54: =I54*E54 -> 4957.2 | K54: =I54/2 -> 459 | L54: =K54*E54 -> 2478.6
A55: 43 | B55: SOL-PL-VSS-165 | C55: 43 007245 85 90 | D55: LACE | E55: 4 | F55: 30 | G55: 150 | H55: 600 | I55: 918 | J55: 3000 | K55: =I55/2 -> 459 | L55: 1800
A56: TOTAL COST | C56: =COUNTA(PL[[ARTICLE ]]) -> 43 | E56: =SUM(E12:E55) -> 213.1 | H56: =SUM(H12:H55) -> 33683.5
A59: LAGATOLALUREXLACE (L.L)
A60: NO | B60: DESIGN | C60: ARTICLE | D60: QUALITY | E60: QTY (m) | F60: COST PER MT EURO | G60: COST PER MT RM | H60: COST PIECE RM | I60: V.I.P PER MT RM | J60: V.I.P PIECE RM | K60: SELLING PER MT RM | L60: SELLING PIECE RM | M60: SOLD TO
A61: 44 | B61: SOL-LL-DSSS-243 | C61: 7001-140-0 | D61: GOLD/BROWN | E61: 3.4 | F61: 53 | G61: =F61*5 -> 265 | H61: =G61*E61 -> 901 | I61: 1621.8 | J61: =I61*E61 -> 5514.12 | K61: =I61/2 -> 810.9 | L61: =K61*E61 -> 2757.06
A62: 45 | B62: SOL-LL-DUSS-244 | C62: 7001-140-0 | D62: LUREXLACE | E62: 4 | F62: 53 | G62: =F62*5 -> 265 | H62: =G62*E62 -> 1060 | I62: 1621.8 | J62: =I62*E62 -> 6487.2 | K62: =I62/2 -> 810.9 | L62: =K62*E62 -> 3243.6
A63: 46 | B63: SOL-LL-DASS-246 | C63: 7001-140-0 | D63: BALZATO | E63: 4.9 | F63: 53 | G63: =F63*5 -> 265 | H63: =G63*E63 -> 1298.5 | I63: 1621.8 | J63: =I63*E63 -> 7946.82 | K63: =I63/2 -> 810.9 | L63: =K63*E63 -> 3973.41
A64: 47 | B64: SOL-LL-DGSS-247 | C64: 7001-140-0 | D64: SILVER / PEACH | E64: 4.6 | F64: 53 | G64: =F64*5 -> 265 | H64: =G64*E64 -> 1219 | I64: 1621.8 | J64: =I64*E64 -> 7460.28 | K64: =I64/2 -> 810.9 | L64: =K64*E64 -> 3730.14
A65: 48 | B65: SOL-LL-DGSS-248 | C65: 7001-140-0 | D65: PIZZO | E65: 4.2 | F65: 53 | G65: =F65*5 -> 265 | H65: =G65*E65 -> 1113 | I65: 1621.8 | J65: =I65*E65 -> 6811.56 | K65: =I65/2 -> 810.9 | L65: =K65*E65 -> 3405.78
A66: 49 | B66: SOL-LL-DASS-250 | C66: 7316-140-0 | D66: LUREXLACE | E66: 4.9 | F66: 53 | G66: =F66*5 -> 265 | H66: =G66*E66 -> 1298.5 | I66: 1621.8 | J66: =I66*E66 -> 7946.82 | K66: =I66/2 -> 810.9 | L66: =K66*E66 -> 3973.41
A67: 50 | B67: SOL-LL-DGSS-251 | C67: 7316-140-0 | D67: GOLD/ GOLD | E67: 4.6 | F67: 53 | G67: =F67*5 -> 265 | H67: =G67*E67 -> 1219 | I67: 1621.8 | J67: =I67*E67 -> 7460.28 | K67: =I67/2 -> 810.9 | L67: =K67*E67 -> 3730.14
A68: 51 | B68: SOL-LL-DGSS-255 | C68: 7316-140-0 | D68: PIZZO | E68: 4.7 | F68: 53 | G68: =F68*5 -> 265 | H68: =G68*E68 -> 1245.5 | I68: 1621.8 | J68: =I68*E68 -> 7622.46 | K68: =I68/2 -> 810.9 | L68: =K68*E68 -> 3811.23
A69: 52 | B69: SOL-LL-DASS-257 | C69: 7316-140-0 | D69: PIZZO | E69: 4.9 | F69: 53 | G69: =F69*5 -> 265 | H69: =G69*E69 -> 1298.5 | I69: 1621.8 | J69: =I69*E69 -> 7946.82 | K69: =I69/2 -> 810.9 | L69: =K69*E69 -> 3973.41
A70: 53 | B70: SOL-LL-DGSS-258 | C70: 7316-140-0 | D70: PIZZO | E70: 4.7 | F70: 53 | G70: =F70*5 -> 265 | H70: =G70*E70 -> 1245.5 | I70: 1621.8 | J70: =I70*E70 -> 7622.46 | K70: =I70/2 -> 810.9 | L70: =K70*E70 -> 3811.23
A71: 54 | B71: SOL-LL-DSAS-260 | C71: 7246.140.0 | D71: BALZATO | E71: 3.5 | F71: 53 | G71: =F71*5 -> 265 | H71: =G71*E71 -> 927.5 | I71: 1621.8 | J71: =I71*E71 -> 5676.3 | K71: =I71/2 -> 810.9 | L71: =K71*E71 -> 2838.15
A72: 55 | B72: SOL-LL-DNSS-262 | C72: 7246.140.0 | D72: BALZATO | E72: 5.2 | F72: 53 | G72: =F72*5 -> 265 | H72: =G72*E72 -> 1378 | I72: 1621.8 | J72: =I72*E72 -> 8433.36 | K72: =I72/2 -> 810.9 | L72: =K72*E72 -> 4216.68
... A110: 93 | B110: SOL-LL-DSAS-305 | C110: 7331.140.0 | D110: GOLD | E110: 3.5 | F110: 53 | G110: =F110*5 -> 265 | H110: =G110*E110 -> 927.5 | I110: 1621.8 | J110: =I110*E110 -> 5676.3 | K110: =I110/2 -> 810.9 | L110: =K110*E110 -> 2838.15
A111: TOTAL COST | C111: =COUNTA(C61:C110) -> 50 | E111: =SUM(E61:E110) -> 238.4 | H111: =SUM(H61:H110) -> 63176
A115: CASA DELLO -SOLSTISS (CD)
A116: NO | B116: DESIGN | C116: ARTICLE | D116: QUALITY | E116: QTY (m) | F116: COST PER MT EURO | G116: COST PER MT RM | H116: COST PIECE RM | I116: V.I.P PER MT RM | J116: V.I.P PIECE RM | K116: SELLING PER MT RM | L116: SELLING PIECE RM | M116: SOLD TO
A117: 94 | B117: SOL-CD-DSSS-110 | C117: 33-B22726-PL | D117: RUST | E117: 5.6 | F117: 27 | G117: 135 | H117: =G117*E117 -> 756 | I117: 918 | J117: 3780 | K117: 270 | L117: 1512
A118: 95 | B118: SOL-CD-DUSS-121 | C118: 50810369-LL | D118: KAKI / SUNDAE | E118: 5.5 | F118: 35 | G118: 175 | H118: =G118*E118 -> 962.5 | I118: 875 | J118: 4812.5 | K118: 350 | L118: 1925
A119: 96 | B119: SOL-CD-DUSS-133 | C119: 102-LL | D119: GOLD | E119: 5.4 | F119: 35 | G119: 175 | H119: =G119*E119 -> 945 | I119: 875 | J119: 4725 | K119: 350 | L119: 1890
A120: 97 | B120: SOL-CD-VSS-134 | C120: 102-LL | D120: LACE | E120: 5.5 | F120: 35 | G120: 175 | H120: =G120*E120 -> 962.5 | I120: 875 | J120: 4812.5 | K120: 350 | L120: 1925
A121: 98 | B121: SOL-CD-DUSS-135 | C121: 102-LL | D121: LACE | E121: 3.6 | F121: 35 | G121: 175 | H121: =G121*E121 -> 630 | I121: 875 | J121: 4812.5 | K121: 350 | L121: 1925
A122: 99 | B122: SOL-CD-DSSS-136 | C122: 102-LL | D122: BOURGOGNE / GOLD | E122: 4.3 | F122: 35 | G122: 175 | H122: =G122*E122 -> 752.5 | I122: 875 | J122: 3762.5 | K122: 350 | L122: 1505
A123: 100 | B123: SOL-CD-DSSS-138 | C123: 102-LL | D123: DARK OLIVE | E123: 4.5 | F123: 35 | G123: 175 | H123: =G123*E123 -> 787.5 | I123: 875 | J123: 3937.5 | K123: 350 | L123: 1575
A124: 101 | B124: SOL-CD-EAS-139 | C124: 102-LL | D124: LACE | E124: 4.2 | F124: 35 | G124: 175 | H124: =G124*E124 -> 735 | I124: 875 | J124: 3675 | K124: 350 | L124: 1470
A125: 102 | B125: SOL-CD-ESS-140 | C125: 102-LL | D125: BLACK / GOLD | E125: 4.3 | F125: 35 | G125: 175 | H125: =G125*E125 -> 752.5 | I125: 875 | J125: 3762.5 | K125: 350 | L125: 1505
A126: 103 | B126: SOL-CD-ESS-141 | C126: 102-LL | D126: GOLD | E126: 4.3 | F126: 35 | G126: 175 | H126: =G126*E126 -> 752.5 | I126: 875 | J126: 3762.5 | K126: 350 | L126: 1505
A127: 104 | B127: SOL-CD-DUSS-142 | C127: 102-LL | D127: LACE | E127: 5.5 | F127: 35 | G127: 175 | H127: =G127*E127 -> 962.5 | I127: 875 | J127: 4812.5 | K127: 350 | L127: 1925
A128: 105 | B128: SOL-CD-ESS-144 | C128: 102-LL | D128: LACE | E128: 4.3 | F128: 35 | G128: 175 | H128: =G128*E128 -> 752.5 | I128: 875 | J128: 3762.5 | K128: 350 | L128: 1505
... A131: 108 | B131: SOL-CD-DUSS-148 | C131: 102-LL | D131: GLAZE / GOLD | E131: 5.4 | F131: 35 | G131: 175 | H131: =G131*E131 -> 945 | I131: 875 | J131: 4725 | K131: 350 | L131: 1890
A132: 109 | B132: SOL-CD-DRSS-149 | C132: KHAKI-LL | D132: LUREXLACE | E132: 5.6 | F132: 35 | G132: =F132*5 -> 175 | H132: =G132*E132 -> 980 | I132: =G132*5 -> 875 | J132: =I132*E132 -> 4900 | K132: =G132*2 -> 350 | L132: =K132*E132 -> 1960
A133: 110 | B133: SOL-CD-ESS-150 | C133: 102-LL | D133: GREEN / PURPLE | E133: 4 | F133: 35 | G133: 175 | H133: =G133*E133 -> 700 | I133: 875 | J133: 3500 | K133: 350 | L133: 1400
A134: 111 | B134: SOL-CD-DRSS-151 | C134: BLUSH/EBENE-PL | D134: LUREXLACE | E134: 5.7 | F134: 35 | G134: 175 | H134: 918 | I134: 875 | J134: 4987.5 | K134: 350 | L134: 1995
A135: 112 | B135: SOL-CD-DSSS-152 | C135: 102-LL | D135: SARCELLE / COPPER | E135: 4.3 | F135: 35 | G135: 175 | H135: =G135*E135 -> 752.5 | I135: 875 | J135: 3762.5 | K135: 350 | L135: 1505
A136: 113 | B136: SOL-CD-DDSS-154 | C136: 230360-LL | D136: GOLD | E136: 4.8 | F136: 40 | G136: 200 | H136: =G136*E136 -> 960 | I136: 1000 | J136: 4800 | K136: 400 | L136: 1920
A137: 114 | B137: SOL-CD-DDSS-155 | C137: 230360-LL | D137: LACE | E137: 5 | F137: 40 | G137: 200 | H137: =G137*E137 -> 1000 | I137: 1000 | J137: 5000 | K137: 400 | L137: 2000
A138: 115 | B138: SOL-CD-DRAS-156 | C138: 30335-LL | D138: GOLD / DEEP GOLD | E138: 6 | F138: 50 | G138: 250 | H138: =G138*E138 -> 1500 | I138: 1250 | J138: 7500 | K138: 500 | L138: 3000
A139: 116 | B139: SOL-CD-DDSS-157 | C139: 102-LL | D139: VERT DE GRIS | E139: 4.7 | F139: 35 | G139: 175 | H139: =G139*E139 -> 822.5 | I139: 875 | J139: 4112.5 | K139: 350 | L139: 1645
A140: 117 | B140: SOL-CD-DUSS-158 | C140: 102-LL | D140: LACE | E140: 5.4 | F140: 40 | G140: 200 | H140: =G140*E140 -> 1080 | I140: 1000 | J140: 5400 | K140: 400 | L140: 2160
A141: 118 | B141: SOL-CD-DUSS-159 | C141: 102-PL | D141: PURPLE | E141: 5.5 | F141: 27 | G141: 135 | H141: =G141*E141 -> 742.5 | I141: 675 | J141: 3712.5 | K141: 270 | L141: 1485
A142: 119 | B142: SOL-CD-DUSS-160 | C142: 1B12718-PL | D142: MIEL | E142: 5.4 | F142: 27 | G142: 135 | H142: =G142*E142 -> 729 | I142: 675 | J142: 3645 | K142: 270 | L142: 1458
A143: 120 | B143: SOL-CD-DSSS-162 | C143: 49 B47542-LL | D143: RUST / SILVER | E143: 4.3 | F143: 35 | G143: 175 | H143: =G143*E143 -> 752.5 | I143: 875 | J143: 3762.5 | K143: 350 | L143: 1505
A144: 121 | B144: SOL-CD-DDSS-163 | C144: 2376285-PL | D144: MAGENTA | E144: 4.9 | F144: 35 | G144: 175 | H144: =G144*E144 -> 857.5 | I144: 875 | J144: 4287.5 | K144: 350 | L144: 1715
A145: 122 | B145: SOL-CD-DUSS-164 | C145: 4 410315-LL | D145: RED | E145: 5.5 | F145: 35 | G145: 175 | H145: =G145*E145 -> 962.5 | I145: 875 | J145: 4812.5 | K145: 350 | L145: 1925
A146: 123 | B146: SOL-CD-ESS-166 | C146: 4410315-LL | D146: LACE | E146: 4.7 | F146: 27 | G146: 135 | H146: =G146*E146 -> 634.5 | I146: 675 | J146: 3172.5 | K146: 270 | L146: 1269
... A148: 125 | B148: SOL-CD-EAS-168 | C148: 49 B47542-LL | D148: BROWN / GOLD | E148: 4.3 | F148: 35 | G148: 175 | H148: =G148*E148 -> 752.5 | I148: 875 | J148: 3762.5 | K148: 350 | L148: 1505
A149: 126 | B149: SOL-CD-ESS-169 | C149: 102-PL | D149: VIOLET / POUDRE | E149: 5.1 | F149: 27 | G149: =F149*5 -> 135 | H149: =G149*E149 -> 688.5 | I149: =G149*5 -> 675 | J149: =I149*E149 -> 3442.5 | K149: =G149*2 -> 270 | L149: =K149*E149 -> 1377
A150: 127 | B150: SOL-CD-DSSS-171 | C150: 23.B39617-PL | D150: GREEN | E150: 5.6 | F150: 27 | G150: 135 | H150: =G150*E150 -> 756 | I150: 675 | J150: 3780 | K150: 270 | L150: 1512
A151: TOTAL COST | C151: =COUNTA(CD[[ARTICLE ]]) -> 34 | E151: =SUM(E116:E150) -> 156.8 | H151: =SUM(H117:H150) -> 28684
A157: BEIRUT LACE (BEI)
A158: NO | B158: DESIGN | C158: ARTICLE | D158: QUALITY | E158: QTY (m) | F158: COST PER MT EURO | G158: COST PER MT RM | H158: COST PIECE RM | I158: V.I.P PER MT RM | J158: V.I.P PIECE RM | K158: SELLING PER MT RM | L158: SELLING PIECE RM | M158: SOLD TO
A159: 128 | B159: DRSS 1 | C159: FSH 538 | D159: DARK GREEN | E159: 6.4 | F159: 30 | G159: =F159*5 -> 150 | H159: =E159*G159 -> 960 | I159: =G159*5 -> 750 | J159: =I159*E159 -> 4800 | K159: =I159/2 -> 375 | L159: =K159*E159 -> 2400
A160: 129 | B160: DRSS 2 | C160: FSH 538 | D160: BLUE | E160: 6.4 | F160: 30 | G160: =F160*5 -> 150 | H160: =E160*G160 -> 960 | I160: =G160*5 -> 750 | J160: =I160*E160 -> 4800 | K160: =I160/2 -> 375 | L160: =K160*E160 -> 2400
A161: 130 | B161: DRSS 3 | C161: FSH 538 | D161: TURQUOISE | E161: 6.4 | F161: 30 | G161: =F161*5 -> 150 | H161: =E161*G161 -> 960 | I161: =G161*5 -> 750 | J161: =I161*E161 -> 4800 | K161: =I161/2 -> 375 | L161: =K161*E161 -> 2400
A162: 131 | B162: DRSS 4 | C162: FSH 538 | D162: GRAY | E162: 6.4 | F162: 30 | G162: =F162*5 -> 150 | H162: =E162*G162 -> 960 | I162: =G162*5 -> 750 | J162: =I162*E162 -> 4800 | K162: =I162/2 -> 375 | L162: =K162*E162 -> 2400
A163: 132 | B163: DRSS 5 | C163: FSH 538 | D163: BLACK | E163: 6.4 | F163: 30 | G163: =F163*5 -> 150 | H163: =E163*G163 -> 960 | I163: =G163*5 -> 750 | J163: =I163*E163 -> 4800 | K163: =I163/2 -> 375 | L163: =K163*E163 -> 2400
A164: 133 | B164: DRSS 6 | C164: FSH 538 | D164: GOLD | E164: 6.4 | F164: 30 | G164: =F164*5 -> 150 | H164: =E164*G164 -> 960 | I164: =G164*5 -> 750 | J164: =I164*E164 -> 4800 | K164: =I164/2 -> 375 | L164: =K164*E164 -> 2400
A165: 134 | B165: DRSS 8 | C165: AN35370 | D165: BLUE | E165: 6.4 | F165: 30 | G165: =F165*5 -> 150 | H165: =E165*G165 -> 960 | I165: =G165*5 -> 750 | J165: =I165*E165 -> 4800 | K165: =I165/2 -> 375 | L165: =K165*E165 -> 2400
A166: 135 | B166: DRSS 9 | C166: AN35370 | D166: DARK BLUE | E166: 6.4 | F166: 30 | G166: =F166*5 -> 150 | H166: =E166*G166 -> 960 | I166: =G166*5 -> 750 | J166: =I166*E166 -> 4800 | K166: =I166/2 -> 375 | L166: =K166*E166 -> 2400
A167: 136 | B167: DRSS 10 | C167: AN35370 | D167: BLACK | E167: 6.4 | F167: 30 | G167: =F167*5 -> 150 | H167: =E167*G167 -> 960 | I167: =G167*5 -> 750 | J167: =I167*E167 -> 4800 | K167: =I167/2 -> 375 | L167: =K167*E167 -> 2400
A168: 137 | B168: DRSS 11 | C168: AN35369 | D168: TURQUOISE | E168: 6.4 | F168: 30 | G168: =F168*5 -> 150 | H168: =E168*G168 -> 960 | I168: =G168*5 -> 750 | J168: =I168*E168 -> 4800 | K168: =I168/2 -> 375 | L168: =K168*E168 -> 2400
A169: 138 | B169: DRSS 12 | C169: AN35369 | D169: ROYAL BLUE | E169: 6.4 | F169: 30 | G169: =F169*5 -> 150 | H169: =E169*G169 -> 960 | I169: =G169*5 -> 750 | J169: =I169*E169 -> 4800 | K169: =I169/2 -> 375 | L169: =K169*E169 -> 2400
A170: 139 | B170: DRSS 13 | C170: AN35369 | D170: NAVY | E170: 6.4 | F170: 30 | G170: =F170*5 -> 150 | H170: =E170*G170 -> 960 | I170: =G170*5 -> 750 | J170: =I170*E170 -> 4800 | K170: =I170/2 -> 375 | L170: =K170*E170 -> 2400
... A228: 197 | B228: UNSS 83 | C228: N 38368 | D228: SKIN | E228: 6.4 | F228: 60 | G228: =F228*5 -> 300 | H228: =E228*G228 -> 1920 | I228: =G228*5 -> 1500 | J228: =I228*E228 -> 9600 | K228: =I228/2 -> 750 | L228: =K228*E228 -> 4800
A229: 198 | B229: UNSS 84 | D229: SKIN | RED | E229: 6.4 | F229: 60 | G229: =F229*5 -> 300 | H229: =E229*G229 -> 1920 | I229: =G229*5 -> 1500 | J229: =I229*E229 -> 9600 | K229: =I229/2 -> 750 | L229: =K229*E229 -> 4800
A230: 199 | B230: UNSS 85 | D230: WHITE | E230: 6.4 | F230: 60 | G230: =F230*5 -> 300 | H230: =E230*G230 -> 1920 | I230: =G230*5 -> 1500 | J230: =I230*E230 -> 9600 | K230: =I230/2 -> 750 | L230: =K230*E230 -> 4800
A231: 200 | B231: UGSS 86 | C231: 1006 | D231: SKIN | E231: 6 | F231: 60 | G231: =F231*5 -> 300 | H231: =E231*G231 -> 1800 | I231: =G231*5 -> 1500 | J231: =I231*E231 -> 9000 | K231: =I231/2 -> 750 | L231: =K231*E231 -> 4500
A232: 201 | B232: UGSS 87 | C232: 1077 150 PF 1086 | E232: 6 | F232: 60 | G232: =F232*5 -> 300 | H232: =E232*G232 -> 1800 | I232: =G232*5 -> 1500 | J232: =I232*E232 -> 9000 | K232: =I232/2 -> 750 | L232: =K232*E232 -> 4500
A233: 202 | B233: UGSS 88 | C233: 1006 U3 J 1029 | E233: 6 | F233: 60 | G233: =F233*5 -> 300 | H233: =E233*G233 -> 1800 | I233: =G233*5 -> 1500 | J233: =I233*E233 -> 9000 | K233: =I233/2 -> 750 | L233: =K233*E233 -> 4500
A234: 203 | B234: UGSS 89 | D234: BLACK | YELLOW | E234: 6 | F234: 60 | G234: =F234*5 -> 300 | H234: =E234*G234 -> 1800 | I234: =G234*5 -> 1500 | J234: =I234*E234 -> 9000 | K234: =I234/2 -> 750 | L234: =K234*E234 -> 4500
A235: 204 | B235: UGSS 90 | D235: SKIN | E235: 6 | F235: 60 | G235: =F235*5 -> 300 | H235: =E235*G235 -> 1800 | I235: =G235*5 -> 1500 | J235: =I235*E235 -> 9000 | K235: =I235/2 -> 750 | L235: =K235*E235 -> 4500
A236: 205 | B236: UGSS 91 | C236: AN 38368 | D236: NAVS | E236: 6 | F236: 60 | G236: =F236*5 -> 300 | H236: =E236*G236 -> 1800 | I236: =G236*5 -> 1500 | J236: =I236*E236 -> 9000 | K236: =I236/2 -> 750 | L236: =K236*E236 -> 4500
A237: 206 | B237: UGSS 92 | C237: AN 38368 | D237: BLACK | E237: 6 | F237: 60 | G237: =F237*5 -> 300 | H237: =E237*G237 -> 1800 | I237: =G237*5 -> 1500 | J237: =I237*E237 -> 9000 | K237: =I237/2 -> 750 | L237: =K237*E237 -> 4500
A238: 207 | B238: UGSS 93 | C238: AN 38368 | D238: SKIN | E238: 6 | F238: 60 | G238: =F238*5 -> 300 | H238: =E238*G238 -> 1800 | I238: =G238*5 -> 1500 | J238: =I238*E238 -> 9000 | K238: =I238/2 -> 750 | L238: =K238*E238 -> 4500
...

Sheet LACE - STOCK OVERVIEW
A4: 2. LACE
A5: ITEM | B5: TOTAL METER | C5: TOTAL BOXES | D5: SOLD | E5: PENDING | F5: AVAILABLE | G5: TOTAL COST
A6: PLAIN LACE (PL) | B6: ='LACE - ALL'!E56 -> 213.1 | C6: =D6+E6+F6 -> 43 | E6: 0 | F6: =COUNTA('LACE - ALL'!B13:B55) -> 43
A7: LUREXLACE (LL) | B7: ='LACE - ALL'!E111 -> 238.4 | C7: =D7+E7+F7 -> 50 | F7: =COUNTA('LACE - ALL'!B61:B110) -> 50
A8: CASA DELLO (CD) | B8: ='LACE - ALL'!E151 -> 156.8 | C8: =D8+E8+F8 -> 34 | F8: =COUNTA('LACE - ALL'!B117:B150) -> 34
A9: SILK TOTAL | C9: =SUM(C4:C8) -> 127 | D9: =SUM(D6:D8) -> 0 | E9: =SUM(E6:F8) -> 127 | F9: =SUM(F6:F8) -> 127 | G9: =SUM(G6:G8) -> 0

Sheet LACE - PENDING
A1: UPDATED ON | F1: UPDATED BY IBRAHIM
A2: DESCRIPTION 31 OCT 2024 | D2: PIECES | F2: VIP-M | I2: NOTED: FOR THE PENDING PCIECES PLEASE CHECK INVIOCE FOR THE GIVEN PRICES
A3: TOTAL | D3: 1058 | F3: Sherry - S | H3: PENDING-P
F4: Angie - A
A5: PENDING | F5: Fong king - FK | I5: Total Cost | K5: =G18+G30+G40 -> 3405.5
A6: SOLD | F6: Bani -B
A7: AVAILABLE | D7: =D3-(D4+D5+D6) -> 1058 | F7: MR. Cetin- C
F8: MS. KLARA-K
A11: LAGATOLA PLAN LACE (P.L) PENDING
A12: NO | B12: DESIGN | C12: ARTICLE | D12: QUALITY | E12: QTY (m) | F12: COST PER MT EURO | G12: COST PER MT RM | H12: COST PIECE RM | I12: V.I.P PER MT RM | J12: V.I.P PIECE RM | K12: SELLING PER MT RM | L12: SELLING PIECE RM | M12: SOLD TO
A13: 1 | B13: SOL-PL-ESS-15 | C13: ML 007314-090-0 | D13: BALZATO | E13: 4.7 | F13: 30 | G13: =F13*5 -> 150 | H13: =G13*E13 -> 705 | I13: =G13*5 -> 750 | J13: =I13*E13 -> 3525 | K13: 459 | L13: =K13*E13 -> 2157.3 | M13: S
A14: 2 | B14: SOL-PL-VAS-23 | C14: ML 007314-090-0 | D14: BEIGE | E14: 4.7 | F14: 30 | G14: =F14*5 -> 150 | H14: =G14*E14 -> 705 | I14: =G14*5 -> 750 | J14: =I14*E14 -> 3525 | K14: 459 | L14: =K14*E14 -> 2157.3 | M14: S
A15: 3 | B15: SOL-PL-ESS-5 | C15: ML 007314-090-0 | D15: GOLD | E15: 5 | F15: 30 | G15: =F15*5 -> 150 | H15: =G15*E15 -> 750 | I15: =G15*5 -> 750 | J15: =I15*E15 -> 3750 | K15: =I15/2 -> 375 | L15: =K15*E15 -> 1875 | M15: S
A16: 4 | M16: S
A17: 5
A18: TOTAL COST | C18: {=COUNTA(C13:INDEX(C:C,ROW()-1))} -> 3 | E18: =SUM(E13:E17) -> 14.4 | G18: =SUBTOTAL(9,H13:H17) -> 2160
A23: LAGATOLALUREXLACE (L.L) PENDING
A24: NO | B24: DESIGN | C24: ARTICLE | D24: QUALITY | E24: QTY | F24: COST PER MT EURO | G24: COST PER MT RM | H24: COST PIECE RM | I24: V.I.P PER MT RM | J24: V.I.P PIECE RM | K24: SELLING PER MT RM | L24: SELLING PIECE RM | M24: SOLD TO
A25: 1 | B25: SOL-LL-DGAS-294 | C25: 7331.140.0 | D25: SILVER | E25: 4.7 | F25: 53 | G25: =F25*5 -> 265 | H25: =G25*E25 -> 1245.5 | I25: =G25*5 -> 1325 | J25: =I25*E25 -> 6227.5 | K25: =I25/2 -> 662.5 | L25: =K25*E25 -> 3113.75
A26: 2 | G26: =F26*5 -> 0 | H26: =G26*E26 -> 0 | I26: =G26*5 -> 0 | J26: =I26*E26 -> 0 | K26: =I26/2 -> 0 | L26: =K26*E26 -> 0
A27: 3 | G27: =F27*5 -> 0 | H27: =G27*E27 -> 0 | I27: =G27*5 -> 0 | J27: =I27*E27 -> 0 | K27: =I27/2 -> 0 | L27: =K27*E27 -> 0
A28: 4 | G28: =F28*5 -> 0 | H28: =G28*E28 -> 0 | I28: =G28*5 -> 0 | J28: =I28*E28 -> 0 | K28: =I28/2 -> 0 | L28: =K28*E28 -> 0
A29: 5 | G29: =F29*5 -> 0 | H29: =G29*E29 -> 0 | I29: =G29*5 -> 0 | J29: =I29*E29 -> 0 | K29: =I29/2 -> 0 | L29: =K29*E29 -> 0
A30: TOTAL COST | C30: {=COUNTA(C25:INDEX(C:C,ROW()-1))} -> 1 | E30: =SUM(E25:E29) -> 4.7 | G30: =SUBTOTAL(9,H25:H29) -> 1245.5
A33: CASA DELLO -SOLSTISS (CD) PENDING
A34: NO | B34: DESIGN | C34: ARTICLE | D34: QUALITY | E34: QTY | F34: COST PER MT EURO | G34: COST PER MT RM | H34: COST PIECE RM | I34: V.I.P PER MT RM | J34: V.I.P PIECE RM | K34: SELLING PER MT RM | L34: SELLING PIECE RM | M34: SOLD TO
A35: 1 | G35: =F35*5 -> 0 | H35: =G35*E35 -> 0 | I35: =G35*5 -> 0 | J35: =I35*E35 -> 0 | K35: =I35/2 -> 0 | L35: =K35*E35 -> 0
A36: 2 | G36: =F36*5 -> 0 | H36: =G36*E36 -> 0 | I36: =G36*5 -> 0 | J36: =I36*E36 -> 0 | K36: =I36/2 -> 0 | L36: =K36*E36 -> 0
A37: 3 | G37: =F37*5 -> 0 | H37: =G37*E37 -> 0 | I37: =G37*5 -> 0 | J37: =I37*E37 -> 0 | K37: =I37/2 -> 0 | L37: =K37*E37 -> 0
A38: 4 | G38: =F38*5 -> 0 | H38: =G38*E38 -> 0 | I38: =G38*5 -> 0 | J38: =I38*E38 -> 0 | K38: =I38/2 -> 0 | L38: =K38*E38 -> 0
A39: 5 | G39: =F39*5 -> 0 | H39: =G39*E39 -> 0 | I39: =G39*5 -> 0 | J39: =I39*E39 -> 0 | K39: =I39/2 -> 0 | L39: =K39*E39 -> 0
A40: TOTAL COST | C40: {=COUNTA(C35:INDEX(C:C,ROW()-1))} -> 0 | E40: =SUM(E34:E39) -> 0 | G40: =SUBTOTAL(9,H35:H39) -> 0
A43: BEIRUT LACE (BEI) PENDING
A44: NO | B44: DESIGN | C44: ARTICLE | D44: QUALITY | E44: QTY | F44: COST PER MT EURO | G44: COST PER MT RM | H44: COST PIECE RM | I44: V.I.P PER MT RM | J44: V.I.P PIECE RM | K44: SELLING PER MT RM | L44: SELLING PIECE RM | M44: SOLD TO
A45: 1 | G45: =F45*5 -> 0 | H45: =G45*E45 -> 0 | I45: =G45*5 -> 0 | J45: =I45*E45 -> 0 | K45: =I45/2 -> 0 | L45: =K45*E45 -> 0
A46: 2 | G46: =F46*5 -> 0 | H46: =G46*E46 -> 0 | I46: =G46*5 -> 0 | J46: =I46*E46 -> 0 | K46: =I46/2 -> 0 | L46: =K46*E46 -> 0
A47: 3 | G47: =F47*5 -> 0 | H47: =G47*E47 -> 0 | I47: =G47*5 -> 0 | J47: =I47*E47 -> 0 | K47: =I47/2 -> 0 | L47: =K47*E47 -> 0
A48: 4 | G48: =F48*5 -> 0 | H48: =G48*E48 -> 0 | I48: =G48*5 -> 0 | J48: =I48*E48 -> 0 | K48: =I48/2 -> 0 | L48: =K48*E48 -> 0
A49: 5 | G49: =F49*5 -> 0 | H49: =G49*E49 -> 0 | I49: =G49*5 -> 0 | J49: =I49*E49 -> 0 | K49: =I49/2 -> 0 | L49: =K49*E49 -> 0
A50: TOTAL COST | C50: {=COUNTA(C45:INDEX(C:C,ROW()-1))} -> 0 | E50: =SUM(E44:E49) -> 0 | G50: =SUBTOTAL(9,H45:H49) -> 0
A54: RICCIARINI CORD LACE(PL-R) PENDING
A55: NO | B55: DESIGN | C55: ARTICLE | D55: QUALITY | E55: QTY | F55: COST PER MT EURO | G55: COST PER MT RM | H55: COST PIECE RM | I55: V.I.P PER MT RM | J55: V.I.P PIECE RM | K55: SELLING PER MT RM | L55: SELLING PIECE RM | M55: SOLD TO
A56: 1 | G56: =F56*5 -> 0 | H56: =G56*E56 -> 0 | I56: =G56*5 -> 0 | J56: =I56*E56 -> 0 | K56: =I56/2 -> 0 | L56: =K56*E56 -> 0
A57: 2 | G57: =F57*5 -> 0 | H57: =G57*E57 -> 0 | I57: =G57*5 -> 0 | J57: =I57*E57 -> 0 | K57: =I57/2 -> 0 | L57: =K57*E57 -> 0
A58: 3 | G58: =F58*5 -> 0 | H58: =G58*E58 -> 0 | I58: =G58*5 -> 0 | J58: =I58*E58 -> 0 | K58: =I58/2 -> 0 | L58: =K58*E58 -> 0
A59: 4 | G59: =F59*5 -> 0 | H59: =G59*E59 -> 0 | I59: =G59*5 -> 0 | J59: =I59*E59 -> 0 | K59: =I59/2 -> 0 | L59: =K59*E59 -> 0
A60: 5 | G60: =F60*5 -> 0 | H60: =G60*E60 -> 0 | I60: =G60*5 -> 0 | J60: =I60*E60 -> 0 | K60: =I60/2 -> 0 | L60: =K60*E60 -> 0
A61: TOTAL COST | C61: {=COUNTA(C56:INDEX(C:C,ROW()-1))} -> 0 | E61: =SUM(E55:E60) -> 0 | G61: =SUBTOTAL(9,H56:H60) -> 0

Sheet LACE - SOLD
A1: UPDATED ON | F1: UPDATED BY IBRAHIM
A2: DESCRIPTION 31 OCT 2024 | D2: PIECES | F2: VIP-M | I2: NOTED: SOME LINEATRE (LINEA) NOT LISTED .COZ OF SHORT PIECES
A3: TOTAL | D3: 1058 | F3: Sherry - S | H3: PENDING-P
A4: RESERVED (M-30+30+20) | F4: Angie - A
A5: PENDING OUT OFFICE( C-30,K-4,FK-43) | F5: Fong king - FK | I5: Total Cost | K5: =J32+J56+J91+J100+J109 -> 50125.59
A6: SOLD | D6: =#REF!+#REF!+#REF!+#REF!+#REF!+#REF!+#REF!+#REF!+#REF!+#REF!+#REF!+#REF!+#REF!+#REF!+#REF!+#REF!+#REF! -> #REF! | F6: Bani -B
A7: AVAILABLE | D7: =D3-(D4+D5+D6) -> #REF! | E7: =COUNTIF('SILK - PENDING'!D14:D17,"*cdc*") -> 2 | F7: MR. Cetin- C | I7: NET PROFIT | K7: =L32+L56+L91+L100+L109 -> 71813.798
F8: MS. KLARA-K
A13: SOLD PLAN LACE (PL)
A15: NO | B15: DESIGN | C15: ARTICLE | D15: QUALITY | E15: QTY | F15: PRICE PER MT | G15: PRICE PER PIECE | H15: NET PRICE AFTER DISCOUNT | I15: COMMI % | J15: LESS COMMISSION PER PC | K15: COST PER PC | L15: NET PROFIT PER PC | M15: SOLD TO
A16: 1 | B16: DSSS-1 | C16: ML 007314-090.0 | D16: BLUE | E16: 5.2 | F16: 918 | G16: 4773.6 | H16: 2386.8 | I16: 0.2 | J16: 1670.76 | K16: 795.6 | L16: 875.16 | M16: M
A17: 2 | B17: ESS-3 | C17: ML 007314-090.0 | D17: GREEN | E17: 5 | F17: 918 | G17: 4590 | H17: 2295 | I17: 0.2 | J17: 1606.5 | K17: 765 | L17: 841.5 | M17: M
A18: 3 | B18: DSSS-12 | C18: ML 007314-090.0 | D18: ORANGE | E18: 5.5 | F18: 918 | G18: 5049 | H18: 2524.5 | I18: 0.2 | J18: 1767.15 | K18: 841.5 | L18: 925.65 | M18: M
A19: 4 | B19: ESS-16 | C19: ML 7314.090.0 | D19: BRONZE | E19: 4.7 | F19: 918 | G19: 4314.6 | H19: 2157.3 | I19: 0.2 | J19: 1510.11 | K19: 719.1 | L19: 791.01 | M19: M
A20: 5 | B20: ESS-20 | C20: ML 7314.090.0 | D20: ROYAL BLUE | E20: 4.8 | F20: 918 | G20: 4406.4 | H20: 2203.2 | I20: 0.2 | J20: 1542.24 | K20: 734.4 | L20: 807.84 | M20: M
A21: 6 | B21: ESS-162 | C21: 43-007314-090.0 | D21: FUXIA | E21: 4.7 | F21: GIFT | J21: 0 | K21: 705 | L21: =J21-K21 -> -705 | M21: M
A22: 7 | B22: PL | C22: 43-007314-090.1 | D22: 763 | E22: 5.2 | F22: 231 | G22: =F22*E22 -> 1201.2 | H22: 1200 | I22: 0.2 | J22: 960 | K22: =150*E22 -> 780 | L22: =J22-K22 -> 180 | M22: A
A23: 8 | B23: ESS-28 | C23: ML 007314-090-0 | D23: LACE | E23: 5 | F23: 420 | G23: =F23*E23 -> 2100 | H23: 2100 | I23: 0.2 | J23: 1680 | K23: 750 | L23: 1350 | M23: B
A24: 9 | B24: ESS-26 | C24: ML 007314-090-0 | D24: LACE | E24: 4.6 | F24: 420 | G24: 1932 | H24: 1932 | I24: 0.2 | J24: 1545.6 | K24: 690 | L24: 1242 | M24: B
A25: 10 | B25: EAS-30 | C25: ML 007314-090-0 | D25: LACE | E25: 5.2 | F25: 420 | G25: 2184 | H25: 2184 | I25: 0.2 | J25: 1747.2 | K25: 780 | L25: 1404 | M25: B
A26: 11 | B26: ESS-112 | C26: 43 007245 85 90 | D26: LACE | E26: 5 | F26: 420 | G26: 2100 | H26: 2100 | I26: 0.2 | J26: 1680 | K26: 750 | L26: 1350 | M26: B
A27: 12 | B27: SOL-VAS-17 | C27: ML 007314-090-0 | D27: LACE | E27: 4.6 | F27: 563 | G27: 2589.8 | H27: 2500 | I27: 0.2 | J27: 2000 | K27: 690 | L27: 1310 | M27: B
A28: 13 | B28: SOL-ESS-22 | C28: ML 007314-090-0 | D28: LACE | E28: 4.7 | F28: 563 | G28: 2646.1 | H28: 2646.1 | I28: 0.2 | J28: 2116.88 | K28: 705 | L28: 1411.88 | M28: B
A29: 14 | B29: SOL-DSSS-33 | C29: 7245.090.1 | D29: LACE | E29: 4.8 | F29: 563 | G29: 2702.4 | H29: 2702.4 | I29: 0.2 | J29: 2161.92 | K29: 888 | L29: 1273.92 | M29: B
A30: 15 | B30: SOL-VSS-166 | C30: 43 007245 85 90 | D30: LACE | E30: 4.3 | F30: 563 | G30: 2420.9 | H30: 2420.9 | I30: 0.2 | J30: 1936.72 | K30: 645 | L30: 1291.72 | M30: B
A31: 16 | B31: SOL-PL-ESS-118 | C31: 43 007245 85 90 | D31: PLENO | E31: 5 | F31: 918 | G31: 4590 | H31: 2295 | I31: 0.2 | J31: 1836 | K31: 750 | L31: 1086 | M31: S
B32: TOTAL | C32: {=COUNTA(C16:INDEX(C:C,ROW()-1))} -> 16 | E32: =SUM(E16:E31) -> 78.3 | J32: =SUM(K16:K30) -> 11238.6 | L32: =SUM(L16:L30) -> 14349.68
A36: SOLDLUREXLACE (L.L)
A38: NO | B38: DESIGN | C38: ARTICLE | D38: QUALITY | E38: QTY | F38: PRICE PER MT | G38: PRICE PER PIECE | H38: NET PRICE AFTER DISCOUNT | I38: COMMI % | J38: LESS COMMISSION PER PC | K38: COST PER PC | L38: NET PROFIT PER PC | M38: SOLD TO
A39: 17 | B39: DGGS-49 | C39: 7316-140.0 | D39: GOLD / BALCK | E39: 4.8 | F39: 1621.8 | G39: 7784.64 | H39: =G39/2 -> 3892.32 | I39: 0.2 | J39: 2724.624 | K39: 1297.44 | L39: 1427.184 | M39: M
A40: 18 | B40: DASS-56 | C40: 7315-140.0 | D40: FUXIA / PINK | E40: 5 | F40: 1621.8 | G40: 8109 | H40: =G40/2 -> 4054.5 | I40: 0.2 | J40: 2838.15 | K40: 1351.5 | L40: 1486.65 | M40: M (256)
A41: 19 | B41: DASS-59 | C41: 7315-140.0 | D41: RED / GREY | E41: 4.9 | F41: 1621.8 | G41: 7946.82 | H41: =G41/2 -> 3973.41 | I41: 0.2 | J41: 2781.387 | K41: 1324.47 | L41: 1456.917 | M41: M
A42: 20 | B42: DDSS-61 | C42: 7246-140.0 | D42: GREEN | E42: 5 | F42: 1621.8 | G42: 8109 | H42: =G42/2 -> 4054.5 | I42: 0.2 | J42: 2838.15 | K42: 1351.5 | L42: 1486.65 | M42: M
A43: 21 | B43: DSSS-7 | C43: 207-LL | D43: LACE | E43: 5.2 | F43: 1621.8 | G43: =F43*E43 -> 8433.36 | H43: 4216.68 | I43: 0.2 | J43: 2951.676 | K43: 1378 | L43: 1573.676 | M43: M
A44: 22 | B44: ESSS-11 | C44: 211-LL | D44: LACE | E44: 5 | F44: 1621.8 | G44: =F44*E44 -> 8109 | H44: 4054.5 | I44: 0.2 | J44: 2838.15 | K44: 1325 | L44: 1513.15 | M44: M
A45: 23 | B45: DSSS-115 | C45: 215-LL | D45: LACE | E45: 4.7 | F45: 1621.8 | G45: =F45*E45 -> 7622.46 | H45: 3811.23 | I45: 0.2 | J45: 2667.861 | K45: 1219 | L45: 1448.861 | M45: M
A46: 24 | B46: DRSS-54 | C46: 254-LL | D46: LACE | E46: 4.3 | F46: 1621.8 | G46: =F46*E46 -> 6973.74 | H46: 3486.87 | I46: 0.2 | J46: 2440.809 | K46: 1139.5 | L46: 1301.309 | M46: M
A47: 25 | B47: DSSS-131 | C47: LUREXLACE | D47: LUREXLACE | E47: 4.4 | F47: 1590 | G47: 6996 | H47: 3498 | I47: 0.2 | J47: 2448.6 | K47: 1166 | L47: 1282.6 | M47: M
A48: 26 | B48: DSSS-129 | C48: LUREXLACE | D48: LUREXLACE | E48: 4.5 | F48: 1590 | G48: 7155 | H48: 3577.5 | I48: 0.2 | J48: 2504.25 | K48: 1192.5 | L48: 1311.75 | M48: M
A49: 27 | B49: SOL-DGSS-291 | C49: 7331.140.0 | D49: LUREXLACE | E49: 4.6 | F49: 637 | G49: 2930.2 | H49: 2800 | I49: 0.2 | J49: 2240 | K49: 1219 | L49: 1021 | M49: B
A50: 28 | B50: SOL-DAAS-275 | C50: 7051.120.0 | D50: LUREXLACE | E50: 5.7 | F50: 1621.8 | G50: 9244.26 | H50: 4622.13 | I50: 0.2 | J50: 3697.704 | K50: 1510.5 | L50: 2187.204 | M50: M
A51: 29 | B51: SOL-LL-DGSS-252 | C51: 7316-140-0 | D51: BONIFICO SILVER | E51: 4.7 | F51: 1621 | G51: 7618.7 | H51: 3809.35 | I51: 0.2 | J51: 3047.48 | K51: 1245.5 | L51: 1801.98 | M51: S
A52: 30 | B52: SOL-LL-DGSS-253 | C52: 7316-140-0 | D52: SILVER | E52: 4.6 | F52: 1621 | G52: 7456.6 | H52: 3728.3 | I52: 0.2 | J52: 2982.64 | K52: 1219 | L52: 1763.64 | M52: S
A53: 31 | B53: SOL-LL-DNSS-263 | C53: 7246.140.0 | D53: PIZZO | E53: 5.2 | F53: 1621 | G53: 8429.2 | H53: 4214.6 | I53: 0.2 | J53: 3371.68 | K53: 1378 | L53: 1993.68 | M53: S
A54: 32 | B54: SOL-LL-DASS-289 | C54: 7331.140.0 | D54: BLACK / GOLD | E54: 4.8 | F54: 1621 | G54: 7780.8 | H54: 3890.4 | I54: 0.2 | J54: 3112.32 | K54: 1272 | L54: 1840.32 | M54: S
A55: 33 | B55: SOL-LL-DASS-292 | C55: 7331.140.0 | D55: SILVER | E55: 4.8 | F55: 1621 | G55: 7780.8 | H55: 3890.4 | I55: 0.2 | J55: 3112.32 | K55: 1272 | L55: 1840.32 | M55: S
B56: TOTAL | C56: {=COUNTA(C39:INDEX(C:C,ROW()-1))} -> 17 | E56: =SUM(E38:E55) -> 82.2 | J56: =SUM(K39:K55) -> 21860.91 | L56: =SUM(L39:L55) -> 26736.891
A70: SOLD CASA DELLO (CD)
A72: NO | B72: DESIGN | C72: ARTICLE | D72: QUALITY | E72: QTY | F72: PRICE PER MT | G72: PRICE PER PIECE | H72: NET PRICE AFTER DISCOUNT | I72: COMMI % | J72: LESS COMMISSION PER PC | K72: COST PER PC | L72: NET PROFIT PER PC | M72: SOLD TO
A73: 34 | B73: ESS-111 | C73: CASA -102 | D73: PINK / ORANGE | E73: 4.8 | F73: 918 | G73: 4406.4 | H73: 2203.2 | I73: 0.3 | J73: 1542.24 | K73: 660.96 | L73: 881.28 | M73: M
A74: 35 | B74: DSSS-116 | C74: CASA- 30.B39617 | D74: DEEP RED | E74: 5.6 | F74: 918 | G74: 5140.8 | H74: 2570.4 | I74: 0.3 | J74: 1799.28 | K74: 771.12 | L74: 1028.16 | M74: M
A75: 36 | B75: DUAS-120 | C75: 50810369 | D75: PINK / BROWN | E75: 5.6 | F75: 1621.8 | G75: 9082.08 | H75: =G75/2 -> 4541.04 | I75: 0.3 | J75: 3178.728 | K75: 999.6 | L75: 2179.128 | M75: M
A76: 37 | B76: DRSS-122 | C76: 52410090 | D76: BLACK | E76: 5.7 | F76: 1621.8 | G76: 9244.26 | H76: =G76/2 -> 4622.13 | I76: 0.3 | J76: 3235.491 | K76: 1017.45 | L76: 2218.041 | M76: M
A77: 38 | B77: DDSS-125 | C77: CASA-102 | D77: BROWN | E77: 5 | F77: 1621.8 | G77: 8109 | H77: =G77/2 -> 4054.5 | I77: 0.3 | J77: 2838.15 | K77: 892.5 | L77: 1945.65 | M77: M
A78: 39 | B78: EAS-137 | C78: CASA-102 | D78: BLACK / GOLD | E78: 4.3 | F78: 1621.8 | G78: 6973.74 | H78: =G78/2 -> 3486.87 | I78: 0.3 | J78: 2440.809 | K78: 767.55 | L78: 1673.259 | M78: M
A79: 40 | B79: DUSS-132 | C79: CASA-102 | D79: GOLD / LT BROWN | E79: 5.4 | F79: 1621.8 | G79: 8757.72 | H79: =G79/2 -> 4378.86 | I79: 0.3 | J79: 3065.202 | K79: 963.9 | L79: 2101.302 | M79: M
A80: 41 | B80: VSS-123 | C80: DDSS-123 | D80: LUREXLACE | E80: 4.9 | F80: 1621.8 | G80: =F80*E80 -> 7946.82 | H80: 3973.41 | I80: 0.3 | J80: 2781.387 | K80: 857.5 | L80: 1923.887 | M80: M
A81: 42 | B81: DUSS-146 | C81: LUREXLACE | D81: MEROON/GOLD | E81: 5.5 | F81: 1621 | G81: 8915.5 | H81: 4457.75 | I81: 0.2 | J81: 3566.2 | K81: 962.5 | L81: 2603.7 | M81: M
A82: 43 | B82: ESS-143 | C82: LUREXLACE | D82: MEROON/GOLD | E82: 4.3 | F82: 1621 | G82: 6970.3 | H82: 3485.15 | I82: 0.2 | J82: 2788.12 | K82: 752.5 | L82: 2035.62 | M82: M
A83: 44 | B83: DUSS-127 | C83: LUREXLACE | D83: ROSE/GOLD | E83: 5.5 | F83: 1621 | G83: 8915.5 | H83: 4457.75 | I83: 0.2 | J83: 3566.2 | K83: 962.5 | L83: 2603.7 | M83: M
A84: 45 | B84: DDAS-165 | C84: 102 | D84: LACE | E84: 5.7 | F84: 480 | G84: 2736 | H84: 2736 | I84: 0.2 | J84: 2188.8 | K84: 997.5 | L84: 1738.5 | M84: B
A85: 46 | B85: ESS-173 | C85: ESS-112 | D85: LACE | E85: 4.8 | F85: 375 | G85: 1800 | H85: 1800 | I85: 0.2 | J85: 1440 | K85: 648 | L85: 1152 | M85: B
A86: 47 | B86: DSSS-130 | C86: 102 | D86: LACE | E86: 4.5 | F86: 480 | G86: 2160 | H86: 2160 | I86: 0.2 | J86: 1728 | K86: 787.5 | L86: 1372.5 | M86: B
A87: 48 | B87: DSSS-170 | C87: 35-B33043 | D87: LACE | E87: 5.5 | F87: 375 | G87: 2062.5 | H87: 2062.5 | I87: 0.2 | J87: 1650 | K87: 742.5 | L87: 1320 | M87: B
A88: 49 | B88: SOL-DSSS-109 | C88: 23.B39618 | D88: LACE | E88: 5.6 | F88: 563 | G88: 3152.8 | H88: 3000 | I88: 0.2 | J88: 2400 | K88: 756 | L88: 1644 | M88: B
A89: 50 | B89: SOL-DSSS-153 | C89: SARCELLE | D89: LUREXLACE | E89: 4.4 | F89: 637 | G89: 2802.8 | H89: 2700 | I89: 0.2 | J89: 2160 | K89: 770 | L89: 1390 | M89: B
A90: 51 | B90: DDSS-117 | C90: DDSS-117 | D90: PLAIN LACE | E90: 5.9 | F90: 270 | G90: =E90*F90 -> 1593 | H90: 1593 | I90: 0 | J90: 1593 | K90: 796.5 | L90: =J90-K90 -> 796.5 | M90: F
B91: TOTAL | C91: {=COUNTA(C73:INDEX(C:C,ROW()-1))} -> 18 | E91: =SUM(E71:E90) -> 93 | J91: =SUM(K73:K90) -> 15106.08 | L91: =SUM(L73:L90) -> 30607.227
A94: SOLD BEIRUT LACE (BEI)
A95: NO | B95: DESIGN | C95: ARTICLE | D95: QUALITY | E95: QTY | F95: PRICE PER MT | G95: PRICE PER PIECE | H95: NET PRICE AFTER DISCOUNT | I95: COMMISSION PERCENTAGE | J95: LESS COMMISSION PER PC | K95: COST PER PC | L95: NET PROFIT PER PC | M95: SOLD TO
A96: 1 | B96: DRSS 17 | C96: FSH 509 | D96: BLACK | E96: 6.4 | F96: GIFT to Mr Warren | J96: 0 | K96: 960 | L96: =J96-K96 -> -960 | M96: W
A97: 2 | B97: DRSS 7 | C97: AN35370 | D97: PURPLE | E97: 6.4 | F97: 375 | G97: 2400 | H97: 2040 | I97: 0 | J97: 2040 | K97: 960 | L97: 1080 | M97: S
B100: TOTAL | C100: =COUNTA(C96:C99) -> 2 | E100: =SUM(E96:E99) -> 12.8 | J100: =SUM(K96:K99) -> 1920 | L100: =SUM(L96:L99) -> 120
A103: SOLD RICCIARINI CORD LACE(PL-R)
A104: NO | B104: DESIGN | C104: ARTICLE | D104: QUALITY | E104: QTY | F104: PRICE PER MT | G104: PRICE PER PIECE | H104: NET PRICE AFTER DISCOUNT | I104: COMMISSION PERCENTAGE | J104: LESS COMMISSION PER PC | K104: COST PER PC | L104: NET PROFIT PER PC | M104: SOLD TO
A105: 1
A106: 2
B109: TOTAL | C109: =COUNTA(C105:C108) -> 0 | E109: =SUM(E105:E108) -> 0 | J109: =SUM(K105:K108) -> 0 | L109: =SUM(L105:L108) -> 0

Sheet CEMB - STOCK OVERVIEW
A1: ITEM | B1: TOTAL BOXES | C1: BOXES AVAILABLE | D1: BOXES SOLD | E1: BOXES PENDING | F1: TOTAL BOXES IN OFFICE | G1: TOTAL METERS IN OFFICE | H1: TOTAL VALUE IN OFFICE MYR | I1: TOTAL METERS IN SOLD | J1: TOTAL VALUE OF SOLD | K1: TOTAL METERS PENDING | L1: TOTAL VALUE OF PENDING | M1: TOTAL METERS | N1: TOTAL VALUE MYR
A2: LACE
A3: CEMB 40 | B3: =D3+E3+C3 -> 207 | C3: ='CEMB - ALL'!D214 -> 201 | D3: ='CEMB - SOLD'!C22 -> 6 | E3: ='CEMB - PENDING'!C18 -> 0 | F3: =C3+E3 -> 201 | G3: ='CEMB - ALL'!E214 -> 862.3 | H3: ='CEMB - ALL'!I214 -> 30233 | I3: ='CEMB - SOLD'!E22 -> 23.45 | J3: ='CEMB - SOLD'!K22 -> 301 | K3: ='CEMB - PENDING'!E18 -> 0 | L3: ='CEMB - PENDING'!H18 -> 0 | M3: =G3+I3+K3 -> 885.75 | N3: =J3+L3+H3 -> 30534
A4: CEMB 60 | B4: =D4+E4+C4 -> 81 | C4: ='CEMB - ALL'!D286 -> 67 | D4: ='CEMB - SOLD'!C43 -> 14 | E4: ='CEMB - PENDING'!C31 -> 0 | F4: =C4+E4 -> 67 | G4: ='CEMB - ALL'!E397 -> 244.6 | H4: ='CEMB - ALL'!I286 -> 20460 | I4: =Table123[[#Totals],[QTY]] -> 73.5 | J4: =Table126[[#Totals],[COST PER PC]] -> 4440 | K4: ='CEMB - PENDING'!E31 -> 0 | L4: ='CEMB - PENDING'!H31 -> 0 | M4: =G4+I4+K4 -> 318.1 | N4: =J4+L4+H4 -> 24900
A5: CEMB 120 | B5: =D5+E5+C5 -> 62 | C5: ='CEMB - ALL'!D346 -> 55 | D5: ='CEMB - SOLD'!C56 -> 7 | E5: ='CEMB - PENDING'!C43 -> 0 | F5: =C5+E5 -> 55 | G5: ='CEMB - ALL'!E346 -> 268.3 | H5: ='CEMB - ALL'!I346 -> 28296 | I5: =Table124[[#Totals],[QTY]] -> 41 | J5: ='CEMB - SOLD'!H56 -> 2512 | K5: =Table133[[#Totals],[QTY]] -> 0 | L5: =Table137[[#Totals],[COST PIECE RM]] -> 0 | M5: =G5+I5+K5 -> 309.3 | N5: =J5+L5+H5 -> 30808
A6: CEMB 180 | B6: =D6+E6+C6 -> 51 | C6: ='CEMB - ALL'!D397 -> 46 | D6: ='CEMB - SOLD'!C68 -> 5 | E6: ='CEMB - PENDING'!C55 -> 0 | F6: =C6+E6 -> 46 | G6: ='CEMB - ALL'!E397 -> 244.6 | H6: ='CEMB - ALL'!I397 -> 44028 | I6: =Table140[[#Totals],[QTY]] -> 23.9 | J6: =Table141[[#Totals],[COST PER PC]] -> 4302 | K6: =Table135[[#Totals],[QTY]] -> 0 | L6: =Table138[[#Totals],[COST PIECE RM]] -> 0 | M6: =G6+I6+K6 -> 268.5 | N6: =J6+L6+H6 -> 48330
A9: LACE TOTAL | B9: =SUM(B3:B6) -> 401 | C9: =SUM(C3:C6) -> 369 | D9: =SUM(D3:D6) -> 32 | E9: =SUM(E3:E6) -> 0 | F9: =SUM(F3:F6) -> 369 | G9: =SUM(G3:G6) -> 1619.8 | H9: =SUM(H3:H6) -> 123017 | I9: =SUM(I3:I6) -> 161.85 | ... N9: =SUM(N3:N6) -> 134572

Sheet CEMB - ALL
A1: UPDATED ON | F1: UPDATED BY IBRAHIM
A2: DESCRIPTION 31 OCT 2024 | D2: PIECES | F2: VIP-M | I2: NOTED: SOME LINEATRE (LINEA) NOT LISTED .COZ OF SHORT PIECES
A3: TOTAL | D3: 1058 | F3: Sherry - S | H3: PENDING-P
F4: Angie - A
F5: Fong king - FK
A6: SOLD | D6: =COUNTA('SILK - SOLD'!A14:A76,'SILK - SOLD'!A86:A106,'SILK - SOLD'!A112:A170,'SILK - SOLD'!A177:A262) -> 229 | F6: Bani -B
A7: AVAILABLE | D7: =D3-(D4+D5+D6) -> 829 | F7: MR. Cetin- C | I7: Total Cost | K7: =I214+I286+I346+I397 -> 123017
F8: MS. KLARA-K
A11: CEMB 40
A12: NO | B12: DESIGN | C12: ARTICLE | D12: QUALITY | E12: QTY | F12: COST PER MT EURO | G12: COST PIECE EURO | H12: COST PER MT RM | I12: COST PIECE RM | J12: V.I.P PER MT RM | K12: V.I.P PIECE RM | L12: SELLING PER MT RM LESS 50% | M12: SELLING PIECE RM | N12: SUPPLIER
A13: 1 | B13: 40 - SE | C13: CEMB - 300 | D13: YELLOW | E13: 5 | F13: 7 | G13: =F13*E13 -> 35 | H13: =F13*5 -> 35 | I13: =G13*5 -> 175 | J13: =H13*5 -> 175 | K13: =J13*E13 -> 875 | L13: =H13+20 -> 55 | M13: =L13*E13 -> 275 | N13: GD - 7157
A14: 2 | B14: 40 - SE | C14: CEMB - 301 | D14: YELLOW | E14: 5 | F14: 7 | G14: =F14*E14 -> 35 | H14: =F14*5 -> 35 | I14: =G14*5 -> 175 | J14: =H14*5 -> 175 | K14: =J14*E14 -> 875 | L14: =H14+20 -> 55 | M14: =L14*E14 -> 275 | N14: GD - 7157
A15: 3 | B15: 40 - SE | C15: CEMB - 302 | D15: PURPLE | E15: 5 | F15: 7 | G15: =F15*E15 -> 35 | H15: =F15*5 -> 35 | I15: =G15*5 -> 175 | J15: =H15*5 -> 175 | K15: =J15*E15 -> 875 | L15: =H15+20 -> 55 | M15: =L15*E15 -> 275 | N15: GD - 7157
A16: 4 | B16: 40 - SE | C16: CEMB - 303 | D16: PURPLE | E16: 5 | F16: 7 | G16: =F16*E16 -> 35 | H16: =F16*5 -> 35 | I16: =G16*5 -> 175 | J16: =H16*5 -> 175 | K16: =J16*E16 -> 875 | L16: =H16+20 -> 55 | M16: =L16*E16 -> 275 | N16: GD - 7157
A17: 5 | B17: 40 - SE | C17: CEMB - 304 | D17: PURPLE | E17: 5 | F17: 7 | G17: =F17*E17 -> 35 | H17: =F17*5 -> 35 | I17: =G17*5 -> 175 | J17: =H17*5 -> 175 | K17: =J17*E17 -> 875 | L17: =H17+20 -> 55 | M17: =L17*E17 -> 275 | N17: GD - 7157
A18: 6 | B18: 40 - SE | C18: CEMB - 305 | D18: PURPLE | E18: 5 | F18: 7 | G18: =F18*E18 -> 35 | H18: =F18*5 -> 35 | I18: =G18*5 -> 175 | J18: =H18*5 -> 175 | K18: =J18*E18 -> 875 | L18: =H18+20 -> 55 | M18: =L18*E18 -> 275 | N18: GD - 7157
A19: 7 | B19: 40 - SE | C19: CEMB - 306 | D19: ROYAL BLUE | E19: 5 | F19: 7 | G19: =F19*E19 -> 35 | H19: =F19*5 -> 35 | I19: =G19*5 -> 175 | J19: =H19*5 -> 175 | K19: =J19*E19 -> 875 | L19: =H19+20 -> 55 | M19: =L19*E19 -> 275 | N19: GD - 7393
A20: 8 | B20: 40 - SE | C20: CEMB - 307 | D20: ROYAL BLUE | E20: 5 | F20: 7 | G20: =F20*E20 -> 35 | H20: =F20*5 -> 35 | I20: =G20*5 -> 175 | J20: =H20*5 -> 175 | K20: =J20*E20 -> 875 | L20: =H20+20 -> 55 | M20: =L20*E20 -> 275 | N20: GD - 7393
A21: 9 | B21: 40 - SE | C21: CEMB - 308 | D21: DARK RED | E21: 5 | F21: 7 | G21: =F21*E21 -> 35 | H21: =F21*5 -> 35 | I21: =G21*5 -> 175 | J21: =H21*5 -> 175 | K21: =J21*E21 -> 875 | L21: =H21+20 -> 55 | M21: =L21*E21 -> 275 | N21: GD - 7157
A22: 10 | B22: 40 - SE | C22: CEMB - 309 | D22: DARK RED | E22: 5 | F22: 7 | G22: =F22*E22 -> 35 | H22: =F22*5 -> 35 | I22: =G22*5 -> 175 | J22: =H22*5 -> 175 | K22: =J22*E22 -> 875 | L22: =H22+20 -> 55 | M22: =L22*E22 -> 275 | N22: GD - 7157
A23: 11 | B23: 40 - SE | C23: CEMB - 310 | D23: GREEN | E23: 5 | F23: 7 | G23: =F23*E23 -> 35 | H23: =F23*5 -> 35 | I23: =G23*5 -> 175 | J23: =H23*5 -> 175 | K23: =J23*E23 -> 875 | L23: =H23+20 -> 55 | M23: =L23*E23 -> 275 | N23: GD - 7157
A24: 12 | B24: 40 - SE | C24: CEMB - 311 | D24: SILVER BLUE | E24: 5 | F24: 7 | G24: =F24*E24 -> 35 | H24: =F24*5 -> 35 | I24: =G24*5 -> 175 | J24: =H24*5 -> 175 | K24: =J24*E24 -> 875 | L24: =H24+20 -> 55 | M24: =L24*E24 -> 275 | N24: GD - 7157
... A208: 196 | B208: 40 - SE | C208: CEMB - 500 | D208: GREEN | E208: 3.2 | F208: 7 | G208: =F208*E208 -> 22.4 | H208: =F208*5 -> 35 | I208: =G208*5 -> 112 | J208: =H208*5 -> 175 | K208: =J208*E208 -> 560 | L208: =H208+20 -> 55 | M208: =L208*E208 -> 176 | N208: DESIGN 4
A209: 197 | B209: 40 - SE | C209: CEMB - 501 | D209: LILAC | E209: 5 | F209: 7 | G209: =F209*E209 -> 35 | H209: =F209*5 -> 35 | I209: =G209*5 -> 175 | J209: =H209*5 -> 175 | K209: =J209*E209 -> 875 | L209: =H209+20 -> 55 | M209: =L209*E209 -> 275 | N209: 7393
A210: 198 | B210: 40 - SE | C210: CEMB - 502 | D210: GREEN | E210: 5 | F210: 7 | G210: =F210*E210 -> 35 | H210: =F210*5 -> 35 | I210: =G210*5 -> 175 | J210: =H210*5 -> 175 | K210: =J210*E210 -> 875 | L210: =H210+20 -> 55 | M210: =L210*E210 -> 275 | N210: 7393
A211: 199 | B211: 40 - SE | C211: CEMB - 503 | D211: YELLOW | E211: 5 | F211: 7 | G211: =F211*E211 -> 35 | H211: =F211*5 -> 35 | I211: =G211*5 -> 175 | J211: =H211*5 -> 175 | K211: =J211*E211 -> 875 | L211: =H211+20 -> 55 | M211: =L211*E211 -> 275 | N211: 7393
A212: 200 | B212: 40 - SE | C212: CEMB - 504 | D212: ORANGE | E212: 5 | F212: 7 | G212: =F212*E212 -> 35 | H212: =F212*5 -> 35 | I212: =G212*5 -> 175 | J212: =H212*5 -> 175 | K212: =J212*E212 -> 875 | L212: =H212+20 -> 55 | M212: =L212*E212 -> 275 | N212: 7393
A213: 201 | B213: 40 - SE | C213: CEMB - 505 | D213: SOFT COFFEE | E213: 3.5 | F213: 7 | G213: 35 | H213: =F213*5 -> 35 | I213: =G213*5 -> 175 | J213: =H213*5 -> 175 | K213: =J213*E213 -> 612.5 | L213: =H213+20 -> 55 | M213: =L213*E213 -> 192.5 | N213: 7393
B214: TOTAL COST | D214: =COUNTA(D13:D213) -> 201 | E214: =SUM(E12:E213) -> 862.3 | G214: =SUM(G12:G213) -> 6046.6 | I214: =SUM(I12:I213) -> 30233
A217: CEMB 60
A218: NO | B218: DESIGN | C218: ARTICLE | D218: QUALITY | E218: QTY | F218: COST PER MT EURO | G218: COST PIECE EURO | H218: COST PER MT RM | I218: COST PIECE RM | J218: V.I.P PER MT RM | K218: V.I.P PIECE RM | L218: SELLING PER MT RM LESS 50% | M218: SELLING PIECE RM | N218: SUPPLIER
A219: 202 | B219: 60-SC | C219: CEMB 1 | D219: 3D-EMBROIDERY | E219: 7 | F219: 12 | G219: =F219*E219 -> 84 | H219: =F219*5 -> 60 | I219: =G219*5 -> 420 | J219: =H219*5 -> 300 | K219: =J219*E219 -> 2100 | L219: =H219*1.5 -> 90 | M219: =L219*E219 -> 630
A220: 203 | B220: 60-SC | C220: CEMB 2 | D220: 3D-EMBROIDERY | E220: 5 | F220: 12 | G220: =F220*E220 -> 60 | H220: =F220*5 -> 60 | I220: =G220*5 -> 300 | J220: =H220*5 -> 300 | K220: =J220*E220 -> 1500 | L220: =H220*1.5 -> 90 | M220: =L220*E220 -> 450
A221: 204 | B221: 60-SC | C221: CEMB 3 | D221: 3D-EMBROIDERY | E221: 7 | F221: 12 | G221: =F221*E221 -> 84 | H221: =F221*5 -> 60 | I221: =G221*5 -> 420 | J221: =H221*5 -> 300 | K221: =J221*E221 -> 2100 | L221: =H221*1.5 -> 90 | M221: =L221*E221 -> 630
A222: 205 | B222: 60-SC | C222: CEMB 4 | D222: 3D-EMBROIDERY | E222: 7 | F222: 12 | G222: =F222*E222 -> 84 | H222: =F222*5 -> 60 | I222: =G222*5 -> 420 | J222: =H222*5 -> 300 | K222: =J222*E222 -> 2100 | L222: =H222*1.5 -> 90 | M222: =L222*E222 -> 630
A223: 206 | B223: 60-SC | C223: CEMB 5 | D223: 3D-EMBROIDERY | E223: 7 | F223: 12 | G223: =F223*E223 -> 84 | H223: =F223*5 -> 60 | I223: =G223*5 -> 420 | J223: =H223*5 -> 300 | K223: =J223*E223 -> 2100 | L223: =H223*1.5 -> 90 | M223: =L223*E223 -> 630
A224: 207 | B224: 60-SC | C224: CEMB 8 | D224: 3D-EMBROIDERY | E224: 7 | F224: 12 | G224: =F224*E224 -> 84 | H224: =F224*5 -> 60 | I224: =G224*5 -> 420 | J224: =H224*5 -> 300 | K224: =J224*E224 -> 2100 | L224: =H224*1.5 -> 90 | M224: =L224*E224 -> 630
A225: 208 | B225: 60-SC | C225: CEMB 9 | D225: 3D-EMBROIDERY | E225: 4.5 | F225: 12 | G225: =F225*E225 -> 54 | H225: =F225*5 -> 60 | I225: =G225*5 -> 270 | J225: =H225*5 -> 300 | K225: =J225*E225 -> 1350 | L225: =H225*1.5 -> 90 | M225: =L225*E225 -> 405
A226: 209 | B226: 60-SC | C226: CEMB 10 | D226: 3D-EMBROIDERY | E226: 5 | F226: 12 | G226: =F226*E226 -> 60 | H226: =F226*5 -> 60 | I226: =G226*5 -> 300 | J226: =H226*5 -> 300 | K226: =J226*E226 -> 1500 | L226: =H226*1.5 -> 90 | M226: =L226*E226 -> 450
A227: 210 | B227: 60-SC | C227: CEMB 11 | D227: 3D-EMBROIDERY | E227: 5 | F227: 12 | G227: =F227*E227 -> 60 | H227: =F227*5 -> 60 | I227: =G227*5 -> 300 | J227: =H227*5 -> 300 | K227: =J227*E227 -> 1500 | L227: =H227*1.5 -> 90 | M227: =L227*E227 -> 450
A228: 211 | B228: 60-SC | C228: CEMB 12 | D228: 3D-EMBROIDERY | E228: 5 | F228: 12 | G228: =F228*E228 -> 60 | H228: =F228*5 -> 60 | I228: =G228*5 -> 300 | J228: =H228*5 -> 300 | K228: =J228*E228 -> 1500 | L228: =H228*1.5 -> 90 | M228: =L228*E228 -> 450
A229: 212 | B229: 60-SC | C229: CEMB 14 | D229: 3D-EMBROIDERY | E229: 5 | F229: 12 | G229: =F229*E229 -> 60 | H229: =F229*5 -> 60 | I229: =G229*5 -> 300 | J229: =H229*5 -> 300 | K229: =J229*E229 -> 1500 | L229: =H229*1.5 -> 90 | M229: =L229*E229 -> 450
A230: 213 | B230: 60-SC | C230: CEMB 17 | D230: 3D-EMBROIDERY | E230: 5 | F230: 12 | G230: =F230*E230 -> 60 | H230: =F230*5 -> 60 | I230: =G230*5 -> 300 | J230: =H230*5 -> 300 | K230: =J230*E230 -> 1500 | L230: =H230*1.5 -> 90 | M230: =L230*E230 -> 450
... A249: 232 | B249: 60-SC | C249: CEMB 39 | D249: 3D-EMBROIDERY | E249: 5 | F249: 12 | G249: =F249*E249 -> 60 | H249: =F249*5 -> 60 | I249: =G249*5 -> 300 | J249: =H249*5 -> 300 | K249: =J249*E249 -> 1500 | L249: =H249*1.5 -> 90 | M249: =L249*E249 -> 450
A250: 233 | B250: 60-SC | C250: CEMB 41 | D250: 3D-EMBROIDERY | E250: 5 | F250: 12 | G250: =F250*E250 -> 60 | H250: =F250*5 -> 60 | I250: =G250*5 -> 300 | J250: =H250*5 -> 300 | K250: =J250*E250 -> 1500 | L250: =H250*1.5 -> 90 | M250: =L250*E250 -> 450 | N250: SST
A251: 234 | B251: 60-SC | C251: CEMB 42 | D251: 3D-EMBROIDERY | E251: 5 | F251: 12 | G251: =F251*E251 -> 60 | H251: =F251*5 -> 60 | I251: =G251*5 -> 300 | J251: =H251*5 -> 300 | K251: =J251*E251 -> 1500 | L251: =H251*1.5 -> 90 | M251: =L251*E251 -> 450 | N251: SST
A252: 235 | B252: 60-SC | C252: CEMB 45 | D252: 3D-EMBROIDERY | E252: 5 | F252: 12 | G252: =F252*E252 -> 60 | H252: =F252*5 -> 60 | I252: =G252*5 -> 300 | J252: =H252*5 -> 300 | K252: =J252*E252 -> 1500 | L252: =H252*1.5 -> 90 | M252: =L252*E252 -> 450 | N252: ONK
A253: 236 | B253: 60-SC | C253: CEMB 46 | D253: 3D-EMBROIDERY | E253: 5 | F253: 12 | G253: =F253*E253 -> 60 | H253: =F253*5 -> 60 | I253: =G253*5 -> 300 | J253: =H253*5 -> 300 | K253: =J253*E253 -> 1500 | L253: =H253*1.5 -> 90 | M253: =L253*E253 -> 450 | N253: ONK
A254: 237 | B254: 60-SC | C254: CEMB 47 | D254: 3D-EMBROIDERY | E254: 5 | F254: 12 | G254: =F254*E254 -> 60 | H254: =F254*5 -> 60 | I254: =G254*5 -> 300 | J254: =H254*5 -> 300 | K254: =J254*E254 -> 1500 | L254: =H254*1.5 -> 90 | M254: =L254*E254 -> 450 | N254: ONK
A255: 238 | B255: 60-SC | C255: CEMB 48 | D255: 3D-EMBROIDERY | E255: 5 | F255: 12 | G255: =F255*E255 -> 60 | H255: =F255*5 -> 60 | I255: =G255*5 -> 300 | J255: =H255*5 -> 300 | K255: =J255*E255 -> 1500 | L255: =H255*1.5 -> 90 | M255: =L255*E255 -> 450 | N255: ONK
A256: 239 | B256: 60-SC | C256: CEMB 49 | D256: 3D-EMBROIDERY | E256: 5 | F256: 12 | G256: =F256*E256 -> 60 | H256: =F256*5 -> 60 | I256: =G256*5 -> 300 | J256: =H256*5 -> 300 | K256: =J256*E256 -> 1500 | L256: =H256*1.5 -> 90 | M256: =L256*E256 -> 450 | N256: S.BAOYUE-598
A257: 240 | B257: 60-SC | C257: CEMB 50 | D257: 3D-EMBROIDERY | E257: 5 | F257: 12 | G257: =F257*E257 -> 60 | H257: =F257*5 -> 60 | I257: =G257*5 -> 300 | J257: =H257*5 -> 300 | K257: =J257*E257 -> 1500 | L257: =H257*1.5 -> 90 | M257: =L257*E257 -> 450 | N257: S.BAOYUE-6
A258: 241 | B258: 60-SC | C258: CEMB 51 | D258: 3D-EMBROIDERY | E258: 5 | F258: 12 | G258: =F258*E258 -> 60 | H258: =F258*5 -> 60 | I258: =G258*5 -> 300 | J258: =H258*5 -> 300 | K258: =J258*E258 -> 1500 | L258: =H258*1.5 -> 90 | M258: =L258*E258 -> 450 | N258: SST-24A
A259: 242 | B259: 60-SC | C259: CEMB 52 | D259: 3D-EMBROIDERY | E259: 5 | F259: 12 | G259: =F259*E259 -> 60 | H259: =F259*5 -> 60 | I259: =G259*5 -> 300 | J259: =H259*5 -> 300 | K259: =J259*E259 -> 1500 | L259: =H259*1.5 -> 90 | M259: =L259*E259 -> 450 | N259: SST-3
A260: 243 | B260: 60-SC | C260: CEMB 53 | D260: 3D-EMBROIDERY | E260: 5 | F260: 12 | G260: =F260*E260 -> 60 | H260: =F260*5 -> 60 | I260: =G260*5 -> 300 | J260: =H260*5 -> 300 | K260: =J260*E260 -> 1500 | L260: =H260*1.5 -> 90 | M260: =L260*E260 -> 450 | N260: SST-20
A261: 244 | B261: 60-SC | C261: CEMB 54 | D261: 3D-EMBROIDERY | E261: 5 | F261: 12 | G261: =F261*E261 -> 60 | H261: =F261*5 -> 60 | I261: =G261*5 -> 300 | J261: =H261*5 -> 300 | K261: =J261*E261 -> 1500 | L261: =H261*1.5 -> 90 | M261: =L261*E261 -> 450 | N261: SST-9
... A267: 250 | B267: 60-SC | C267: CEMB 62 | D267: 3D-EMBROIDERY | E267: 5 | F267: 12 | G267: =F267*E267 -> 60 | H267: =F267*5 -> 60 | I267: =G267*5 -> 300 | J267: =H267*5 -> 300 | K267: =J267*E267 -> 1500 | L267: =H267*1.5 -> 90 | M267: =L267*E267 -> 450 | N267: S.BAOYUE-568
A268: 251 | B268: 60-SC | C268: CEMB 63 | D268: 3D-EMBROIDERY | E268: 3.5 | F268: 12 | G268: =F268*E268 -> 42 | H268: =F268*5 -> 60 | I268: =G268*5 -> 210 | J268: =H268*5 -> 300 | K268: =J268*E268 -> 1050 | L268: =H268*1.5 -> 90 | M268: =L268*E268 -> 315
A269: 252 | B269: 60-SC | C269: CEMB 64 | D269: 3D-EMBROIDERY | E269: 5 | F269: 12 | G269: =F269*E269 -> 60 | H269: =F269*5 -> 60 | I269: =G269*5 -> 300 | J269: =H269*5 -> 300 | K269: =J269*E269 -> 1500 | L269: =H269*1.5 -> 90 | M269: =L269*E269 -> 450 | N269: SST-18
A270: 253 | B270: 60-SC | C270: CEMB 65 | D270: 3D-EMBROIDERY | E270: 5 | F270: 12 | G270: =F270*E270 -> 60 | H270: =F270*5 -> 60 | I270: =G270*5 -> 300 | J270: =H270*5 -> 300 | K270: =J270*E270 -> 1500 | L270: =H270*1.5 -> 90 | M270: =L270*E270 -> 450 | N270: SBT-12
A271: 254 | B271: 60-SC | C271: CEMB 66 | D271: 3D-EMBROIDERY | E271: 5 | F271: 12 | G271: =F271*E271 -> 60 | H271: =F271*5 -> 60 | I271: =G271*5 -> 300 | J271: =H271*5 -> 300 | K271: =J271*E271 -> 1500 | L271: =H271*1.5 -> 90 | M271: =L271*E271 -> 450 | N271: SBT-10
A272: 255 | B272: 60-SC | C272: CEMB 67 | D272: 3D-EMBROIDERY | E272: 5 | F272: 12 | G272: =F272*E272 -> 60 | H272: =F272*5 -> 60 | I272: =G272*5 -> 300 | J272: =H272*5 -> 300 | K272: =J272*E272 -> 1500 | L272: =H272*1.5 -> 90 | M272: =L272*E272 -> 450 | N272: SST-7
A273: 256 | B273: 60-SC | C273: CEMB 68 | D273: 3D-EMBROIDERY | E273: 5 | F273: 12 | G273: =F273*E273 -> 60 | H273: =F273*5 -> 60 | I273: =G273*5 -> 300 | J273: =H273*5 -> 300 | K273: =J273*E273 -> 1500 | L273: =H273*1.5 -> 90 | M273: =L273*E273 -> 450 | N273: SBT-11
A274: 257 | B274: 60-SC | C274: CEMB 69 | D274: 3D-EMBROIDERY | E274: 5 | F274: 12 | G274: =F274*E274 -> 60 | H274: =F274*5 -> 60 | I274: =G274*5 -> 300 | J274: =H274*5 -> 300 | K274: =J274*E274 -> 1500 | L274: =H274*1.5 -> 90 | M274: =L274*E274 -> 450 | N274: CASA DELLO
A275: 258 | B275: 60-SC | C275: CEMB 70 | D275: 3D-EMBROIDERY | E275: 5 | F275: 12 | G275: =F275*E275 -> 60 | H275: =F275*5 -> 60 | I275: =G275*5 -> 300 | J275: =H275*5 -> 300 | K275: =J275*E275 -> 1500 | L275: =H275*1.5 -> 90 | M275: =L275*E275 -> 450 | N275: SBT-20
A276: 259 | B276: 60-SC | C276: CEMB 71 | D276: 3D-EMBROIDERY | E276: 5 | F276: 12 | G276: =F276*E276 -> 60 | H276: =F276*5 -> 60 | I276: =G276*5 -> 300 | J276: =H276*5 -> 300 | K276: =J276*E276 -> 1500 | L276: =H276*1.5 -> 90 | M276: =L276*E276 -> 450 | N276: SBT-4
A277: 260 | B277: 60-SC | C277: CEMB 72 | D277: 3D-EMBROIDERY | E277: 5 | F277: 12 | G277: =F277*E277 -> 60 | H277: =F277*5 -> 60 | I277: =G277*5 -> 300 | J277: =H277*5 -> 300 | K277: =J277*E277 -> 1500 | L277: =H277*1.5 -> 90 | M277: =L277*E277 -> 450 | N277: SBT-7
A278: 261 | B278: 60-SC | C278: CEMB 73 | D278: 3D-EMBROIDERY | E278: 5 | F278: 12 | G278: =F278*E278 -> 60 | H278: =F278*5 -> 60 | I278: =G278*5 -> 300 | J278: =H278*5 -> 300 | K278: =J278*E278 -> 1500 | L278: =H278*1.5 -> 90 | M278: =L278*E278 -> 450 | N278: SBT-3
A279: 262 | B279: 60-SC | C279: CEMB 74 | D279: 3D-EMBROIDERY | E279: 5 | F279: 12 | G279: =F279*E279 -> 60 | H279: =F279*5 -> 60 | I279: =G279*5 -> 300 | J279: =H279*5 -> 300 | K279: =J279*E279 -> 1500 | L279: =H279*1.5 -> 90 | M279: =L279*E279 -> 450 | N279: SBT-18
A280: 263 | B280: 60-SC | C280: CEMB 75 | D280: 3D-EMBROIDERY | E280: 5 | F280: 12 | G280: =F280*E280 -> 60 | H280: =F280*5 -> 60 | I280: =G280*5 -> 300 | J280: =H280*5 -> 300 | K280: =J280*E280 -> 1500 | L280: =H280*1.5 -> 90 | M280: =L280*E280 -> 450 | N280: SBT-19
... A285: 268 | B285: 60-SC | C285: CEMB 80 | D285: 3D-EMBROIDERY | E285: 5 | F285: 12 | G285: =F285*E285 -> 60 | H285: =F285*5 -> 60 | I285: =G285*5 -> 300 | J285: =H285*5 -> 300 | K285: =J285*E285 -> 1500 | L285: =H285*1.5 -> 90 | M285: =L285*E285 -> 450 | N285: T1-17-PX161242-A
A286: TOTAL COST | D286: =COUNTA(D219:D285) -> 67 | E286: =SUM(E219:E285) -> 341 | G286: =SUM(G219:G285) -> 4092 | I286: =SUM(I219:I285) -> 20460
A289: CEMB 120
A290: NO | B290: DESIGN | C290: ARTICLE | D290: QUALITY | E290: QTY | F290: COST PER MT EURO | G290: COST PIECE EURO | H290: COST PER MT RM | I290: COST PIECE RM | J290: V.I.P PER MT RM | K290: V.I.P PIECE RM | L290: SELLING PER MT RM LESS 50% | M290: SELLING PIECE RM | N290: SUPPLIER
A291: 269 | B291: 120-SE | C291: CEMB-100 | D291: EMBROIDERY LACE | E291: 7 | F291: 24 | G291: =F291*E291 -> 168 | H291: =F291*5 -> 120 | I291: =H291*E291 -> 840 | J291: =H291*5 -> 600 | K291: =J291*E291 -> 4200 | L291: =H291+20 -> 140 | M291: =L291*E291 -> 980 | N291: DESIGN CHILI-2
A292: 270 | B292: 120-SE | C292: CEMB-101 | D292: EMBROIDERY LACE | E292: 5 | F292: 24 | G292: =F292*E292 -> 120 | H292: =F292*5 -> 120 | I292: =H292*E292 -> 600 | J292: =H292*5 -> 600 | K292: =J292*E292 -> 3000 | L292: =H292+20 -> 140 | M292: =L292*E292 -> 700 | N292: SHAOXING RINGDA GD-7187
A293: 271 | B293: 120-SE | C293: CEMB-102 | D293: EMBROIDERY LACE | E293: 4.5 | F293: 24 | G293: =F293*E293 -> 108 | H293: =F293*5 -> 120 | I293: =H293*E293 -> 540 | J293: =H293*5 -> 600 | K293: =J293*E293 -> 2700 | L293: =H293+20 -> 140 | M293: =L293*E293 -> 630 | N293: RT-ACC 8551-AW
A294: 272 | B294: 120-SE | C294: CEMB-103 | D294: EMBROIDERY LACE | E294: 5 | F294: 24 | G294: =F294*E294 -> 120 | H294: =F294*5 -> 120 | I294: =H294*E294 -> 600 | J294: =H294*5 -> 600 | K294: =J294*E294 -> 3000 | L294: =H294+20 -> 140 | M294: =L294*E294 -> 700 | N294: ONK-9
A295: 273 | B295: 120-SE | C295: CEMB-104 | D295: EMBROIDERY LACE | E295: 5 | F295: 24 | G295: =F295*E295 -> 120 | H295: =F295*5 -> 120 | I295: =H295*E295 -> 600 | J295: =H295*5 -> 600 | K295: =J295*E295 -> 3000 | L295: =H295+20 -> 140 | M295: =L295*E295 -> 700 | N295: ONK-11
A296: 274 | B296: 120-SE | C296: CEMB-105 | D296: EMBROIDERY LACE | E296: 5 | F296: 24 | G296: =F296*E296 -> 120 | H296: =F296*5 -> 120 | I296: =H296*E296 -> 600 | J296: =H296*5 -> 600 | K296: =J296*E296 -> 3000 | L296: =H296+20 -> 140 | M296: =L296*E296 -> 700 | N296: ONK-10
A297: 275 | B297: 120-SE | C297: CEMB-107 | D297: EMBROIDERY LACE | E297: 3.8 | F297: 24 | G297: =F297*E297 -> 91.2 | H297: =F297*5 -> 120 | I297: =H297*E297 -> 456 | J297: =H297*5 -> 600 | K297: =J297*E297 -> 2280 | L297: =H297+20 -> 140 | M297: =L297*E297 -> 532 | N297: SKT-9
A298: 276 | B298: 120-SE | C298: CEMB-108 | D298: EMBROIDERY LACE | E298: 7.8 | F298: 24 | G298: =F298*E298 -> 187.2 | H298: =F298*5 -> 120 | I298: =H298*E298 -> 936 | J298: =H298*5 -> 600 | K298: =J298*E298 -> 4680 | L298: =H298+20 -> 140 | M298: =L298*E298 -> 1092 | N298: SKT-4
A299: 277 | B299: 120-SE | C299: CEMB-109 | D299: EMBROIDERY LACE | E299: 5.6 | F299: 24 | G299: =F299*E299 -> 134.4 | H299: =F299*5 -> 120 | I299: =H299*E299 -> 672 | J299: =H299*5 -> 600 | K299: =J299*E299 -> 3360 | L299: =H299+20 -> 140 | M299: =L299*E299 -> 784 | N299: SKT-13
A300: 278 | B300: 120-SE | C300: CEMB-111 | D300: EMBROIDERY LACE | E300: 8 | F300: 24 | G300: =F300*E300 -> 192 | H300: =F300*5 -> 120 | I300: =H300*E300 -> 960 | J300: =H300*5 -> 600 | K300: =J300*E300 -> 4800 | L300: =H300+20 -> 140 | M300: =L300*E300 -> 1120 | N300: SKT-7
A301: 279 | B301: 120-SE | C301: CEMB-113 | D301: EMBROIDERY LACE | E301: 5 | F301: 24 | G301: =F301*E301 -> 120 | H301: =F301*5 -> 120 | I301: =H301*E301 -> 600 | J301: =H301*5 -> 600 | K301: =J301*E301 -> 3000 | L301: =H301+20 -> 140 | M301: =L301*E301 -> 700 | N301: MJSK-17219
A302: 280 | B302: 120-SE | C302: CEMB-114 | D302: EMBROIDERY LACE | E302: 5 | F302: 24 | G302: =F302*E302 -> 120 | H302: =F302*5 -> 120 | I302: =H302*E302 -> 600 | J302: =H302*5 -> 600 | K302: =J302*E302 -> 3000 | L302: =H302+20 -> 140 | M302: =L302*E302 -> 700 | N302: GTX-S17100-1 RICAMIFICIO TEX
... A306: 284 | B306: 120-SE | C306: CEMB-118 | D306: EMBROIDERY LACE | E306: 5 | F306: 24 | G306: =F306*E306 -> 120 | H306: =F306*5 -> 120 | I306: =H306*E306 -> 600 | J306: =H306*5 -> 600 | K306: =J306*E306 -> 3000 | L306: =H306+20 -> 140 | M306: =L306*E306 -> 700 | N306: SBT-18
A307: 285 | B307: 120-SE | C307: CEMB-119 | D307: EMBROIDERY LACE | E307: 5 | F307: 24 | G307: =F307*E307 -> 120 | H307: =F307*5 -> 120 | I307: =H307*E307 -> 600 | J307: =H307*5 -> 600 | K307: =J307*E307 -> 3000 | L307: =H307+20 -> 140 | M307: =L307*E307 -> 700
A308: 286 | B308: 120-SE | C308: CEMB-120 | D308: EMBROIDERY LACE | E308: 5 | F308: 24 | G308: =F308*E308 -> 120 | H308: =F308*5 -> 120 | I308: =H308*E308 -> 600 | J308: =H308*5 -> 600 | K308: =J308*E308 -> 3000 | L308: =H308+20 -> 140 | M308: =L308*E308 -> 700 | N308: T1-17-PX16525 -F
A309: 287 | B309: 120-SE | C309: CEMB-121 | D309: EMBROIDERY LACE | E309: 5 | F309: 24 | G309: =F309*E309 -> 120 | H309: =F309*5 -> 120 | I309: =H309*E309 -> 600 | J309: =H309*5 -> 600 | K309: =J309*E309 -> 3000 | L309: =H309+20 -> 140 | M309: =L309*E309 -> 700 | N309: T1-17-PX16525 -C
A310: 288 | B310: 120-SE | C310: CEMB-123 | D310: EMBROIDERY LACE | E310: 5 | F310: 24 | G310: =F310*E310 -> 120 | H310: =F310*5 -> 120 | I310: =H310*E310 -> 600 | J310: =H310*5 -> 600 | K310: =J310*E310 -> 3000 | L310: =H310+20 -> 140 | M310: =L310*E310 -> 700 | N310: GTX-S17164-1 RICAMIFICIO TEX
A311: 289 | B311: 120-SE | C311: CEMB-124 | D311: EMBROIDERY LACE | E311: 5 | F311: 24 | G311: =F311*E311 -> 120 | H311: =F311*5 -> 120 | I311: =H311*E311 -> 600 | J311: =H311*5 -> 600 | K311: =J311*E311 -> 3000 | L311: =H311+20 -> 140 | M311: =L311*E311 -> 700 | N311: RGD-01
A312: 290 | B312: 120-SE | C312: CEMB-125 | D312: EMBROIDERY LACE | E312: 5 | F312: 24 | G312: =F312*E312 -> 120 | H312: =F312*5 -> 120 | I312: =H312*E312 -> 600 | J312: =H312*5 -> 600 | K312: =J312*E312 -> 3000 | L312: =H312+20 -> 140 | M312: =L312*E312 -> 700
A313: 291 | B313: 120-SE | C313: CEMB-126 | D313: EMBROIDERY LACE | E313: 7 | F313: 24 | G313: =F313*E313 -> 168 | H313: =F313*5 -> 120 | I313: =H313*E313 -> 840 | J313: =H313*5 -> 600 | K313: =J313*E313 -> 4200 | L313: =H313+20 -> 140 | M313: =L313*E313 -> 980 | N313: DESIGN - CITI-7
A314: 292 | B314: 120-SE | C314: CEMB-128 | D314: EMBROIDERY LACE | E314: 5 | F314: 24 | G314: =F314*E314 -> 120 | H314: =F314*5 -> 120 | I314: =H314*E314 -> 600 | J314: =H314*5 -> 600 | K314: =J314*E314 -> 3000 | L314: =H314+20 -> 140 | M314: =L314*E314 -> 700 | N314: SBT-25
A315: 293 | B315: 120-SE | C315: CEMB-129 | D315: EMBROIDERY LACE | E315: 5 | F315: 24 | G315: =F315*E315 -> 120 | H315: =F315*5 -> 120 | I315: =H315*E315 -> 600 | J315: =H315*5 -> 600 | K315: =J315*E315 -> 3000 | L315: =H315+20 -> 140 | M315: =L315*E315 -> 700 | N315: MJSK - 17121
A316: 294 | B316: 120-SE | C316: CEMB-130 | D316: EMBROIDERY LACE | E316: 5 | F316: 24 | G316: =F316*E316 -> 120 | H316: =F316*5 -> 120 | I316: =H316*E316 -> 600 | J316: =H316*5 -> 600 | K316: =J316*E316 -> 3000 | L316: =H316+20 -> 140 | M316: =L316*E316 -> 700 | N316: MJSK - 17136
A317: 295 | B317: 120-SE | C317: CEMB-131 | D317: EMBROIDERY LACE | E317: 5 | F317: 24 | G317: =F317*E317 -> 120 | H317: =F317*5 -> 120 | I317: =H317*E317 -> 600 | J317: =H317*5 -> 600 | K317: =J317*E317 -> 3000 | L317: =H317+20 -> 140 | M317: =L317*E317 -> 700 | N317: MJSK - 17205
A318: 296 | B318: 120-SE | C318: CEMB-133 | D318: EMBROIDERY LACE | E318: 5 | F318: 24 | G318: =F318*E318 -> 120 | H318: =F318*5 -> 120 | I318: =H318*E318 -> 600 | J318: =H318*5 -> 600 | K318: =J318*E318 -> 3000 | L318: =H318+20 -> 140 | M318: =L318*E318 -> 700 | N318: MJSK - 17172
A319: 297 | B319: 120-SE | C319: CEMB-134 | D319: EMBROIDERY LACE | E319: 5 | F319: 24 | G319: =F319*E319 -> 120 | H319: =F319*5 -> 120 | I319: =H319*E319 -> 600 | J319: =H319*5 -> 600 | K319: =J319*E319 -> 3000 | L319: =H319+20 -> 140 | M319: =L319*E319 -> 700 | N319: KS - 2703
...

Sheet CEMB - PENDING
A1: UPDATED ON | F1: UPDATED BY IBRAHIM
A2: DESCRIPTION 31 OCT 2024 | D2: PIECES | F2: VIP-M | I2: NOTED: FOR THE PENDING PCIECES PLEASE CHECK INVIOCE FOR THE GIVEN PRICES
A3: TOTAL | D3: 1058 | F3: Sherry - S | H3: PENDING-P
F4: Angie - A
A5: PENDING | F5: Fong king - FK | I5: Total Cost | K5: =#REF!+#REF!+#REF!+#REF!+#REF!+#REF!+#REF!+#REF!+#REF!+#REF!+#REF!+#REF!+#REF!+#REF!+#REF!+#REF!+#REF! -> #REF!
A6: SOLD | F6: Bani -B
A7: AVAILABLE | D7: =D3-(D4+D5+D6) -> 1058 | F7: MR. Cetin- C
F8: MS. KLARA-K
A11: CEMB 40 PENDING
A12: NO | B12: DESIGN | C12: ARTICLE | D12: QUALITY | E12: QTY | F12: COST PER MT EURO | G12: COST PER MT RM | H12: COST PIECE RM | I12: V.I.P PER MT RM | J12: V.I.P PIECE RM | K12: SELLING PER MT RM | L12: SELLING PIECE RM | M12: SOLD TO
A13: 1 | G13: =F13*5 -> 0 | H13: =G13*E13 -> 0 | I13: =G13*5 -> 0 | J13: =I13*E13 -> 0 | K13: =I13/2 -> 0 | L13: =K13*E13 -> 0
A14: 2 | G14: =F14*5 -> 0 | H14: =G14*E14 -> 0 | I14: =G14*5 -> 0 | J14: =I14*E14 -> 0 | K14: =I14/2 -> 0 | L14: =K14*E14 -> 0
A15: 3 | G15: =F15*5 -> 0 | H15: =G15*E15 -> 0 | I15: =G15*5 -> 0 | J15: =I15*E15 -> 0 | K15: =I15/2 -> 0 | L15: =K15*E15 -> 0
A16: 4 | G16: =F16*5 -> 0 | H16: =G16*E16 -> 0 | I16: =G16*5 -> 0 | J16: =I16*E16 -> 0 | K16: =I16/2 -> 0 | L16: =K16*E16 -> 0
A17: 5 | G17: =F17*5 -> 0 | H17: =G17*E17 -> 0 | I17: =G17*5 -> 0 | J17: =I17*E17 -> 0 | K17: =I17/2 -> 0 | L17: =K17*E17 -> 0
A18: TOTAL COST | C18: {=COUNTA(C13:INDEX(C:C,ROW()-1))} -> 0 | E18: =SUM(Table129[]) -> 0 | H18: =SUM(Table127[]) -> 0
A24: CEMB 60 PENDING
A25: NO | B25: DESIGN | C25: ARTICLE | D25: QUALITY | E25: QTY | F25: COST PER MT EURO | G25: COST PER MT RM | H25: COST PIECE RM | I25: V.I.P PER MT RM | J25: V.I.P PIECE RM | K25: SELLING PER MT RM | L25: SELLING PIECE RM | M25: SOLD TO
A26: 1 | G26: =F26*5 -> 0 | H26: =G26*E26 -> 0 | I26: =G26*5 -> 0 | J26: =I26*E26 -> 0 | K26: =I26/2 -> 0 | L26: =K26*E26 -> 0
A27: 2 | G27: =F27*5 -> 0 | H27: =G27*E27 -> 0 | I27: =G27*5 -> 0 | J27: =I27*E27 -> 0 | K27: =I27/2 -> 0 | L27: =K27*E27 -> 0
A28: 3 | G28: =F28*5 -> 0 | H28: =G28*E28 -> 0 | I28: =G28*5 -> 0 | J28: =I28*E28 -> 0 | K28: =I28/2 -> 0 | L28: =K28*E28 -> 0
A29: 4 | G29: =F29*5 -> 0 | H29: =G29*E29 -> 0 | I29: =G29*5 -> 0 | J29: =I29*E29 -> 0 | K29: =I29/2 -> 0 | L29: =K29*E29 -> 0
A30: 5 | G30: =F30*5 -> 0 | H30: =G30*E30 -> 0 | I30: =G30*5 -> 0 | J30: =I30*E30 -> 0 | K30: =I30/2 -> 0 | L30: =K30*E30 -> 0
A31: TOTAL COST | C31: {=COUNTA(C26:INDEX(C:C,ROW()-1))} -> 0 | E31: =SUM(Table134[]) -> 0 | H31: =SUM(Table130[]) -> 0
A36: CEMB 120 PENDING
A37: NO | B37: DESIGN | C37: ARTICLE | D37: QUALITY | E37: QTY | F37: COST PER MT EURO | G37: COST PER MT RM | H37: COST PIECE RM | I37: V.I.P PER MT RM | J37: V.I.P PIECE RM | K37: SELLING PER MT RM | L37: SELLING PIECE RM | M37: SOLD TO
A38: 1 | G38: =F38*5 -> 0 | H38: =G38*E38 -> 0 | I38: =G38*5 -> 0 | J38: =I38*E38 -> 0 | K38: =I38/2 -> 0 | L38: =K38*E38 -> 0
A39: 2 | G39: =F39*5 -> 0 | H39: =G39*E39 -> 0 | I39: =G39*5 -> 0 | J39: =I39*E39 -> 0 | K39: =I39/2 -> 0 | L39: =K39*E39 -> 0
A40: 3 | G40: =F40*5 -> 0 | H40: =G40*E40 -> 0 | I40: =G40*5 -> 0 | J40: =I40*E40 -> 0 | K40: =I40/2 -> 0 | L40: =K40*E40 -> 0
A41: 4 | G41: =F41*5 -> 0 | H41: =G41*E41 -> 0 | I41: =G41*5 -> 0 | J41: =I41*E41 -> 0 | K41: =I41/2 -> 0 | L41: =K41*E41 -> 0
A42: 5 | G42: =F42*5 -> 0 | H42: =G42*E42 -> 0 | I42: =G42*5 -> 0 | J42: =I42*E42 -> 0 | K42: =I42/2 -> 0 | L42: =K42*E42 -> 0
A43: TOTAL COST | C43: {=COUNTA(C38:INDEX(C:C,ROW()-1))} -> 0 | E43: =SUM(Table133[]) -> 0 | H43: =SUM(Table137[]) -> 0
A48: CEMB 180 PENDING
A49: NO | B49: DESIGN | C49: ARTICLE | D49: QUALITY | E49: QTY | F49: COST PER MT EURO | G49: COST PER MT RM | H49: COST PIECE RM | I49: V.I.P PER MT RM | J49: V.I.P PIECE RM | K49: SELLING PER MT RM | L49: SELLING PIECE RM | M49: SOLD TO
A50: 1 | G50: =F50*5 -> 0 | H50: =G50*E50 -> 0 | I50: =G50*5 -> 0 | J50: =I50*E50 -> 0 | K50: =I50/2 -> 0 | L50: =K50*E50 -> 0
A51: 2 | G51: =F51*5 -> 0 | H51: =G51*E51 -> 0 | I51: =G51*5 -> 0 | J51: =I51*E51 -> 0 | K51: =I51/2 -> 0 | L51: =K51*E51 -> 0
A52: 3 | G52: =F52*5 -> 0 | H52: =G52*E52 -> 0 | I52: =G52*5 -> 0 | J52: =I52*E52 -> 0 | K52: =I52/2 -> 0 | L52: =K52*E52 -> 0
A53: 4 | G53: =F53*5 -> 0 | H53: =G53*E53 -> 0 | I53: =G53*5 -> 0 | J53: =I53*E53 -> 0 | K53: =I53/2 -> 0 | L53: =K53*E53 -> 0
A54: 5 | G54: =F54*5 -> 0 | H54: =G54*E54 -> 0 | I54: =G54*5 -> 0 | J54: =I54*E54 -> 0 | K54: =I54/2 -> 0 | L54: =K54*E54 -> 0
A55: TOTAL COST | C55: {=COUNTA(C50:INDEX(C:C,ROW()-1))} -> 0 | E55: =SUM(Table135[]) -> 0 | H55: =SUM(Table138[]) -> 0

Sheet CEMB - SOLD
A1: UPDATED ON | F1: UPDATED BY IBRAHIM
A2: DESCRIPTION 31 OCT 2024 | D2: PIECES | F2: VIP-M
F3: Sherry - S | H3: PENDING-P
F4: Angie - A
F5: Fong king - FK | I5: Total Cost
F6: Bani -B
E7: =COUNTIF('SILK - PENDING'!D14:D17,"*cdc*") -> 2 | F7: MR. Cetin- C
F8: MS. KLARA-K
A13: SOLD CEMB - 40
A15: NO | B15: DESIGN | C15: ARTICLE | D15: QUALITY | E15: QTY | F15: PRICE PER MT | G15: PRICE PER PIECE | H15: NET PRICE AFTER DISC | I15: COMMI % | J15: LESS COMMI PER PC | K15: COST PER PC | L15: NET PROFIT PER PC | M15: SOLD TO
A16: 1 | B16: 40 - SE | C16: CEMB-371 | D16: ROYAL BLUE | E16: 3.6 | F16: 68 | G16: 244.8 | H16: 244.8 | I16: 0.1 | J16: 220.32 | K16: 126 | L16: 94.32 | M16: A
A17: 2 | B17: 40 - SE | C17: CEMB - 373 | D17: LIGHT PINK | E17: 3.35 | F17: Ms Rani | I17: 0 | J17: 0 | K17: 35 | L17: -35 | M17: R
A18: 3 | B18: 40 - SE | C18: CEMB - 382 | D18: RED | E18: 3.5 | F18: Ms Rani | I18: 0 | J18: 0 | K18: 35 | L18: -35 | M18: R
A19: 4 | B19: 40 - SE | C19: CEMB - 387 | D19: GREEN | E19: 4.5 | I19: 0 | J19: 0 | K19: 35 | L19: -35
A20: 5 | B20: 40 - SE | C20: CEMB - 342 | D20: PINK | E20: 5 | F20: Ms Rani | I20: 0 | J20: 0 | K20: 35 | L20: -35
A21: 6 | B21: 40 - SE | C21: CEMB - 464 | D21: RED | E21: 3.5 | F21: Ms Rani | I21: 0 | J21: 0 | K21: 35 | L21: -35
B22: TOTAL | C22: {=COUNTA(C16:INDEX(C:C,ROW()-1))} -> 6 | E22: =SUM(Table120[QTY]) -> 23.45 | K22: =SUM(Table121[]) -> 301 | L22: =SUM(L16:L21) -> -80.68
A26: SOLD CEMB - 60
A28: NO | B28: DESIGN | C28: ARTICLE | D28: QUALITY | E28: QTY | F28: PRICE PER MT | G28: PRICE PER PIECE | H28: NET PRICE AFTER DISCOUNT | I28: COMMI % | J28: LESS COMM PER PC | K28: COST PER PC | L28: NET PROFIT PER PC | M28: SOLD TO
A29: 7 | B29: 60-SE | C29: CEMB-16 | D29: EMBROIDERY SOFT TULLE | E29: 5 | F29: 60 | G29: =E29*F29 -> 300 | H29: =G29 -> 300 | I29: 0 | J29: 300 | K29: 300 | L29: =J29-K29 -> 0 | M29: CASH
A30: 8 | B30: 60-SE | C30: CEMB-20 | D30: EMBROIDERY SOFT TULLE | E30: 5 | F30: 60 | G30: =E30*F30 -> 300 | H30: =G30 -> 300 | I30: 0 | J30: 300 | K30: 300 | L30: =J30-K30 -> 0 | M30: CASH
A31: 9 | B31: 60-SE | C31: CEMB-56 | D31: EMBROIDERY SOFT TULLE | E31: 5 | F31: 60 | G31: =E31*F31 -> 300 | H31: =G31 -> 300 | I31: 0 | J31: 300 | K31: 300 | L31: =J31-K31 -> 0 | M31: CASH
A32: 10 | B32: 60-SE | C32: CEMB-57 | D32: EMBROIDERY SOFT TULLE | E32: 5 | F32: 60 | G32: =E32*F32 -> 300 | H32: =G32 -> 300 | I32: 0 | J32: 300 | K32: 300 | L32: =J32-K32 -> 0 | M32: CASH
A33: 11 | B33: 60-SC | C33: CEMB ( SST 9) | D33: 3D-EMBROIDERY | E33: 5 | F33: 60 | G33: 350 | H33: =G33 -> 350 | I33: 0 | J33: 350 | K33: 300 | L33: =J33-K33 -> 50 | M33: CASH
A34: 12 | B34: 60-SC | C34: CEMB 13 | D34: 3D-EMBROIDERY | E34: 4.5 | F34: 90 | G34: =E34*F34 -> 405 | H34: 400 | I34: 0 | J34: 400 | K34: 300 | L34: =J34-K34 -> 100 | M34: CASH
A35: 13 | B35: 60-SC | C35: CEMB 15 | D35: 3D-EMBROIDERY | E35: 5 | F35: 99 | G35: 495 | H35: 495 | I35: 0.1 | J35: 445.5 | K35: 300 | L35: 145.5 | M35: A
A36: 14 | B36: 60-SC | C36: CEMB 18 | D36: 3D-EMBROIDERY | E36: 5 | F36: 99 | G36: 495 | H36: 495 | I36: 0.1 | J36: 445.5 | K36: 300 | L36: 145.5 | M36: A
A37: 15 | B37: 60-SC | C37: CEMB 43 | D37: 3D-EMBROIDERY | E37: 5 | F37: 150 | G37: 750 | H37: 637.5 | I37: 0 | J37: =H37*(1-I37) -> 637.5 | K37: 300 | L37: =J37-K37 -> 337.5 | M37: S
A38: 16 | B38: 60-SC | C38: CEMB 6 | D38: 3D-EMBROIDERY | E38: 7 | F38: 150 | G38: 1050 | H38: 892.5 | I38: 0 | J38: 892.5 | K38: 420 | L38: 472.5 | M38: S
A39: 17 | B39: 60-SC | C39: CEMB 7 | D39: 3D-EMBROIDERY | E39: 7 | F39: 150 | G39: 1050 | H39: 892.5 | I39: 0 | J39: 892.5 | K39: 420 | L39: 472.5 | M39: S
A40: 18 | B40: 60-SC | C40: CEMB 33 | D40: 3D-EMBROIDERY | E40: 5 | F40: 150 | G40: 750 | H40: 637.5 | I40: 0 | J40: 637.5 | K40: 300 | L40: 337.5 | M40: S
A41: 19 | B41: 60-SC | C41: CEMB 40 | D41: 3D-EMBROIDERY | E41: 5 | F41: 150 | G41: 750 | H41: 637.5 | I41: 0 | J41: 637.5 | K41: 300 | L41: 337.5 | M41: S
A42: 20 | B42: 60-SC | C42: CEMB 44 | D42: 3D-EMBROIDERY | E42: 5 | F42: 150 | G42: 750 | H42: 637.5 | I42: 0 | J42: 637.5 | K42: 300 | L42: 337.5 | M42: S
B43: TOTAL | C43: {=COUNTA(C29:INDEX(C:C,ROW()-1))} -> 14 | E43: =SUM(Table123[]) -> 73.5 | H43: =SUM(H26:H42) -> 7275 | K43: =SUM(Table126[COST PER PC]) -> 4440 | L43: =SUM(L29:L42) -> 2736
A46: SOLD CEMB-120
A48: NO | B48: DESIGN | C48: ARTICLE | D48: QUALITY | E48: QTY | F48: PRICE PER MT | G48: PRICE PER PIECE | H48: NET PRICE AFTER DISCOUNT | I48: COMMI % | J48: LESS COMM PER PC | K48: COST PER PC | L48: NET PROFIT PER PC | M48: SOLD TO
A49: 21 | B49: 120-SE | C49: CEMB-127 | D49: EMBROIDERY LACE | E49: 7 | F49: 157 | G49: 1099 | H49: 1099 | I49: 0.1 | J49: 989.1 | K49: 840 | L49: 149.1 | M49: A
A50: 22 | B50: 120-SE | C50: CEMB-132 | D50: EMBROIDERY LACE | E50: 5 | F50: 157 | G50: 785 | H50: 785 | I50: 0.1 | J50: 706.5 | K50: 600 | L50: 106.5 | M50: A
A51: 23 | B51: 120-SE | C51: CEMB-148 | D51: EMBROIDERY SOFT TULLE | E51: 4 | F51: 157 | G51: 628 | H51: 628 | I51: 0.1 | J51: 565.2 | K51: 220 | L51: 345.2 | M51: A
A52: 24 | B52: 120-SE | C52: CEMB-106 | D52: EMBROIDERY LACE | E52: 7 | F52: 300 | G52: 2100 | H52: 1785 | I52: 0 | J52: 1785 | K52: 840 | L52: 945 | M52: S
A53: 25 | B53: 120-SE | C53: CEMB-112 | D53: EMBROIDERY LACE | E53: 5 | F53: 300 | G53: 1500 | H53: 1275 | I53: 0 | J53: 1275 | K53: 600 | L53: 675 | M53: S
A54: 26 | B54: 120-SE | C54: CEMB-110 | D54: EMBROIDERY LACE | E54: 8 | F54: 300 | G54: 2400 | H54: 2040 | I54: 0 | J54: 2040 | K54: 960 | L54: 1080 | M54: S
A55: 27 | B55: 120-SE | C55: CEMB-122 | D55: EMBROIDERY LACE | E55: 5 | F55: 300 | G55: 1500 | H55: 1275 | I55: 0 | J55: 1275 | K55: 600 | L55: 675 | M55: S
B56: TOTAL | C56: {=COUNTA(C49:INDEX(C:C,ROW()-1))} -> 7 | E56: =SUM(Table124[]) -> 41 | H56: =SUM(H46:H51) -> 2512 | K56: =SUM(Table125[COST PER PC]) -> 4660 | L56: =SUM(L49:L55) -> 3975.8
A59: SOLD CEMB-180
A61: NO | B61: DESIGN | C61: ARTICLE | D61: QUALITY | E61: QTY | F61: PRICE PER MT | G61: PRICE PER PIECE | H61: NET PRICE AFTER DISCOUNT | I61: COMMI % | J61: LESS COMM PER PC | K61: COST PER PC | L61: NET PROFIT PER PC | M61: SOLD TO
A62: 28 | B62: 180-SE B | C62: CEMB - 203 | D62: EMBROIDERY LACE | E62: 4.9 | F62: 450 | G62: 2205 | H62: 1874.25 | I62: 0 | J62: 1874.25 | K62: 882 | L62: 992.25 | M62: S
A63: 29 | B63: 180-SE | C63: CEMB - 225 | D63: EMBROIDERY LACE | E63: 5 | F63: 450 | G63: 2250 | H63: 1912.5 | I63: 0 | J63: 1912.5 | K63: 900 | L63: 1012.5 | M63: S
A64: 30 | B64: 180-SE | C64: CEMB - 227 | D64: EMBROIDERY LACE | E64: 4 | F64: 450 | G64: 1800 | H64: 1530 | I64: 0 | J64: 1530 | K64: 720 | L64: 810 | M64: S
A65: 31 | B65: 180-SE | C65: CEMB - 230 | D65: EMBROIDERY LACE | E65: 5 | F65: 450 | G65: 2250 | H65: 1912.5 | I65: 0 | J65: 1912.5 | K65: 900 | L65: 1012.5 | M65: S
A66: 32 | B66: 180-SE | C66: CEMB - 231 | D66: EMBROIDERY LACE | E66: 5 | F66: 450 | G66: 2250 | H66: 1912.5 | I66: 0 | J66: 1912.5 | K66: 900 | L66: 1012.5 | M66: S
B68: TOTAL | C68: {=COUNTA(C62:INDEX(C:C,ROW()-1))} -> 5 | E68: =SUM(Table140[]) -> 23.9 | H68: =SUM(H59:H67) -> 9141.75 | K68: =SUM(Table141[COST PER PC]) -> 4302 | L68: =SUM(L62:L67) -> 4839.75

Sheet EMBROIDERY - STOCK OVERVIEW 
A1: ITEM | B1: TOTAL BOXES | C1: BOXES SOLD | D1: TOTAL BOXES IN OFFICE | E1: BOXES AVAILABLE | F1: BOXES PENDING | G1: TOTAL METERS | H1: TOTAL METERS IN OFFICE | I1: TOTAL METERS IN SOLD | J1: TOTAL METERS PENDING | K1: TOTAL VALUE MYR | L1: TOTAL VALUE IN OFFICE MYR | M1: TOTAL VALUE OF SOLD | N1: TOTAL VALUE OF PENDING
A2: EMBROIDERY
A3: ARGOMENTI (ARGO) | B3: 10 | C3: ='EMBROIDERY - SOLD'!C16 -> 0 | D3: =B3-C3-F3 -> 10 | E3: =D3+F3 -> 10 | K3: 15672.5 | L3: ='EMBROIDERY - ALL'!I25 -> 15672.5 | M3: ='EMBROIDERY - SOLD'!K16 -> 0
A4: RICAMIFICIO PAOLO (RIC-P) | B4: 5 | C4: ='EMBROIDERY - SOLD'!C23 -> 2 | D4: =B4-C4-F4 -> 3 | E4: =D4+F4 -> 3 | K4: 35185 | L4: ='EMBROIDERY - ALL'!I34 -> 22855 | M4: ='EMBROIDERY - SOLD'!K23 -> 12330
A5: HOFERHECHT (HOFE) | B5: 5 | C5: ='EMBROIDERY - SOLD'!C32 -> 0 | D5: =B5-C5-F5 -> 5 | E5: =D5+F5 -> 5 | K5: 18920 | L5: ='EMBROIDERY - ALL'!I45 -> 18920 | M5: ='EMBROIDERY - SOLD'!J32 -> 0
A6: ALDOBIANCHI (ALDO) | B6: 13 | C6: ='EMBROIDERY - SOLD'!C41 -> 1 | D6: =B6-C6-F6 -> 12 | E6: =D6+F6 -> 12 | K6: 112605 | L6: ='EMBROIDERY - ALL'!I63 -> 103903 | M6: ='EMBROIDERY - SOLD'!J41 -> 5725
A7: RICAMIFICIO GUEGAIN (RIC-G) | B7: 11 | C7: ='EMBROIDERY - SOLD'!C50 -> 3 | D7: =B7-C7-F7 -> 8 | E7: =D7+F7 -> 8 | K7: 29217.5 | L7: ='EMBROIDERY - ALL'!I77 -> 21279.5 | M7: ='EMBROIDERY - SOLD'!J50 -> 7938
A8: QUORUM (QUO) | B8: 6 | C8: ='EMBROIDERY - SOLD'!C59 -> 0 | D8: =B8-C8-F8 -> 6 | E8: =D8+F8 -> 6 | K8: 5700 | L8: ='EMBROIDERY - ALL'!I89 -> 5700 | M8: ='EMBROIDERY - SOLD'!J59 -> 0
A9: RICAMIFICIO BRAGA & ASPESI (ASPE) | B9: 4 | C9: ='EMBROIDERY - SOLD'!C68 -> 0 | D9: =B9-C9-F9 -> 4 | E9: =D9+F9 -> 4 | K9: 10080 | L9: ='EMBROIDERY - ALL'!I99 -> 10080 | M9: ='EMBROIDERY - SOLD'!J68 -> 0
A10: RICAMIFICIO CANDELLI (CAND) | B10: 15 | C10: ='EMBROIDERY - SOLD'!C77 -> 0 | D10: =B10-C10-F10 -> 15 | E10: =D10+F10 -> 15 | K10: 26207 | L10: ='EMBROIDERY - ALL'!I120 -> 26207 | M10: ='EMBROIDERY - SOLD'!J77 -> 0
A11: UNICRAFT (UNI) | B11: 16 | C11: ='EMBROIDERY - SOLD'!C86 -> 0 | D11: =B11-C11-F11 -> 16 | E11: =D11+F11 -> 16 | K11: 15503.5 | L11: ='EMBROIDERY - ALL'!I142 -> 15503.5 | M11: ='EMBROIDERY - SOLD'!J86 -> 0
A12: OKU TEX AG (OKU) | B12: 12 | C12: ='EMBROIDERY - SOLD'!C95 -> 0 | D12: =B12-C12-F12 -> 12 | E12: =D12+F12 -> 12 | K12: 73370 | L12: ='EMBROIDERY - ALL'!I160 -> 73370 | M12: ='EMBROIDERY - SOLD'!J95 -> 0
A13: RICAMIFICIO GIMAR (RIC-GIM) | B13: 44 | C13: ='EMBROIDERY - SOLD'!C103 -> 0 | D13: =B13-C13-F13 -> 44 | E13: =D13+F13 -> 44 | K13: 98559 | L13: ='EMBROIDERY - ALL'!I210 -> 98559 | M13: ='EMBROIDERY - SOLD'!J103 -> 0
A14: DISENO & ELIESAAB (DIS) | B14: 9 | C14: ='EMBROIDERY - SOLD'!C111 -> 0 | D14: =B14-C14-F14 -> 9 | E14: =D14+F14 -> 9 | K14: 44475 | L14: ='EMBROIDERY - ALL'!I225 -> 44475 | M14: ='EMBROIDERY - SOLD'!J111 -> 0
A15: RICAMIFICIO BRAGA (R-BR) | B15: 14 | C15: ='EMBROIDERY - SOLD'!C120 -> 0 | D15: =B15-C15-F15 -> 14 | E15: =D15+F15 -> 14 | K15: 25584 | L15: ='EMBROIDERY - ALL'!I245 -> 25584 | M15: ='EMBROIDERY - SOLD'!J120 -> 0
A16: VEMA (VEM) | B16: 23 | C16: ='EMBROIDERY - SOLD'!C129 -> 0 | D16: =B16-C16-F16 -> 23 | E16: =D16+F16 -> 23 | K16: 104627.5 | L16: ='EMBROIDERY - ALL'!I274 -> 104627.5 | M16: ='EMBROIDERY - SOLD'!J129 -> 0
A17: TGM EMBROIDERY BORDER (TGM-B) | B17: 13 | C17: ='EMBROIDERY - SOLD'!C139 -> 0 | D17: =B17-C17-F17 -> 13 | E17: =D17+F17 -> 13 | K17: 38585 | L17: ='EMBROIDERY - ALL'!I293 -> 38585 | M17: ='EMBROIDERY - SOLD'!J139 -> 0
A18: MURARAKA (MURA) | B18: 6 | C18: ='EMBROIDERY - SOLD'!C148 -> 0 | D18: =B18-C18-F18 -> 6 | E18: =D18+F18 -> 6 | K18: 6000 | L18: ='EMBROIDERY - ALL'!I305 -> 6000 | M18: ='EMBROIDERY - SOLD'!J148 -> 0
A19: LAGATOLA (LAGA) | B19: 7 | C19: ='EMBROIDERY - SOLD'!C157 -> 0 | D19: =B19-C19-F19 -> 7 | E19: =D19+F19 -> 7 | K19: 37700.5 | L19: ='EMBROIDERY - ALL'!I317 -> 37700.5 | M19: ='EMBROIDERY - SOLD'!J157 -> 0
A20: CASA DELLO (CASA) | B20: 14 | C20: ='EMBROIDERY - SOLD'!C167 -> 0 | D20: =B20-C20-F20 -> 14 | E20: =D20+F20 -> 14 | K20: 10692.5 | L20: ='EMBROIDERY - ALL'!I337 -> 10692.5 | M20: ='EMBROIDERY - SOLD'!J167 -> 0
A21: SHAGUN (SHA) | B21: 3 | C21: ='EMBROIDERY - SOLD'!C176 -> 0 | D21: =B21-C21-F21 -> 3 | E21: =D21+F21 -> 3 | K21: 6710 | L21: ='EMBROIDERY - ALL'!I346 -> 6710 | M21: ='EMBROIDERY - SOLD'!J176 -> 0
A22: SOLSTISS (SID) | B22: 10 | C22: ='EMBROIDERY - SOLD'!C185 -> 0 | D22: =B22-C22-F22 -> 10 | E22: =D22+F22 -> 10 | K22: 42090 | L22: ='EMBROIDERY - ALL'!I362 -> 42090 | M22: ='EMBROIDERY - SOLD'!J185 -> 0
A23: SOLSTISS (ORIGINAL) | B23: 10 | C23: ='EMBROIDERY - SOLD'!C194 -> 1 | D23: =B23-C23-F23 -> 9 | E23: =D23+F23 -> 9 | K23: 39892.5 | L23: ='EMBROIDERY - ALL'!I377 -> 34012.5 | M23: ='EMBROIDERY - SOLD'!J194 -> 5880
A24: TGM SILK (TGM) | B24: 8 | C24: ='EMBROIDERY - SOLD'!C203 -> 0 | D24: =B24-C24-F24 -> 8 | E24: =D24+F24 -> 8 | K24: 24500 | L24: ='EMBROIDERY - ALL'!I391 -> 24500 | M24: ='EMBROIDERY - SOLD'!J203 -> 0
A25: TGM WITH BORDER | B25: 7 | C25: ='EMBROIDERY - SOLD'!C212 -> 0 | D25: =B25-C25-F25 -> 7 | E25: =D25+F25 -> 7 | K25: 28505 | L25: ='EMBROIDERY - ALL'!I404 -> 28505 | M25: ='EMBROIDERY - SOLD'!J212 -> 0
A26: NEC EMBROIDERY (NEC) | B26: 5 | C26: ='EMBROIDERY - SOLD'!C222 -> 0 | D26: =B26-C26-F26 -> 5 | E26: =D26+F26 -> 5 | K26: 11250 | L26: ='EMBROIDERY - ALL'!I415 -> 11250 | M26: ='EMBROIDERY - SOLD'!J222 -> 0
A27: RUFFO COLI (RUFF) | B27: 3 | C27: ='EMBROIDERY - SOLD'!C231 -> 0 | D27: =B27-C27-F27 -> 3 | E27: =D27+F27 -> 3 | K27: 7425 | L27: ='EMBROIDERY - ALL'!I424 -> 7425 | M27: ='EMBROIDERY - SOLD'!J231 -> 0
